Workbook

Sheet PEDIDO
I2: NUMERO DO PEDIDO | N2: 500 | W2: COMPRADOR | AK2: DATA | AN2: =TODAY() -> 46057
I3: MARCA | W3: REPRESENTANTE | AK3: TEL.
I4: FORNECEDOR | W4: EMAIL | AK4: FRETE | AN4: CIF
I5: PRAZO DE PAG. | N5: 90 | Q5: 120 | T5: 150 | W5: FATURAMENTO | AF5: LIMITE | AK5: CREDITO | AN5: SIM
I6: VENC. DUPLICATAS | N6: =N5+AA5 -> 90 | Q6: =Q5+AA5 -> 120 | T6: =T5+AA5 -> 150 | W6: DESCONTO: | AD6: MARKUP:
I8: OBSERVAÇÕES: | M8: CASO HAJA DIVERGÊNCIAS, ERROS OU ALTERAÇÕES , DEVEM SER APRESENTADOS EM ATÉ 7 DIAS APÓS A DATA DE ENVIO DO PEDIDO *
I9: TODAS AS REFERENCIAS DEVEM CONSTAR NA NOTA FISCAL DA MESMA FORMA QUE CONSTA NO PEDIDO * SUJEITO A DEVOLUÇÃO NO ATO DA
I10: ENTREGA EM CASO DE DIVERGÊNCIA
B13: GRADE | D13: UN | E13: P | F13: M | G13: G | H13: GG | I13: 16 | J13: 17 | K13: 18 | L13: 19 | M13: 20 | N13: 21 | O13: 22 | P13: 23 | Q13: 24 | R13: 25 | S13: 26 | T13: 27 | U13: 28 | V13: 29 | W13: 30 | X13: 31 | Y13: 32 | Z13: 33 | AA13: 34 | AB13: 35 | AC13: 36 | AD13: 37 | AE13: 38 | AF13: 39 | AG13: 40 | AH13: 41 | AI13: 42 | AJ13: 43 | AK13: 44 | AL13: 45 | AM13: 46 | AN13: 47 | AO13: 48 | AP13: TOTAL
B14: A | AP14: =SUM(D14:AO14) -> 0 | AY14: =IF(COUNTA(PEDIDO!$I$14:$AO$21)>0,"NUMERICO","")
B15: B | AP15: =SUM(D15:AO15) -> 0 | AY15: =IF(COUNTA(PEDIDO!$D$14:$H$21)>0,"ALFANUMERICO","")
B16: C | AP16: =SUM(D16:AO16) -> 0
B17: D | AP17: =SUM(D17:AO17) -> 0
B18: E | AP18: =SUM(D18:AO18) -> 0
B19: F | AP19: =SUM(D19:AO19) -> 0
B20: G | AP20: =SUM(D20:AO20) -> 0
B21: H | AP21: =SUM(D21:AO21) -> 0 | BF21: 49
BF22: 70
B23: =W29 -> PEDIDO 1 | AP23: =COUNT(D23:AO23) -> 0 | BF23: 70
B24: =Z29 -> PEDIDO 2 | AP24: =COUNT(D24:AO24) -> 0 | BF24: 000
B25: =AC29 -> PEDIDO 3 | AP25: =COUNT(D25:AO25) -> 0
B26: =AF29 -> PEDIDO 4 | AP26: =COUNT(D26:AO26) -> 0 | BF26: UN
B27: =AI29 -> PEDIDO 5 | AP27: =COUNT(D27:AO27) -> 0 | BF27: 64042000
B28: N/C | D28: 2 | F28: 4 | G28: 5 | H28: 12 | I28: 13 | J28: 14 | K28: 19 | L28: 32 | M28: 33 | N28: 35 | O28: 37 | P28: 38 | Q28: 46 | R28: 47 | S28: 49 | T28: 51 | U28: 57 | V28: 74 | W28: 77 | X28: 79 | Y28: 81 | Z28: 83 | AA28: 84 | AB28: 85 | AC28: 87 | AD28: 90 | AE28: 91 | AF28: 92 | AG28: 93 | AH28: 94 | AI28: 97 | AJ28: 98 | AP28: =COUNT(D28:AO28) -> 32
B29: PEDIDOS | W29: PEDIDO 1 | Z29: PEDIDO 2 | AC29: PEDIDO 3 | AF29: PEDIDO 4 | AI29: PEDIDO 5 | AL29: TOTAL DE LOJAS | AP29: =SUM(AP23:AQ27) -> 0 | BF29: 2805900
B30: QUANTIDADES DE PARES / CAIXAS | W30: =SUM(W36:W164) -> 0 | Y30: =W30/12 -> 0 | Z30: =SUM(Z36:Z164) -> 0 | AB30: =Z30/12 -> 0 | AC30: =SUM(AC36:AC164) -> 0 | AE30: =AC30/12 -> 0 | AF30: =SUM(AF36:AF164) -> 0 | AH30: =AF30/12 -> 0 | AI30: =SUM(AI36:AI164) -> 0 | AK30: =AI30/12 -> 0 | AL30: TOTAL DE ÍTENS
B31: VALOR BRUTO | W31: =SUM(AS166) -> 0 | Z31: =SUM(AT166) -> 0 | AC31: =SUM(AU166) -> 0 | AF31: =SUM(AV166) -> 0 | AI31: =SUM(AW166) -> 0 | AL31: =(W30*AP23)+(Z30*AP24)+(AC30*AP25)+(AF30*AP27) -> 0
B32: VALOR LIQUIDO | W32: =W31-(W31*Z6) -> 0 | Z32: =Z31-(Z31*Z6) -> 0 | AC32: =AC31-(AC31*Z6) -> 0 | AF32: =AF31-(AF31*Z6) -> 0 | AI32: =AI31-(AI31*Z6) -> 0 | AY32: SUGESTÃO DE PREÇO (CUSTO - DESC * MKP)
B34: REFERÊNCIA | H34: TIPO | R34: COR 1 | S34: COR 2 | T34: COR 3 | U34: MODELO | W34: 1 | X34: GRADE | Z34: 2 | AA34: GRADE | AC34: 3 | AD34: GRADE | AF34: 4 | AG34: GRADE | AI34: 5 | AJ34: GRADE | AL34: CUSTO | AO34: VENDA | AS34: PEDIDO 1 | AT34: PEDIDO 2 | AU34: PEDIDO 3 | AV34: PEDIDO 4 | AW34: PEDIDO 5
B36: 1 | S36: =IF(R36<>"",R36,"") | T36: =IF(R36<>"",R36,"") | W36: =IFERROR(INDEX($AP$14:$AP$21,MATCH(X36,$B$14:$B$21,0)),"") | Z36: =IFERROR(INDEX($AP$14:$AP$21,MATCH(AA36,$B$14:$B$21,0)),"") | AC36: =IFERROR(INDEX($AP$14:$AP$21,MATCH(AD36,$B$14:$B$21,0)),"") | AF36: =IFERROR(INDEX($AP$14:$AP$21,MATCH(AG36,$B$14:$B$21,0)),"") | AI36: =IFERROR(INDEX($AP$14:$AP$21,MATCH(AJ36,$B$14:$B$21,0)),"") | AS36: =IF(OR(AL36="",W36=""),"",AL36*W36) | AT36: =IF(OR(AL36="",Z36=""),"",AL36*Z36) | AU36: =IF(OR(AL36="",AC36=""),"",AL36*AC36) | AV36: =IF(OR(AL36="",AF36=""),"",AL36*AF36) | AW36: =IF(OR(AL36="",AI36=""),"",AL36*AI36) | AX36: =IF(OR(AL36="",AI36=""),"",AL36*W36) | AY36: =(AL36-(AL36*$Z$6))*$AF$6 -> 0 | BC36: =(AL36-(AL36*$Z$6)) -> 0 | BE36: P
B37: 2 | S37: =IF(R37<>"",R37,"") | T37: =IF(R37<>"",R37,"") | W37: =IFERROR(INDEX($AP$14:$AP$21,MATCH(X37,$B$14:$B$21,0)),"") | Z37: =IFERROR(INDEX($AP$14:$AP$21,MATCH(AA37,$B$14:$B$21,0)),"") | AC37: =IFERROR(INDEX($AP$14:$AP$21,MATCH(AD37,$B$14:$B$21,0)),"") | AF37: =IFERROR(INDEX($AP$14:$AP$21,MATCH(AG37,$B$14:$B$21,0)),"") | AI37: =IFERROR(INDEX($AP$14:$AP$21,MATCH(AJ37,$B$14:$B$21,0)),"") | AR37: =AO37*AI6 -> 0 | AS37: =IF(OR(AL37="",W37=""),"",AL37*W37) | AT37: =IF(OR(AL37="",Z37=""),"",AL37*Z37) | AU37: =IF(OR(AL37="",AC37=""),"",AL37*AC37) | AV37: =IF(OR(AL37="",AF37=""),"",AL37*AF37) | AW37: =IF(OR(AL37="",AI37=""),"",AL37*AI37) | AX37: =IF(OR(AL37="",AI37=""),"",AL37*W37) | AY37: =(AL37-(AL37*$Z$6))*$AF$6 -> 0 | BC37: =(AL37-(AL37*$Z$6)) -> 0 | BE37: T
B38: 3 | S38: =IF(R38<>"",R38,"") | T38: =IF(R38<>"",R38,"") | W38: =IFERROR(INDEX($AP$14:$AP$21,MATCH(X38,$B$14:$B$21,0)),"") | Z38: =IFERROR(INDEX($AP$14:$AP$21,MATCH(AA38,$B$14:$B$21,0)),"") | AC38: =IFERROR(INDEX($AP$14:$AP$21,MATCH(AD38,$B$14:$B$21,0)),"") | AF38: =IFERROR(INDEX($AP$14:$AP$21,MATCH(AG38,$B$14:$B$21,0)),"") | AI38: =IFERROR(INDEX($AP$14:$AP$21,MATCH(AJ38,$B$14:$B$21,0)),"") | AS38: =IF(OR(AL38="",W38=""),"",AL38*W38) | AT38: =IF(OR(AL38="",Z38=""),"",AL38*Z38) | AU38: =IF(OR(AL38="",AC38=""),"",AL38*AC38) | AV38: =IF(OR(AL38="",AF38=""),"",AL38*AF38) | AW38: =IF(OR(AL38="",AI38=""),"",AL38*AI38) | AX38: =IF(OR(AL38="",AI38=""),"",AL38*W38) | AY38: =(AL38-(AL38*$Z$6))*$AF$6 -> 0 | BC38: =(AL38-(AL38*$Z$6)) -> 0 | CD38: ANABELA;
B39: 4 | S39: =IF(R39<>"",R39,"") | T39: =IF(R39<>"",R39,"") | W39: =IFERROR(INDEX($AP$14:$AP$21,MATCH(X39,$B$14:$B$21,0)),"") | Z39: =IFERROR(INDEX($AP$14:$AP$21,MATCH(AA39,$B$14:$B$21,0)),"") | AC39: =IFERROR(INDEX($AP$14:$AP$21,MATCH(AD39,$B$14:$B$21,0)),"") | AF39: =IFERROR(INDEX($AP$14:$AP$21,MATCH(AG39,$B$14:$B$21,0)),"") | AI39: =IFERROR(INDEX($AP$14:$AP$21,MATCH(AJ39,$B$14:$B$21,0)),"") | AS39: =IF(OR(AL39="",W39=""),"",AL39*W39) | AT39: =IF(OR(AL39="",Z39=""),"",AL39*Z39) | AU39: =IF(OR(AL39="",AC39=""),"",AL39*AC39) | AV39: =IF(OR(AL39="",AF39=""),"",AL39*AF39) | AW39: =IF(OR(AL39="",AI39=""),"",AL39*AI39) | AX39: =IF(OR(AL39="",AI39=""),"",AL39*W39) | AY39: =(AL39-(AL39*$Z$6))*$AF$6 -> 0 | BC39: =(AL39-(AL39*$Z$6)) -> 0 | CD39: ANABELA INFANTIL;
B40: 5 | S40: =IF(R40<>"",R40,"") | T40: =IF(R40<>"",R40,"") | W40: =IFERROR(INDEX($AP$14:$AP$21,MATCH(X40,$B$14:$B$21,0)),"") | Z40: =IFERROR(INDEX($AP$14:$AP$21,MATCH(AA40,$B$14:$B$21,0)),"") | AC40: =IFERROR(INDEX($AP$14:$AP$21,MATCH(AD40,$B$14:$B$21,0)),"") | AF40: =IFERROR(INDEX($AP$14:$AP$21,MATCH(AG40,$B$14:$B$21,0)),"") | AI40: =IFERROR(INDEX($AP$14:$AP$21,MATCH(AJ40,$B$14:$B$21,0)),"") | AS40: =IF(OR(AL40="",W40=""),"",AL40*W40) | AT40: =IF(OR(AL40="",Z40=""),"",AL40*Z40) | AU40: =IF(OR(AL40="",AC40=""),"",AL40*AC40) | AV40: =IF(OR(AL40="",AF40=""),"",AL40*AF40) | AW40: =IF(OR(AL40="",AI40=""),"",AL40*AI40) | AX40: =IF(OR(AL40="",AI40=""),"",AL40*W40) | AY40: =(AL40-(AL40*$Z$6))*$AF$6 -> 0 | BC40: =(AL40-(AL40*$Z$6)) -> 0 | CD40: ANEL;
B41: 6 | S41: =IF(R41<>"",R41,"") | T41: =IF(R41<>"",R41,"") | W41: =IFERROR(INDEX($AP$14:$AP$21,MATCH(X41,$B$14:$B$21,0)),"") | Z41: =IFERROR(INDEX($AP$14:$AP$21,MATCH(AA41,$B$14:$B$21,0)),"") | AC41: =IFERROR(INDEX($AP$14:$AP$21,MATCH(AD41,$B$14:$B$21,0)),"") | AF41: =IFERROR(INDEX($AP$14:$AP$21,MATCH(AG41,$B$14:$B$21,0)),"") | AI41: =IFERROR(INDEX($AP$14:$AP$21,MATCH(AJ41,$B$14:$B$21,0)),"") | AS41: =IF(OR(AL41="",W41=""),"",AL41*W41) | AT41: =IF(OR(AL41="",Z41=""),"",AL41*Z41) | AU41: =IF(OR(AL41="",AC41=""),"",AL41*AC41) | AV41: =IF(OR(AL41="",AF41=""),"",AL41*AF41) | AW41: =IF(OR(AL41="",AI41=""),"",AL41*AI41) | AX41: =IF(OR(AL41="",AI41=""),"",AL41*W41) | AY41: =(AL41-(AL41*$Z$6))*$AF$6 -> 0 | BC41: =(AL41-(AL41*$Z$6)) -> 0 | CD41: AROMATIZANTE;
B42: 7 | S42: =IF(R42<>"",R42,"") | T42: =IF(R42<>"",R42,"") | W42: =IFERROR(INDEX($AP$14:$AP$21,MATCH(X42,$B$14:$B$21,0)),"") | Z42: =IFERROR(INDEX($AP$14:$AP$21,MATCH(AA42,$B$14:$B$21,0)),"") | AC42: =IFERROR(INDEX($AP$14:$AP$21,MATCH(AD42,$B$14:$B$21,0)),"") | AF42: =IFERROR(INDEX($AP$14:$AP$21,MATCH(AG42,$B$14:$B$21,0)),"") | AI42: =IFERROR(INDEX($AP$14:$AP$21,MATCH(AJ42,$B$14:$B$21,0)),"") | AS42: =IF(OR(AL42="",W42=""),"",AL42*W42) | AT42: =IF(OR(AL42="",Z42=""),"",AL42*Z42) | AU42: =IF(OR(AL42="",AC42=""),"",AL42*AC42) | AV42: =IF(OR(AL42="",AF42=""),"",AL42*AF42) | AW42: =IF(OR(AL42="",AI42=""),"",AL42*AI42) | AX42: =IF(OR(AL42="",AI42=""),"",AL42*W42) | AY42: =(AL42-(AL42*$Z$6))*$AF$6 -> 0 | BC42: =(AL42-(AL42*$Z$6)) -> 0 | CD42: BABUCHE;
B43: 8 | S43: =IF(R43<>"",R43,"") | T43: =IF(R43<>"",R43,"") | W43: =IFERROR(INDEX($AP$14:$AP$21,MATCH(X43,$B$14:$B$21,0)),"") | Z43: =IFERROR(INDEX($AP$14:$AP$21,MATCH(AA43,$B$14:$B$21,0)),"") | AC43: =IFERROR(INDEX($AP$14:$AP$21,MATCH(AD43,$B$14:$B$21,0)),"") | AF43: =IFERROR(INDEX($AP$14:$AP$21,MATCH(AG43,$B$14:$B$21,0)),"") | AI43: =IFERROR(INDEX($AP$14:$AP$21,MATCH(AJ43,$B$14:$B$21,0)),"") | AS43: =IF(OR(AL43="",W43=""),"",AL43*W43) | AT43: =IF(OR(AL43="",Z43=""),"",AL43*Z43) | AU43: =IF(OR(AL43="",AC43=""),"",AL43*AC43) | AV43: =IF(OR(AL43="",AF43=""),"",AL43*AF43) | AW43: =IF(OR(AL43="",AI43=""),"",AL43*AI43) | AX43: =IF(OR(AL43="",AI43=""),"",AL43*W43) | AY43: =(AL43-(AL43*$Z$6))*$AF$6 -> 0 | BC43: =(AL43-(AL43*$Z$6)) -> 0 | CD43: BABUCHE FEMININO;
B44: 9 | S44: =IF(R44<>"",R44,"") | T44: =IF(R44<>"",R44,"") | W44: =IFERROR(INDEX($AP$14:$AP$21,MATCH(X44,$B$14:$B$21,0)),"") | Z44: =IFERROR(INDEX($AP$14:$AP$21,MATCH(AA44,$B$14:$B$21,0)),"") | AC44: =IFERROR(INDEX($AP$14:$AP$21,MATCH(AD44,$B$14:$B$21,0)),"") | AF44: =IFERROR(INDEX($AP$14:$AP$21,MATCH(AG44,$B$14:$B$21,0)),"") | AI44: =IFERROR(INDEX($AP$14:$AP$21,MATCH(AJ44,$B$14:$B$21,0)),"") | AS44: =IF(OR(AL44="",W44=""),"",AL44*W44) | AT44: =IF(OR(AL44="",Z44=""),"",AL44*Z44) | AU44: =IF(OR(AL44="",AC44=""),"",AL44*AC44) | AV44: =IF(OR(AL44="",AF44=""),"",AL44*AF44) | AW44: =IF(OR(AL44="",AI44=""),"",AL44*AI44) | AX44: =IF(OR(AL44="",AI44=""),"",AL44*W44) | AY44: =(AL44-(AL44*$Z$6))*$AF$6 -> 0 | BC44: =(AL44-(AL44*$Z$6)) -> 0 | CD44: BABUCHE INFANTIL;
B45: 10 | S45: =IF(R45<>"",R45,"") | T45: =IF(R45<>"",R45,"") | W45: =IFERROR(INDEX($AP$14:$AP$21,MATCH(X45,$B$14:$B$21,0)),"") | Z45: =IFERROR(INDEX($AP$14:$AP$21,MATCH(AA45,$B$14:$B$21,0)),"") | AC45: =IFERROR(INDEX($AP$14:$AP$21,MATCH(AD45,$B$14:$B$21,0)),"") | AF45: =IFERROR(INDEX($AP$14:$AP$21,MATCH(AG45,$B$14:$B$21,0)),"") | AI45: =IFERROR(INDEX($AP$14:$AP$21,MATCH(AJ45,$B$14:$B$21,0)),"") | AS45: =IF(OR(AL45="",W45=""),"",AL45*W45) | AT45: =IF(OR(AL45="",Z45=""),"",AL45*Z45) | AU45: =IF(OR(AL45="",AC45=""),"",AL45*AC45) | AV45: =IF(OR(AL45="",AF45=""),"",AL45*AF45) | AW45: =IF(OR(AL45="",AI45=""),"",AL45*AI45) | AX45: =IF(OR(AL45="",AI45=""),"",AL45*W45) | AY45: =(AL45-(AL45*$Z$6))*$AF$6 -> 0 | BC45: =(AL45-(AL45*$Z$6)) -> 0 | CD45: BABUCHE INFANTIL FEMININA;
B46: 11 | S46: =IF(R46<>"",R46,"") | T46: =IF(R46<>"",R46,"") | W46: =IFERROR(INDEX($AP$14:$AP$21,MATCH(X46,$B$14:$B$21,0)),"") | Z46: =IFERROR(INDEX($AP$14:$AP$21,MATCH(AA46,$B$14:$B$21,0)),"") | AC46: =IFERROR(INDEX($AP$14:$AP$21,MATCH(AD46,$B$14:$B$21,0)),"") | AF46: =IFERROR(INDEX($AP$14:$AP$21,MATCH(AG46,$B$14:$B$21,0)),"") | AI46: =IFERROR(INDEX($AP$14:$AP$21,MATCH(AJ46,$B$14:$B$21,0)),"") | AS46: =IF(OR(AL46="",W46=""),"",AL46*W46) | AT46: =IF(OR(AL46="",Z46=""),"",AL46*Z46) | AU46: =IF(OR(AL46="",AC46=""),"",AL46*AC46) | AV46: =IF(OR(AL46="",AF46=""),"",AL46*AF46) | AW46: =IF(OR(AL46="",AI46=""),"",AL46*AI46) | AX46: =IF(OR(AL46="",AI46=""),"",AL46*W46) | AY46: =(AL46-(AL46*$Z$6))*$AF$6 -> 0 | BC46: =(AL46-(AL46*$Z$6)) -> 0 | CD46: BABUCHE INFANTIL MASCULINO;
B47: 12 | S47: =IF(R47<>"",R47,"") | T47: =IF(R47<>"",R47,"") | W47: =IFERROR(INDEX($AP$14:$AP$21,MATCH(X47,$B$14:$B$21,0)),"") | Z47: =IFERROR(INDEX($AP$14:$AP$21,MATCH(AA47,$B$14:$B$21,0)),"") | AC47: =IFERROR(INDEX($AP$14:$AP$21,MATCH(AD47,$B$14:$B$21,0)),"") | AF47: =IFERROR(INDEX($AP$14:$AP$21,MATCH(AG47,$B$14:$B$21,0)),"") | AI47: =IFERROR(INDEX($AP$14:$AP$21,MATCH(AJ47,$B$14:$B$21,0)),"") | AS47: =IF(OR(AL47="",W47=""),"",AL47*W47) | AT47: =IF(OR(AL47="",Z47=""),"",AL47*Z47) | AU47: =IF(OR(AL47="",AC47=""),"",AL47*AC47) | AV47: =IF(OR(AL47="",AF47=""),"",AL47*AF47) | AW47: =IF(OR(AL47="",AI47=""),"",AL47*AI47) | AX47: =IF(OR(AL47="",AI47=""),"",AL47*W47) | AY47: =(AL47-(AL47*$Z$6))*$AF$6 -> 0 | BC47: =(AL47-(AL47*$Z$6)) -> 0 | CD47: BABUCHE MASCULINO;
B48: 13 | S48: =IF(R48<>"",R48,"") | T48: =IF(R48<>"",R48,"") | W48: =IFERROR(INDEX($AP$14:$AP$21,MATCH(X48,$B$14:$B$21,0)),"") | Z48: =IFERROR(INDEX($AP$14:$AP$21,MATCH(AA48,$B$14:$B$21,0)),"") | AC48: =IFERROR(INDEX($AP$14:$AP$21,MATCH(AD48,$B$14:$B$21,0)),"") | AF48: =IFERROR(INDEX($AP$14:$AP$21,MATCH(AG48,$B$14:$B$21,0)),"") | AI48: =IFERROR(INDEX($AP$14:$AP$21,MATCH(AJ48,$B$14:$B$21,0)),"") | AS48: =IF(OR(AL48="",W48=""),"",AL48*W48) | AT48: =IF(OR(AL48="",Z48=""),"",AL48*Z48) | AU48: =IF(OR(AL48="",AC48=""),"",AL48*AC48) | AV48: =IF(OR(AL48="",AF48=""),"",AL48*AF48) | AW48: =IF(OR(AL48="",AI48=""),"",AL48*AI48) | AX48: =IF(OR(AL48="",AI48=""),"",AL48*W48) | AY48: =(AL48-(AL48*$Z$6))*$AF$6 -> 0 | BC48: =(AL48-(AL48*$Z$6)) -> 0 | CD48: BABY DOLL;
B49: 14 | S49: =IF(R49<>"",R49,"") | T49: =IF(R49<>"",R49,"") | W49: =IFERROR(INDEX($AP$14:$AP$21,MATCH(X49,$B$14:$B$21,0)),"") | Z49: =IFERROR(INDEX($AP$14:$AP$21,MATCH(AA49,$B$14:$B$21,0)),"") | AC49: =IFERROR(INDEX($AP$14:$AP$21,MATCH(AD49,$B$14:$B$21,0)),"") | AF49: =IFERROR(INDEX($AP$14:$AP$21,MATCH(AG49,$B$14:$B$21,0)),"") | AI49: =IFERROR(INDEX($AP$14:$AP$21,MATCH(AJ49,$B$14:$B$21,0)),"") | AS49: =IF(OR(AL49="",W49=""),"",AL49*W49) | AT49: =IF(OR(AL49="",Z49=""),"",AL49*Z49) | AU49: =IF(OR(AL49="",AC49=""),"",AL49*AC49) | AV49: =IF(OR(AL49="",AF49=""),"",AL49*AF49) | AW49: =IF(OR(AL49="",AI49=""),"",AL49*AI49) | AX49: =IF(OR(AL49="",AI49=""),"",AL49*W49) | AY49: =(AL49-(AL49*$Z$6))*$AF$6 -> 0 | BC49: =(AL49-(AL49*$Z$6)) -> 0 | CD49: BABY DOLL FEMININO;
... B94: 59 | S94: =IF(R94<>"",R94,"") | T94: =IF(R94<>"",R94,"") | W94: =IFERROR(INDEX($AP$14:$AP$21,MATCH(X94,$B$14:$B$21,0)),"") | Z94: =IFERROR(INDEX($AP$14:$AP$21,MATCH(AA94,$B$14:$B$21,0)),"") | AC94: =IFERROR(INDEX($AP$14:$AP$21,MATCH(AD94,$B$14:$B$21,0)),"") | AF94: =IFERROR(INDEX($AP$14:$AP$21,MATCH(AG94,$B$14:$B$21,0)),"") | AI94: =IFERROR(INDEX($AP$14:$AP$21,MATCH(AJ94,$B$14:$B$21,0)),"") | AS94: =IF(OR(AL94="",W94=""),"",AL94*W94) | AT94: =IF(OR(AL94="",Z94=""),"",AL94*Z94) | AU94: =IF(OR(AL94="",AC94=""),"",AL94*AC94) | AV94: =IF(OR(AL94="",AF94=""),"",AL94*AF94) | AW94: =IF(OR(AL94="",AI94=""),"",AL94*AI94) | AX94: =IF(OR(AL94="",AI94=""),"",AL94*W94) | AY94: =(AL94-(AL94*$Z$6))*$AF$6 -> 0 | BC94: =(AL94-(AL94*$Z$6)) -> 0 | CD94: BLUSAO INFANTIL;
B95: 60 | S95: =IF(R95<>"",R95,"") | T95: =IF(R95<>"",R95,"") | W95: =IFERROR(INDEX($AP$14:$AP$21,MATCH(X95,$B$14:$B$21,0)),"") | Z95: =IFERROR(INDEX($AP$14:$AP$21,MATCH(AA95,$B$14:$B$21,0)),"") | AC95: =IFERROR(INDEX($AP$14:$AP$21,MATCH(AD95,$B$14:$B$21,0)),"") | AF95: =IFERROR(INDEX($AP$14:$AP$21,MATCH(AG95,$B$14:$B$21,0)),"") | AI95: =IFERROR(INDEX($AP$14:$AP$21,MATCH(AJ95,$B$14:$B$21,0)),"") | AS95: =IF(OR(AL95="",W95=""),"",AL95*W95) | AT95: =IF(OR(AL95="",Z95=""),"",AL95*Z95) | AU95: =IF(OR(AL95="",AC95=""),"",AL95*AC95) | AV95: =IF(OR(AL95="",AF95=""),"",AL95*AF95) | AW95: =IF(OR(AL95="",AI95=""),"",AL95*AI95) | AX95: =IF(OR(AL95="",AI95=""),"",AL95*W95) | AY95: =(AL95-(AL95*$Z$6))*$AF$6 -> 0 | CD95: BLUSAO MASCULINO;
B96: 61 | S96: =IF(R96<>"",R96,"") | T96: =IF(R96<>"",R96,"") | W96: =IFERROR(INDEX($AP$14:$AP$21,MATCH(X96,$B$14:$B$21,0)),"") | Z96: =IFERROR(INDEX($AP$14:$AP$21,MATCH(AA96,$B$14:$B$21,0)),"") | AC96: =IFERROR(INDEX($AP$14:$AP$21,MATCH(AD96,$B$14:$B$21,0)),"") | AF96: =IFERROR(INDEX($AP$14:$AP$21,MATCH(AG96,$B$14:$B$21,0)),"") | AI96: =IFERROR(INDEX($AP$14:$AP$21,MATCH(AJ96,$B$14:$B$21,0)),"") | AS96: =IF(OR(AL96="",W96=""),"",AL96*W96) | AT96: =IF(OR(AL96="",Z96=""),"",AL96*Z96) | AU96: =IF(OR(AL96="",AC96=""),"",AL96*AC96) | AV96: =IF(OR(AL96="",AF96=""),"",AL96*AF96) | AW96: =IF(OR(AL96="",AI96=""),"",AL96*AI96) | AX96: =IF(OR(AL96="",AI96=""),"",AL96*W96) | AY96: =(AL96-(AL96*$Z$6))*$AF$6 -> 0 | CD96: BOARDSHORT;
B97: 62 | S97: =IF(R97<>"",R97,"") | T97: =IF(R97<>"",R97,"") | W97: =IFERROR(INDEX($AP$14:$AP$21,MATCH(X97,$B$14:$B$21,0)),"") | Z97: =IFERROR(INDEX($AP$14:$AP$21,MATCH(AA97,$B$14:$B$21,0)),"") | AC97: =IFERROR(INDEX($AP$14:$AP$21,MATCH(AD97,$B$14:$B$21,0)),"") | AF97: =IFERROR(INDEX($AP$14:$AP$21,MATCH(AG97,$B$14:$B$21,0)),"") | AI97: =IFERROR(INDEX($AP$14:$AP$21,MATCH(AJ97,$B$14:$B$21,0)),"") | AS97: =IF(OR(AL97="",W97=""),"",AL97*W97) | AT97: =IF(OR(AL97="",Z97=""),"",AL97*Z97) | AU97: =IF(OR(AL97="",AC97=""),"",AL97*AC97) | AV97: =IF(OR(AL97="",AF97=""),"",AL97*AF97) | AW97: =IF(OR(AL97="",AI97=""),"",AL97*AI97) | AX97: =IF(OR(AL97="",AI97=""),"",AL97*W97) | AY97: =(AL97-(AL97*$Z$6))*$AF$6 -> 0 | CD97: BODY;
B98: 63 | S98: =IF(R98<>"",R98,"") | T98: =IF(R98<>"",R98,"") | W98: =IFERROR(INDEX($AP$14:$AP$21,MATCH(X98,$B$14:$B$21,0)),"") | Z98: =IFERROR(INDEX($AP$14:$AP$21,MATCH(AA98,$B$14:$B$21,0)),"") | AC98: =IFERROR(INDEX($AP$14:$AP$21,MATCH(AD98,$B$14:$B$21,0)),"") | AF98: =IFERROR(INDEX($AP$14:$AP$21,MATCH(AG98,$B$14:$B$21,0)),"") | AI98: =IFERROR(INDEX($AP$14:$AP$21,MATCH(AJ98,$B$14:$B$21,0)),"") | AS98: =IF(OR(AL98="",W98=""),"",AL98*W98) | AT98: =IF(OR(AL98="",Z98=""),"",AL98*Z98) | AU98: =IF(OR(AL98="",AC98=""),"",AL98*AC98) | AV98: =IF(OR(AL98="",AF98=""),"",AL98*AF98) | AW98: =IF(OR(AL98="",AI98=""),"",AL98*AI98) | AX98: =IF(OR(AL98="",AI98=""),"",AL98*W98) | AY98: =(AL98-(AL98*$Z$6))*$AF$6 -> 0 | CD98: BODY FEMININO;
B99: 64 | S99: =IF(R99<>"",R99,"") | T99: =IF(R99<>"",R99,"") | W99: =IFERROR(INDEX($AP$14:$AP$21,MATCH(X99,$B$14:$B$21,0)),"") | Z99: =IFERROR(INDEX($AP$14:$AP$21,MATCH(AA99,$B$14:$B$21,0)),"") | AC99: =IFERROR(INDEX($AP$14:$AP$21,MATCH(AD99,$B$14:$B$21,0)),"") | AF99: =IFERROR(INDEX($AP$14:$AP$21,MATCH(AG99,$B$14:$B$21,0)),"") | AI99: =IFERROR(INDEX($AP$14:$AP$21,MATCH(AJ99,$B$14:$B$21,0)),"") | AS99: =IF(OR(AL99="",W99=""),"",AL99*W99) | AT99: =IF(OR(AL99="",Z99=""),"",AL99*Z99) | AU99: =IF(OR(AL99="",AC99=""),"",AL99*AC99) | AV99: =IF(OR(AL99="",AF99=""),"",AL99*AF99) | AW99: =IF(OR(AL99="",AI99=""),"",AL99*AI99) | AX99: =IF(OR(AL99="",AI99=""),"",AL99*W99) | AY99: =(AL99-(AL99*$Z$6))*$AF$6 -> 0 | CD99: BODY INFANTIL;
B100: 65 | S100: =IF(R100<>"",R100,"") | T100: =IF(R100<>"",R100,"") | W100: =IFERROR(INDEX($AP$14:$AP$21,MATCH(X100,$B$14:$B$21,0)),"") | Z100: =IFERROR(INDEX($AP$14:$AP$21,MATCH(AA100,$B$14:$B$21,0)),"") | AC100: =IFERROR(INDEX($AP$14:$AP$21,MATCH(AD100,$B$14:$B$21,0)),"") | AF100: =IFERROR(INDEX($AP$14:$AP$21,MATCH(AG100,$B$14:$B$21,0)),"") | AI100: =IFERROR(INDEX($AP$14:$AP$21,MATCH(AJ100,$B$14:$B$21,0)),"") | AS100: =IF(OR(AL100="",W100=""),"",AL100*W100) | AT100: =IF(OR(AL100="",Z100=""),"",AL100*Z100) | AU100: =IF(OR(AL100="",AC100=""),"",AL100*AC100) | AV100: =IF(OR(AL100="",AF100=""),"",AL100*AF100) | AW100: =IF(OR(AL100="",AI100=""),"",AL100*AI100) | AX100: =IF(OR(AL100="",AI100=""),"",AL100*W100) | AY100: =(AL100-(AL100*$Z$6))*$AF$6 -> 0 | CD100: BODY INFANTIL FEMININO;
B101: 66 | S101: =IF(R101<>"",R101,"") | T101: =IF(R101<>"",R101,"") | W101: =IFERROR(INDEX($AP$14:$AP$21,MATCH(X101,$B$14:$B$21,0)),"") | Z101: =IFERROR(INDEX($AP$14:$AP$21,MATCH(AA101,$B$14:$B$21,0)),"") | AC101: =IFERROR(INDEX($AP$14:$AP$21,MATCH(AD101,$B$14:$B$21,0)),"") | AF101: =IFERROR(INDEX($AP$14:$AP$21,MATCH(AG101,$B$14:$B$21,0)),"") | AI101: =IFERROR(INDEX($AP$14:$AP$21,MATCH(AJ101,$B$14:$B$21,0)),"") | AS101: =IF(OR(AL101="",W101=""),"",AL101*W101) | AT101: =IF(OR(AL101="",Z101=""),"",AL101*Z101) | AU101: =IF(OR(AL101="",AC101=""),"",AL101*AC101) | AV101: =IF(OR(AL101="",AF101=""),"",AL101*AF101) | AW101: =IF(OR(AL101="",AI101=""),"",AL101*AI101) | AX101: =IF(OR(AL101="",AI101=""),"",AL101*W101) | AY101: =(AL101-(AL101*$Z$6))*$AF$6 -> 0 | CD101: BODY MASCULINO;
B102: 67 | S102: =IF(R102<>"",R102,"") | T102: =IF(R102<>"",R102,"") | W102: =IFERROR(INDEX($AP$14:$AP$21,MATCH(X102,$B$14:$B$21,0)),"") | Z102: =IFERROR(INDEX($AP$14:$AP$21,MATCH(AA102,$B$14:$B$21,0)),"") | AC102: =IFERROR(INDEX($AP$14:$AP$21,MATCH(AD102,$B$14:$B$21,0)),"") | AF102: =IFERROR(INDEX($AP$14:$AP$21,MATCH(AG102,$B$14:$B$21,0)),"") | AI102: =IFERROR(INDEX($AP$14:$AP$21,MATCH(AJ102,$B$14:$B$21,0)),"") | AS102: =IF(OR(AL102="",W102=""),"",AL102*W102) | AT102: =IF(OR(AL102="",Z102=""),"",AL102*Z102) | AU102: =IF(OR(AL102="",AC102=""),"",AL102*AC102) | AV102: =IF(OR(AL102="",AF102=""),"",AL102*AF102) | AW102: =IF(OR(AL102="",AI102=""),"",AL102*AI102) | AX102: =IF(OR(AL102="",AI102=""),"",AL102*W102) | AY102: =(AL102-(AL102*$Z$6))*$AF$6 -> 0 | CD102: BODY SAIA;
B103: 68 | S103: =IF(R103<>"",R103,"") | T103: =IF(R103<>"",R103,"") | W103: =IFERROR(INDEX($AP$14:$AP$21,MATCH(X103,$B$14:$B$21,0)),"") | Z103: =IFERROR(INDEX($AP$14:$AP$21,MATCH(AA103,$B$14:$B$21,0)),"") | AC103: =IFERROR(INDEX($AP$14:$AP$21,MATCH(AD103,$B$14:$B$21,0)),"") | AF103: =IFERROR(INDEX($AP$14:$AP$21,MATCH(AG103,$B$14:$B$21,0)),"") | AI103: =IFERROR(INDEX($AP$14:$AP$21,MATCH(AJ103,$B$14:$B$21,0)),"") | AS103: =IF(OR(AL103="",W103=""),"",AL103*W103) | AT103: =IF(OR(AL103="",Z103=""),"",AL103*Z103) | AU103: =IF(OR(AL103="",AC103=""),"",AL103*AC103) | AV103: =IF(OR(AL103="",AF103=""),"",AL103*AF103) | AW103: =IF(OR(AL103="",AI103=""),"",AL103*AI103) | AX103: =IF(OR(AL103="",AI103=""),"",AL103*W103) | AY103: =(AL103-(AL103*$Z$6))*$AF$6 -> 0 | CD103: BODY-VESTIDO;
B104: 69 | S104: =IF(R104<>"",R104,"") | T104: =IF(R104<>"",R104,"") | W104: =IFERROR(INDEX($AP$14:$AP$21,MATCH(X104,$B$14:$B$21,0)),"") | Z104: =IFERROR(INDEX($AP$14:$AP$21,MATCH(AA104,$B$14:$B$21,0)),"") | AC104: =IFERROR(INDEX($AP$14:$AP$21,MATCH(AD104,$B$14:$B$21,0)),"") | AF104: =IFERROR(INDEX($AP$14:$AP$21,MATCH(AG104,$B$14:$B$21,0)),"") | AI104: =IFERROR(INDEX($AP$14:$AP$21,MATCH(AJ104,$B$14:$B$21,0)),"") | AS104: =IF(OR(AL104="",W104=""),"",AL104*W104) | AT104: =IF(OR(AL104="",Z104=""),"",AL104*Z104) | AU104: =IF(OR(AL104="",AC104=""),"",AL104*AC104) | AV104: =IF(OR(AL104="",AF104=""),"",AL104*AF104) | AW104: =IF(OR(AL104="",AI104=""),"",AL104*AI104) | AX104: =IF(OR(AL104="",AI104=""),"",AL104*W104) | AY104: =(AL104-(AL104*$Z$6))*$AF$6 -> 0 | CD104: BODY-VESTIDO FEMININO;
B105: 70 | S105: =IF(R105<>"",R105,"") | T105: =IF(R105<>"",R105,"") | W105: =IFERROR(INDEX($AP$14:$AP$21,MATCH(X105,$B$14:$B$21,0)),"") | Z105: =IFERROR(INDEX($AP$14:$AP$21,MATCH(AA105,$B$14:$B$21,0)),"") | AC105: =IFERROR(INDEX($AP$14:$AP$21,MATCH(AD105,$B$14:$B$21,0)),"") | AF105: =IFERROR(INDEX($AP$14:$AP$21,MATCH(AG105,$B$14:$B$21,0)),"") | AI105: =IFERROR(INDEX($AP$14:$AP$21,MATCH(AJ105,$B$14:$B$21,0)),"") | AS105: =IF(OR(AL105="",W105=""),"",AL105*W105) | AT105: =IF(OR(AL105="",Z105=""),"",AL105*Z105) | AU105: =IF(OR(AL105="",AC105=""),"",AL105*AC105) | AV105: =IF(OR(AL105="",AF105=""),"",AL105*AF105) | AW105: =IF(OR(AL105="",AI105=""),"",AL105*AI105) | AX105: =IF(OR(AL105="",AI105=""),"",AL105*W105) | AY105: =(AL105-(AL105*$Z$6))*$AF$6 -> 0 | CD105: BODY-VESTIDO INFANTIL;
B106: 71 | S106: =IF(R106<>"",R106,"") | T106: =IF(R106<>"",R106,"") | W106: =IFERROR(INDEX($AP$14:$AP$21,MATCH(X106,$B$14:$B$21,0)),"") | Z106: =IFERROR(INDEX($AP$14:$AP$21,MATCH(AA106,$B$14:$B$21,0)),"") | AC106: =IFERROR(INDEX($AP$14:$AP$21,MATCH(AD106,$B$14:$B$21,0)),"") | AF106: =IFERROR(INDEX($AP$14:$AP$21,MATCH(AG106,$B$14:$B$21,0)),"") | AI106: =IFERROR(INDEX($AP$14:$AP$21,MATCH(AJ106,$B$14:$B$21,0)),"") | AS106: =IF(OR(AL106="",W106=""),"",AL106*W106) | AT106: =IF(OR(AL106="",Z106=""),"",AL106*Z106) | AU106: =IF(OR(AL106="",AC106=""),"",AL106*AC106) | AV106: =IF(OR(AL106="",AF106=""),"",AL106*AF106) | AW106: =IF(OR(AL106="",AI106=""),"",AL106*AI106) | AX106: =IF(OR(AL106="",AI106=""),"",AL106*W106) | AY106: =(AL106-(AL106*$Z$6))*$AF$6 -> 0 | CD106: BODY-VESTIDO INFANTIL FEMININO;
... B164: 129 | S164: =IF(R164<>"",R164,"") | T164: =IF(R164<>"",R164,"") | W164: =IFERROR(INDEX($AP$14:$AP$21,MATCH(X164,$B$14:$B$21,0)),"") | Z164: =IFERROR(INDEX($AP$14:$AP$21,MATCH(AA164,$B$14:$B$21,0)),"") | AC164: =IFERROR(INDEX($AP$14:$AP$21,MATCH(AD164,$B$14:$B$21,0)),"") | AF164: =IFERROR(INDEX($AP$14:$AP$21,MATCH(AG164,$B$14:$B$21,0)),"") | AI164: =IFERROR(INDEX($AP$14:$AP$21,MATCH(AJ164,$B$14:$B$21,0)),"") | AS164: =IF(OR(AL164="",W164=""),"",AL164*W164) | AT164: =IF(OR(AL164="",Z164=""),"",AL164*Z164) | AU164: =IF(OR(AL164="",AC164=""),"",AL164*AC164) | AV164: =IF(OR(AL164="",AF164=""),"",AL164*AF164) | AW164: =IF(OR(AL164="",AI164=""),"",AL164*AI164) | AX164: =IF(OR(AL164="",AI164=""),"",AL164*W164) | AY164: =(AL164-(AL164*$Z$6))*$AF$6 -> 0 | CD164: CALCADEIRA;
CD165: CALCAO;
AS166: =SUM(AS36:AS164) -> 0 | AT166: =SUM(AT36:AT164) -> 0 | AU166: =SUM(AU36:AU164) -> 0 | AV166: =SUM(AV36:AV164) -> 0 | AW166: =SUM(AW36:AW165) -> 0 | CD166: CALCAO FEMININO;
CD167: CALCAO MASCULINO;
CD168: CALCINHA;
CD169: CALCINHA FEMININO;
CD170: CALCINHA INFANTIL;
CD171: CAMISA;
CD172: CAMISA FEMININO;
CD173: CAMISA INFANTIL;
CD174: CAMISA INFANTIL MASCULINO;
CD175: CAMISA JUVENIL;
CD176: CAMISA MASCULINO;
CD177: CAMISA SOCIAL;
CD178: CAMISA TERMICA;
... CD633: VISEIRA;

Sheet TABELA
A1: Lojas | B1: 1 | C1: 2 | D1: 3 | E1: 4 | F1: 5 | G1: 6 | H1: 7 | I1: 8 | J1: 9 | K1: 10 | L1: 11 | M1: 12 | N1: 13 | O1: 14 | P1: 15 | Q1: 19 | R1: 20 | S1: 21 | T1: 22 | U1: 23 | V1: 24 | W1: 25 | X1: 26 | Y1: 27 | Z1: 28 | AA1: 29 | AB1: 30 | AC1: 31 | AD1: 32 | AE1: 33 | AF1: 34 | AG1: 35 | AH1: 36 | AI1: 37 | AJ1: 38 | AK1: 39 | AL1: 40 | AM1: 41 | AN1: 42 | AO1: 43 | AP1: 44 | AQ1: 45 | AR1: 46 | AS1: 47 | AT1: 48 | AU1: 49 | AV1: 50 | AW1: 51 | AX1: 52 | AY1: 53 | AZ1: 54 | BA1: 56 | BB1: 57 | BC1: 58 | BD1: 59 | BE1: 60 | BF1: 61 | BG1: 62 | BH1: 63 | BI1: 64 | BJ1: 65 | BK1: 66 | BL1: 67 | BM1: 68 | BN1: 69 | BO1: 70 | BP1: 72 | BQ1: 73 | BR1: 74 | BS1: 75 | BT1: 76 | BU1: 77 | BV1: 78 | BW1: 79 | BX1: 80 | BY1: 81 | BZ1: 82 | CA1: 83 | CB1: 84 | CC1: 85 | CD1: 86 | CE1: 87 | CF1: 88 | CG1: 89 | CH1: 90 | CI1: 91 | CJ1: 92 | CK1: 93 | CL1: 94 | CM1: 95 | CN1: 96 | CO1: 97 | CP1: 98 | CQ1: 99 | CR1: 100 | CS1: 101 | CT1: 102 | CU1: 103 | CV1: 104 | CW1: 105 | CX1: 106 | CY1: 107 | CZ1: 108 | DA1: 999 | DB1: 109 | DC1: 110 | DD1: 111 | DE1: 112 | DF1: 113 | DG1: 114 | DH1: 115 | DI1: 116 | DJ1: 117 | DK1: 118 | DL1: 119 | DM1: 120 | DY1: tipo | DZ1: forncedor | EA1: KAMYSTORE | EB1: PINOLI | EC1: MATIS X
CW2: =IF(COUNTIF(PEDIDO!$D$23:$AO$23, CW$1)>0, CW$1, "") | CX2: =IF(COUNTIF(PEDIDO!$D$23:$AO$23, CX$1)>0, CX$1, "") | CY2: =IF(COUNTIF(PEDIDO!$D$23:$AO$23, CY$1)>0, CY$1, "") | CZ2: =IF(COUNTIF(PEDIDO!$D$23:$AO$23, CZ$1)>0, CZ$1, "") | DA2: =IF(COUNTIF(PEDIDO!$D$23:$AO$23, DA$1)>0, DA$1, "") | DY2: ANABELA | DZ2: POWER GLASSES | EA2: 100 MORENA | EB2: ACADEMY | EC2: NK6 PRO TREKKING
DY3: ANABELA INFANTIL | DZ3: CASA DO FILTRO | EA3: 100 PLUS | EB3: ACAI | EC3: 20L
A4: =PEDIDO!B23 -> PEDIDO 1 | B4: =IF(PEDIDO!D23<>"",PEDIDO!D23,"") | C4: =IF(PEDIDO!E23<>"",PEDIDO!E23,"") | D4: =IF(PEDIDO!F23<>"",PEDIDO!F23,"") | E4: =IF(PEDIDO!G23<>"",PEDIDO!G23,"") | F4: =IF(PEDIDO!H23<>"",PEDIDO!H23,"") | G4: =IF(PEDIDO!I23<>"",PEDIDO!I23,"") | H4: =IF(PEDIDO!J23<>"",PEDIDO!J23,"") | I4: =IF(PEDIDO!K23<>"",PEDIDO!K23,"") | ... AM4: =IF(PEDIDO!AO23<>"",PEDIDO!AO23,"") | AO4: =IF(PEDIDO!AQ23<>"",PEDIDO!AQ23,"") | AP4: =IF(PEDIDO!AR23<>"",PEDIDO!AR23,"") | AQ4: =IF(PEDIDO!AS23<>"",PEDIDO!AS23,"") | AR4: =IF(PEDIDO!AT23<>"",PEDIDO!AT23,"") | AS4: =IF(PEDIDO!AU23<>"",PEDIDO!AU23,"") | AT4: =IF(PEDIDO!AV23<>"",PEDIDO!AV23,"") | AU4: =IF(PEDIDO!AW23<>"",PEDIDO!AW23,"") | AV4: =IF(PEDIDO!AX23<>"",PEDIDO!AX23,"") | ... BC4: =IF(PEDIDO!BE23<>"",PEDIDO!BE23,"") | DY4: ANEL | DZ4: MUSA FASHION | EA4: 2 RIOS | EB4: ACEROLA | EC4: 3 PECA
A5: =PEDIDO!B24 -> PEDIDO 2 | B5: =IF(PEDIDO!D24<>"",PEDIDO!D24,"") | C5: =IF(PEDIDO!E24<>"",PEDIDO!E24,"") | D5: =IF(PEDIDO!F24<>"",PEDIDO!F24,"") | E5: =IF(PEDIDO!G24<>"",PEDIDO!G24,"") | F5: =IF(PEDIDO!H24<>"",PEDIDO!H24,"") | G5: =IF(PEDIDO!I24<>"",PEDIDO!I24,"") | H5: =IF(PEDIDO!J24<>"",PEDIDO!J24,"") | I5: =IF(PEDIDO!K24<>"",PEDIDO!K24,"") | ... AM5: =IF(PEDIDO!AO24<>"",PEDIDO!AO24,"") | DY5: AROMATIZANTE | DZ5: NC | EA5: 206OZ | EB5: ACID LIME | EC5: 360 4 LIFE
A6: =PEDIDO!B25 -> PEDIDO 3 | B6: =IF(PEDIDO!D25<>"",PEDIDO!D25,"") | C6: =IF(PEDIDO!E25<>"",PEDIDO!E25,"") | D6: =IF(PEDIDO!F25<>"",PEDIDO!F25,"") | E6: =IF(PEDIDO!G25<>"",PEDIDO!G25,"") | F6: =IF(PEDIDO!H25<>"",PEDIDO!H25,"") | G6: =IF(PEDIDO!I25<>"",PEDIDO!I25,"") | H6: =IF(PEDIDO!J25<>"",PEDIDO!J25,"") | I6: =IF(PEDIDO!K25<>"",PEDIDO!K25,"") | ... AM6: =IF(PEDIDO!AO25<>"",PEDIDO!AO25,"") | DY6: BABUCHE | DZ6: ISABEL KARINE SANTANA SILVA ALVES | EA6: 23 GRAUS | EB6: ACO | EC6: 360 ATLANTA
A7: =PEDIDO!B26 -> PEDIDO 4 | B7: =IF(PEDIDO!D26<>"",PEDIDO!D26,"") | C7: =IF(PEDIDO!E26<>"",PEDIDO!E26,"") | D7: =IF(PEDIDO!F26<>"",PEDIDO!F26,"") | E7: =IF(PEDIDO!G26<>"",PEDIDO!G26,"") | F7: =IF(PEDIDO!H26<>"",PEDIDO!H26,"") | G7: =IF(PEDIDO!I26<>"",PEDIDO!I26,"") | H7: =IF(PEDIDO!J26<>"",PEDIDO!J26,"") | I7: =IF(PEDIDO!K26<>"",PEDIDO!K26,"") | ... AM7: =IF(PEDIDO!AO26<>"",PEDIDO!AO26,"") | DY7: BABUCHE FEMININO | DZ7: GMAD | EA7: 2K | EB7: ACO INOX | EC7: 360 GAMA
A8: =PEDIDO!B27 -> PEDIDO 5 | B8: =IF(PEDIDO!D27<>"",PEDIDO!D27,"") | C8: =IF(PEDIDO!E27<>"",PEDIDO!E27,"") | D8: =IF(PEDIDO!F27<>"",PEDIDO!F27,"") | E8: =IF(PEDIDO!G27<>"",PEDIDO!G27,"") | F8: =IF(PEDIDO!H27<>"",PEDIDO!H27,"") | G8: =IF(PEDIDO!I27<>"",PEDIDO!I27,"") | H8: =IF(PEDIDO!J27<>"",PEDIDO!J27,"") | I8: =IF(PEDIDO!K27<>"",PEDIDO!K27,"") | ... AM8: =IF(PEDIDO!AO27<>"",PEDIDO!AO27,"") | DY8: BABUCHE INFANTIL | DZ8: GIBIZINHO | EA8: 4R BABY | EB8: ACQUA | EC8: 360 GAMA 3
DY9: BABUCHE INFANTIL FEMININA | DZ9: LIFE GYM | EA9: 4S | EB9: ACQUA WHITE | EC9: 360 GENEBRA
A10: Itens | B10: PEDIDO 1 | C10: PEDIDO 2 | D10: PEDIDO 3 | E10: PEDIDO 4 | F10: PEDIDO 5 | J10: Lojas | K10: 1 | L10: 2 | M10: 3 | N10: 4 | O10: 5 | P10: 6 | Q10: 7 | R10: 8 | S10: 9 | T10: 10 | U10: 11 | V10: 12 | W10: 13 | X10: 14 | Y10: 15 | Z10: 19 | AA10: 20 | AB10: 21 | AC10: 22 | AD10: 23 | AE10: 24 | AF10: 25 | AG10: 26 | AH10: 27 | AI10: 28 | AJ10: 29 | AK10: 30 | AL10: 31 | AM10: 32 | AN10: 33 | AO10: 34 | AP10: 35 | AQ10: 36 | AR10: 37 | AS10: 38 | AT10: 39 | AU10: 40 | AV10: 41 | AW10: 42 | AX10: 43 | AY10: 44 | AZ10: 45 | BA10: 46 | BB10: 47 | BC10: 48 | BD10: 49 | BE10: 50 | BF10: 51 | BG10: 52 | BH10: 53 | BI10: 54 | BJ10: 56 | BK10: 57 | BL10: 58 | BM10: 59 | BN10: 60 | BO10: 61 | BP10: 62 | BQ10: 63 | BR10: 64 | BS10: 65 | BT10: 66 | BU10: 67 | BV10: 68 | BW10: 69 | BX10: 70 | BY10: 72 | BZ10: 73 | CA10: 74 | CB10: 75 | CC10: 76 | CD10: 77 | CE10: 78 | CF10: 79 | CG10: 80 | CH10: 81 | CI10: 82 | CJ10: 83 | CK10: 84 | CL10: 85 | CM10: 86 | CN10: 87 | CO10: 88 | CP10: 89 | CQ10: 90 | CR10: 91 | CS10: 92 | CT10: 93 | CU10: 94 | CV10: 95 | CW10: 96 | CX10: 97 | CY10: 98 | CZ10: 99 | DA10: 100 | DB10: 101 | DC10: 102 | DD10: 103 | DE10: 104 | DF10: 105 | DG10: 106 | DH10: 107 | DI10: 108 | DJ10: 999 | DK10: 109 | DL10: 110 | DM10: 111 | DN10: 112 | DO10: 113 | DP10: 114 | DQ10: 115 | DR10: 116 | DS10: 117 | DT10: 118 | DU10: 119 | DV10: 120 | DY10: BABUCHE INFANTIL MASCULINO | DZ10: IMPERIO MOVEIS E ELETRO | EA10: 5 GERAÇÃO | EB10: ADAMES COLORS | EC10: 360 RACER
A11: =IF(PEDIDO!C36<>"",PEDIDO!B36,"") | B11: =IF(PEDIDO!X36<>"",PEDIDO!X36,"") | C11: =IF(PEDIDO!AA36<>"",PEDIDO!AA36,"") | D11: =IF(PEDIDO!AD36<>"",PEDIDO!AD36,"") | E11: =IF(PEDIDO!AG36<>"",PEDIDO!AG36,"") | F11: =IF(PEDIDO!AJ36<>"",PEDIDO!AJ36,"") | J11: Pedido 1 | K11: =IF(COUNTIF(PEDIDO!$D$23:$AO$23, K$10)>0, K$10, "") | L11: =IF(COUNTIF(PEDIDO!$D$23:$AO$23, L$10)>0, L$10, "") | M11: =IF(COUNTIF(PEDIDO!$D$23:$AO$23, M$10)>0, M$10, "") | N11: =IF(COUNTIF(PEDIDO!$D$23:$AO$23, N$10)>0, N$10, "") | O11: =IF(COUNTIF(PEDIDO!$D$23:$AO$23, O$10)>0, O$10, "") | P11: =IF(COUNTIF(PEDIDO!$D$23:$AO$23, P$10)>0, P$10, "") | Q11: =IF(COUNTIF(PEDIDO!$D$23:$AO$23, Q$10)>0, Q$10, "") | R11: =IF(COUNTIF(PEDIDO!$D$23:$AO$23, R$10)>0, R$10, "") | ... DV11: =IF(COUNTIF(PEDIDO!$D$23:$AO$23, DV$10)>0, DV$10, "") | DY11: BABUCHE MASCULINO | DZ11: AUTENTICA | EA11: 551 JEANS | EB11: AERORANG | EC11: 360 TO CROSS
A12: =IF(PEDIDO!C37<>"",PEDIDO!B37,"") | B12: =IF(PEDIDO!X37<>"",PEDIDO!X37,"") | C12: =IF(PEDIDO!AA37<>"",PEDIDO!AA37,"") | D12: =IF(PEDIDO!AD37<>"",PEDIDO!AD37,"") | E12: =IF(PEDIDO!AG37<>"",PEDIDO!AG37,"") | F12: =IF(PEDIDO!AJ37<>"",PEDIDO!AJ37,"") | J12: =IF(PEDIDO!C36<>"",PEDIDO!B36,"") | K12: =IF($K$11<>"",B11,"") | L12: =IF($L$11<>"",B11,"") | M12: =IF($M$11<>"",B11,"") | N12: =IF($N$11<>"",B11,"") | O12: =IF($O$11<>"",B11,"") | P12: =IF($P$11<>"",B11,"") | Q12: =IF($Q$11<>"",B11,"") | R12: =IF($R$11<>"",B11,"") | S12: =IF($S$11<>"",B11,"") | T12: =IF($T$11<>"",B11,"") | U12: =IF($U$11<>"",B11,"") | V12: =IF($V$11<>"",B11,"") | W12: =IF($W$11<>"",B11,"") | X12: =IF($X$11<>"",B11,"") | Y12: =IF($Y$11<>"",B11,"") | Z12: =IF($Z$11<>"",B11,"") | AA12: =IF($AA$11<>"",B11,"") | AB12: =IF($AB$11<>"",B11,"") | AC12: =IF($AC$11<>"",B11,"") | AD12: =IF($AD$11<>"",B11,"") | AE12: =IF($AE$11<>"",B11,"") | AF12: =IF($AF$11<>"",B11,"") | AG12: =IF($AG$11<>"",B11,"") | AH12: =IF($AH$11<>"",B11,"") | AI12: =IF($AI$11<>"",B11,"") | AJ12: =IF($AJ$11<>"",B11,"") | AK12: =IF($AK$11<>"",B11,"") | AL12: =IF($AL$11<>"",B11,"") | AM12: =IF($AM$11<>"",B11,"") | AN12: =IF($AN$11<>"",B11,"") | AO12: =IF($AO$11<>"",B11,"") | AP12: =IF($AP$11<>"",B11,"") | AQ12: =IF($AQ$11<>"",B11,"") | AR12: =IF($AR$11<>"",B11,"") | AS12: =IF($AS$11<>"",B11,"") | AT12: =IF($AT$11<>"",B11,"") | AU12: =IF($AU$11<>"",B11,"") | AV12: =IF($AV$11<>"",B11,"") | AW12: =IF($AW$11<>"",B11,"") | AX12: =IF($AX$11<>"",B11,"") | AY12: =IF($AY$11<>"",B11,"") | AZ12: =IF($AZ$11<>"",B11,"") | BA12: =IF($BA$11<>"",B11,"") | BB12: =IF($BB$11<>"",B11,"") | BC12: =IF($BC$11<>"",B11,"") | BD12: =IF($BD$11<>"",B11,"") | BE12: =IF($BE$11<>"",B11,"") | BF12: =IF($BF$11<>"",B11,"") | BG12: =IF($BG$11<>"",B11,"") | BH12: =IF($BH$11<>"",B11,"") | BI12: =IF($BI$11<>"",B11,"") | BJ12: =IF($BJ$11<>"",B11,"") | BK12: =IF($BK$11<>"",B11,"") | BL12: =IF($BL$11<>"",B11,"") | BM12: =IF($BM$11<>"",B11,"") | BN12: =IF($BN$11<>"",B11,"") | BO12: =IF($BO$11<>"",B11,"") | BP12: =IF($BP$11<>"",B11,"") | BQ12: =IF($BQ$11<>"",B11,"") | BR12: =IF($BR$11<>"",B11,"") | BS12: =IF($BS$11<>"",B11,"") | BT12: =IF($BT$11<>"",B11,"") | BU12: =IF($BU$11<>"",B11,"") | BV12: =IF($BV$11<>"",B11,"") | BW12: =IF($BW$11<>"",B11,"") | BX12: =IF($BX$11<>"",B11,"") | BY12: =IF($BY$11<>"",B11,"") | BZ12: =IF($BZ$11<>"",B11,"") | CA12: =IF($CA$11<>"",B11,"") | CB12: =IF($CB$11<>"",B11,"") | CC12: =IF($CC$11<>"",B11,"") | CD12: =IF($CD$11<>"",B11,"") | CE12: =IF($CE$11<>"",B11,"") | CF12: =IF($CF$11<>"",B11,"") | CG12: =IF($CG$11<>"",B11,"") | CH12: =IF($CH$11<>"",B11,"") | CI12: =IF($CI$11<>"",B11,"") | CJ12: =IF($CJ$11<>"",B11,"") | CK12: =IF($CK$11<>"",B11,"") | CL12: =IF($CL$11<>"",B11,"") | CM12: =IF($CM$11<>"",B11,"") | CN12: =IF($CN$11<>"",B11,"") | CO12: =IF($CO$11<>"",B11,"") | CP12: =IF($CP$11<>"",B11,"") | CQ12: =IF($CQ$11<>"",B11,"") | CR12: =IF($CR$11<>"",B11,"") | CS12: =IF($CS$11<>"",B11,"") | CT12: =IF($CT$11<>"",B11,"") | CU12: =IF($CU$11<>"",B11,"") | CV12: =IF($CV$11<>"",B11,"") | CW12: =IF($CW$11<>"",B11,"") | CX12: =IF($CX$11<>"",B11,"") | CY12: =IF($CY$11<>"",B11,"") | CZ12: =IF($CZ$11<>"",B11,"") | DA12: =IF($DA$11<>"",B11,"") | DB12: =IF($DB$11<>"",B11,"") | DC12: =IF($DC$11<>"",B11,"") | DD12: =IF($DD$11<>"",B11,"") | DE12: =IF($DE$11<>"",B11,"") | DF12: =IF($DF$11<>"",B11,"") | DG12: =IF($DG$11<>"",B11,"") | DH12: =IF($DH$11<>"",B11,"") | DI12: =IF($DI$11<>"",B11,"") | DJ12: =IF($DJ$11<>"",B11,"") | DK12: =IF($DK$11<>"",$B11,"") | DL12: =IF($DL$11<>"",$B11,"") | DM12: =IF($DM$11<>"",$B11,"") | DN12: =IF($DN$11<>"",$B11,"") | DO12: =IF($DO$11<>"",$B11,"") | DP12: =IF($DP$11<>"",$B11,"") | DQ12: =IF($DQ$11<>"",$B11,"") | DR12: =IF($DR$11<>"",$B11,"") | DS12: =IF($DS$11<>"",$B11,"") | DT12: =IF($DT$11<>"",$B11,"") | DU12: =IF($DU$11<>"",$B11,"") | DV12: =IF($DV$11<>"",$B11,"") | DY12: BABY DOLL | DZ12: DUFRIO | EA12: 7 SEVEN | EB12: ALECRIM | EC12: 360 TO FLY
A13: =IF(PEDIDO!C38<>"",PEDIDO!B38,"") | B13: =IF(PEDIDO!X38<>"",PEDIDO!X38,"") | C13: =IF(PEDIDO!AA38<>"",PEDIDO!AA38,"") | D13: =IF(PEDIDO!AD38<>"",PEDIDO!AD38,"") | E13: =IF(PEDIDO!AG38<>"",PEDIDO!AG38,"") | F13: =IF(PEDIDO!AJ38<>"",PEDIDO!AJ38,"") | J13: =IF(PEDIDO!C37<>"",PEDIDO!B37,"") | K13: =IF($K$11<>"",B12,"") | L13: =IF($L$11<>"",B12,"") | M13: =IF($M$11<>"",B12,"") | N13: =IF($N$11<>"",B12,"") | O13: =IF($O$11<>"",B12,"") | P13: =IF($P$11<>"",B12,"") | Q13: =IF($Q$11<>"",B12,"") | R13: =IF($R$11<>"",B12,"") | S13: =IF($S$11<>"",B12,"") | T13: =IF($T$11<>"",B12,"") | U13: =IF($U$11<>"",B12,"") | V13: =IF($V$11<>"",B12,"") | W13: =IF($W$11<>"",B12,"") | X13: =IF($X$11<>"",B12,"") | Y13: =IF($Y$11<>"",B12,"") | Z13: =IF($Z$11<>"",B12,"") | AA13: =IF($AA$11<>"",B12,"") | AB13: =IF($AB$11<>"",B12,"") | AC13: =IF($AC$11<>"",B12,"") | AD13: =IF($AD$11<>"",B12,"") | AE13: =IF($AE$11<>"",B12,"") | AF13: =IF($AF$11<>"",B12,"") | AG13: =IF($AG$11<>"",B12,"") | AH13: =IF($AH$11<>"",B12,"") | AI13: =IF($AI$11<>"",B12,"") | AJ13: =IF($AJ$11<>"",B12,"") | AK13: =IF($AK$11<>"",B12,"") | AL13: =IF($AL$11<>"",B12,"") | AM13: =IF($AM$11<>"",B12,"") | AN13: =IF($AN$11<>"",B12,"") | AO13: =IF($AO$11<>"",B12,"") | AP13: =IF($AP$11<>"",B12,"") | AQ13: =IF($AQ$11<>"",B12,"") | AR13: =IF($AR$11<>"",B12,"") | AS13: =IF($AS$11<>"",B12,"") | AT13: =IF($AT$11<>"",B12,"") | AU13: =IF($AU$11<>"",B12,"") | AV13: =IF($AV$11<>"",B12,"") | AW13: =IF($AW$11<>"",B12,"") | AX13: =IF($AX$11<>"",B12,"") | AY13: =IF($AY$11<>"",B12,"") | AZ13: =IF($AZ$11<>"",B12,"") | BA13: =IF($BA$11<>"",B12,"") | BB13: =IF($BB$11<>"",B12,"") | BC13: =IF($BC$11<>"",B12,"") | BD13: =IF($BD$11<>"",B12,"") | BE13: =IF($BE$11<>"",B12,"") | BF13: =IF($BF$11<>"",B12,"") | BG13: =IF($BG$11<>"",B12,"") | BH13: =IF($BH$11<>"",B12,"") | BI13: =IF($BI$11<>"",B12,"") | BJ13: =IF($BJ$11<>"",B12,"") | BK13: =IF($BK$11<>"",B12,"") | BL13: =IF($BL$11<>"",B12,"") | BM13: =IF($BM$11<>"",B12,"") | BN13: =IF($BN$11<>"",B12,"") | BO13: =IF($BO$11<>"",B12,"") | BP13: =IF($BP$11<>"",B12,"") | BQ13: =IF($BQ$11<>"",B12,"") | BR13: =IF($BR$11<>"",B12,"") | BS13: =IF($BS$11<>"",B12,"") | BT13: =IF($BT$11<>"",B12,"") | BU13: =IF($BU$11<>"",B12,"") | BV13: =IF($BV$11<>"",B12,"") | BW13: =IF($BW$11<>"",B12,"") | BX13: =IF($BX$11<>"",B12,"") | BY13: =IF($BY$11<>"",B12,"") | BZ13: =IF($BZ$11<>"",B12,"") | CA13: =IF($CA$11<>"",B12,"") | CB13: =IF($CB$11<>"",B12,"") | CC13: =IF($CC$11<>"",B12,"") | CD13: =IF($CD$11<>"",B12,"") | CE13: =IF($CE$11<>"",B12,"") | CF13: =IF($CF$11<>"",B12,"") | CG13: =IF($CG$11<>"",B12,"") | CH13: =IF($CH$11<>"",B12,"") | CI13: =IF($CI$11<>"",B12,"") | CJ13: =IF($CJ$11<>"",B12,"") | CK13: =IF($CK$11<>"",B12,"") | CL13: =IF($CL$11<>"",B12,"") | CM13: =IF($CM$11<>"",B12,"") | CN13: =IF($CN$11<>"",B12,"") | CO13: =IF($CO$11<>"",B12,"") | CP13: =IF($CP$11<>"",B12,"") | CQ13: =IF($CQ$11<>"",B12,"") | CR13: =IF($CR$11<>"",B12,"") | CS13: =IF(CS12<>"",$B$12,"") | CT13: =IF($CT$11<>"",B12,"") | CU13: =IF($CU$11<>"",B12,"") | CV13: =IF($CV$11<>"",B12,"") | CW13: =IF($CW$11<>"",B12,"") | CX13: =IF($CX$11<>"",B12,"") | CY13: =IF($CY$11<>"",B12,"") | CZ13: =IF($CZ$11<>"",B12,"") | DA13: =IF($DA$11<>"",B12,"") | DB13: =IF($DB$11<>"",B12,"") | DC13: =IF($DC$11<>"",B12,"") | DD13: =IF($DD$11<>"",B12,"") | DE13: =IF($DE$11<>"",B12,"") | DF13: =IF($DF$11<>"",B12,"") | DG13: =IF($DG$11<>"",B12,"") | DH13: =IF($DH$11<>"",B12,"") | DI13: =IF($DI$11<>"",B12,"") | DJ13: =IF($DJ$11<>"",B12,"") | DK13: =IF($DK$11<>"",$B12,"") | DL13: =IF($DL$11<>"",$B12,"") | DM13: =IF($DM$11<>"",$B12,"") | DN13: =IF($DN$11<>"",$B12,"") | DO13: =IF($DO$11<>"",$B12,"") | DP13: =IF($DP$11<>"",$B12,"") | DQ13: =IF($DQ$11<>"",$B12,"") | DR13: =IF($DR$11<>"",$B12,"") | DS13: =IF($DS$11<>"",$B12,"") | DT13: =IF($DT$11<>"",$B12,"") | DU13: =IF($DU$11<>"",$B12,"") | DV13: =IF($DV$11<>"",$B12,"") | DY13: BABY DOLL FEMININO | DZ13: KEROLYNE | EA13: 767 JEANS | EB13: ALFAZEMA | EC13: 360 TO GO
A14: =IF(PEDIDO!C39<>"",PEDIDO!B39,"") | B14: =IF(PEDIDO!X39<>"",PEDIDO!X39,"") | C14: =IF(PEDIDO!AA39<>"",PEDIDO!AA39,"") | D14: =IF(PEDIDO!AD39<>"",PEDIDO!AD39,"") | E14: =IF(PEDIDO!AG39<>"",PEDIDO!AG39,"") | F14: =IF(PEDIDO!AJ39<>"",PEDIDO!AJ39,"") | J14: =IF(PEDIDO!C38<>"",PEDIDO!B38,"") | K14: =IF($K$11<>"",B13,"") | L14: =IF($L$11<>"",B13,"") | M14: =IF($M$11<>"",B13,"") | N14: =IF($N$11<>"",B13,"") | O14: =IF($O$11<>"",B13,"") | P14: =IF($P$11<>"",B13,"") | Q14: =IF($Q$11<>"",B13,"") | R14: =IF($R$11<>"",B13,"") | S14: =IF($S$11<>"",B13,"") | T14: =IF($T$11<>"",B13,"") | U14: =IF($U$11<>"",B13,"") | V14: =IF($V$11<>"",B13,"") | W14: =IF($W$11<>"",B13,"") | X14: =IF($X$11<>"",B13,"") | Y14: =IF($Y$11<>"",B13,"") | Z14: =IF($Z$11<>"",B13,"") | AA14: =IF($AA$11<>"",B13,"") | AB14: =IF($AB$11<>"",B13,"") | AC14: =IF($AC$11<>"",B13,"") | AD14: =IF($AD$11<>"",B13,"") | AE14: =IF($AE$11<>"",B13,"") | AF14: =IF($AF$11<>"",B13,"") | AG14: =IF($AG$11<>"",B13,"") | AH14: =IF($AH$11<>"",B13,"") | AI14: =IF($AI$11<>"",B13,"") | AJ14: =IF($AJ$11<>"",B13,"") | AK14: =IF($AK$11<>"",B13,"") | AL14: =IF($AL$11<>"",B13,"") | AM14: =IF($AM$11<>"",B13,"") | AN14: =IF($AN$11<>"",B13,"") | AO14: =IF($AO$11<>"",B13,"") | AP14: =IF($AP$11<>"",B13,"") | AQ14: =IF($AQ$11<>"",B13,"") | AR14: =IF($AR$11<>"",B13,"") | AS14: =IF($AS$11<>"",B13,"") | AT14: =IF($AT$11<>"",B13,"") | AU14: =IF($AU$11<>"",B13,"") | AV14: =IF($AV$11<>"",B13,"") | AW14: =IF($AW$11<>"",B13,"") | AX14: =IF($AX$11<>"",B13,"") | AY14: =IF($AY$11<>"",B13,"") | AZ14: =IF($AZ$11<>"",B13,"") | BA14: =IF($BA$11<>"",B13,"") | BB14: =IF($BB$11<>"",B13,"") | BC14: =IF($BC$11<>"",B13,"") | BD14: =IF($BD$11<>"",B13,"") | BE14: =IF($BE$11<>"",B13,"") | BF14: =IF($BF$11<>"",B13,"") | BG14: =IF($BG$11<>"",B13,"") | BH14: =IF($BH$11<>"",B13,"") | BI14: =IF($BI$11<>"",B13,"") | BJ14: =IF($BJ$11<>"",B13,"") | BK14: =IF($BK$11<>"",B13,"") | BL14: =IF($BL$11<>"",B13,"") | BM14: =IF($BM$11<>"",B13,"") | BN14: =IF($BN$11<>"",B13,"") | BO14: =IF($BO$11<>"",B13,"") | BP14: =IF($BP$11<>"",B13,"") | BQ14: =IF($BQ$11<>"",B13,"") | BR14: =IF($BR$11<>"",B13,"") | BS14: =IF($BS$11<>"",B13,"") | BT14: =IF($BT$11<>"",B13,"") | BU14: =IF($BU$11<>"",B13,"") | BV14: =IF($BV$11<>"",B13,"") | BW14: =IF($BW$11<>"",B13,"") | BX14: =IF($BX$11<>"",B13,"") | BY14: =IF($BY$11<>"",B13,"") | BZ14: =IF($BZ$11<>"",B13,"") | CA14: =IF($CA$11<>"",B13,"") | CB14: =IF($CB$11<>"",B13,"") | CC14: =IF($CC$11<>"",B13,"") | CD14: =IF($CD$11<>"",B13,"") | CE14: =IF($CE$11<>"",B13,"") | CF14: =IF($CF$11<>"",B13,"") | CG14: =IF($CG$11<>"",B13,"") | CH14: =IF($CH$11<>"",B13,"") | CI14: =IF($CI$11<>"",B13,"") | CJ14: =IF($CJ$11<>"",B13,"") | CK14: =IF($CK$11<>"",B13,"") | CL14: =IF($CL$11<>"",B13,"") | CM14: =IF($CM$11<>"",B13,"") | CN14: =IF($CN$11<>"",B13,"") | CO14: =IF($CO$11<>"",B13,"") | CP14: =IF($CP$11<>"",B13,"") | CQ14: =IF($CQ$11<>"",B13,"") | CR14: =IF($CR$11<>"",B13,"") | CS14: =IF(CS13<>"",$B$13,"") | CT14: =IF($CT$11<>"",B13,"") | CU14: =IF($CU$11<>"",B13,"") | CV14: =IF($CV$11<>"",B13,"") | CW14: =IF($CW$11<>"",B13,"") | CX14: =IF($CX$11<>"",B13,"") | CY14: =IF($CY$11<>"",B13,"") | CZ14: =IF($CZ$11<>"",B13,"") | DA14: =IF($DA$11<>"",B13,"") | DB14: =IF($DB$11<>"",B13,"") | DC14: =IF($DC$11<>"",B13,"") | DD14: =IF($DD$11<>"",B13,"") | DE14: =IF($DE$11<>"",B13,"") | DF14: =IF($DF$11<>"",B13,"") | DG14: =IF($DG$11<>"",B13,"") | DH14: =IF($DH$11<>"",B13,"") | DI14: =IF($DI$11<>"",B13,"") | DJ14: =IF($DJ$11<>"",B13,"") | DK14: =IF($DK$11<>"",$B13,"") | DL14: =IF($DL$11<>"",$B13,"") | DM14: =IF($DM$11<>"",$B13,"") | DN14: =IF($DN$11<>"",$B13,"") | DO14: =IF($DO$11<>"",$B13,"") | DP14: =IF($DP$11<>"",$B13,"") | DQ14: =IF($DQ$11<>"",$B13,"") | DR14: =IF($DR$11<>"",$B13,"") | DS14: =IF($DS$11<>"",$B13,"") | DT14: =IF($DT$11<>"",$B13,"") | DU14: =IF($DU$11<>"",$B13,"") | DV14: =IF($DV$11<>"",$B13,"") | DY14: BABY LOOK | DZ14: SYSTEM32 | EA14: A E | EB14: ALGA | EC14: 360 TO TRAVEL
A15: =IF(PEDIDO!C40<>"",PEDIDO!B40,"") | B15: =IF(PEDIDO!X40<>"",PEDIDO!X40,"") | C15: =IF(PEDIDO!AA40<>"",PEDIDO!AA40,"") | D15: =IF(PEDIDO!AD40<>"",PEDIDO!AD40,"") | E15: =IF(PEDIDO!AG40<>"",PEDIDO!AG40,"") | F15: =IF(PEDIDO!AJ40<>"",PEDIDO!AJ40,"") | J15: =IF(PEDIDO!C39<>"",PEDIDO!B39,"") | K15: =IF($K$11<>"",B14,"") | L15: =IF($L$11<>"",B14,"") | M15: =IF($M$11<>"",B14,"") | N15: =IF($N$11<>"",B14,"") | O15: =IF($O$11<>"",B14,"") | P15: =IF($P$11<>"",B14,"") | Q15: =IF($Q$11<>"",B14,"") | R15: =IF($R$11<>"",B14,"") | S15: =IF($S$11<>"",B14,"") | T15: =IF($T$11<>"",B14,"") | U15: =IF($U$11<>"",B14,"") | V15: =IF($V$11<>"",B14,"") | W15: =IF($W$11<>"",B14,"") | X15: =IF($X$11<>"",B14,"") | Y15: =IF($Y$11<>"",B14,"") | Z15: =IF($Z$11<>"",B14,"") | AA15: =IF($AA$11<>"",B14,"") | AB15: =IF($AB$11<>"",B14,"") | AC15: =IF($AC$11<>"",B14,"") | AD15: =IF($AD$11<>"",B14,"") | AE15: =IF($AE$11<>"",B14,"") | AF15: =IF($AF$11<>"",B14,"") | AG15: =IF($AG$11<>"",B14,"") | AH15: =IF($AH$11<>"",B14,"") | AI15: =IF($AI$11<>"",B14,"") | AJ15: =IF($AJ$11<>"",B14,"") | AK15: =IF($AK$11<>"",B14,"") | AL15: =IF($AL$11<>"",B14,"") | AM15: =IF($AM$11<>"",B14,"") | AN15: =IF($AN$11<>"",B14,"") | AO15: =IF($AO$11<>"",B14,"") | AP15: =IF($AP$11<>"",B14,"") | AQ15: =IF($AQ$11<>"",B14,"") | AR15: =IF($AR$11<>"",B14,"") | AS15: =IF($AS$11<>"",B14,"") | AT15: =IF($AT$11<>"",B14,"") | AU15: =IF($AU$11<>"",B14,"") | AV15: =IF($AV$11<>"",B14,"") | AW15: =IF($AW$11<>"",B14,"") | AX15: =IF($AX$11<>"",B14,"") | AY15: =IF($AY$11<>"",B14,"") | AZ15: =IF($AZ$11<>"",B14,"") | BA15: =IF($BA$11<>"",B14,"") | BB15: =IF($BB$11<>"",B14,"") | BC15: =IF($BC$11<>"",B14,"") | BD15: =IF($BD$11<>"",B14,"") | BE15: =IF($BE$11<>"",B14,"") | BF15: =IF($BF$11<>"",B14,"") | BG15: =IF($BG$11<>"",B14,"") | BH15: =IF($BH$11<>"",B14,"") | BI15: =IF($BI$11<>"",B14,"") | BJ15: =IF($BJ$11<>"",B14,"") | BK15: =IF($BK$11<>"",B14,"") | BL15: =IF($BL$11<>"",B14,"") | BM15: =IF($BM$11<>"",B14,"") | BN15: =IF($BN$11<>"",B14,"") | BO15: =IF($BO$11<>"",B14,"") | BP15: =IF($BP$11<>"",B14,"") | BQ15: =IF($BQ$11<>"",B14,"") | BR15: =IF($BR$11<>"",B14,"") | BS15: =IF($BS$11<>"",B14,"") | BT15: =IF($BT$11<>"",B14,"") | BU15: =IF($BU$11<>"",B14,"") | BV15: =IF($BV$11<>"",B14,"") | BW15: =IF($BW$11<>"",B14,"") | BX15: =IF($BX$11<>"",B14,"") | BY15: =IF($BY$11<>"",B14,"") | BZ15: =IF($BZ$11<>"",B14,"") | CA15: =IF($CA$11<>"",B14,"") | CB15: =IF($CB$11<>"",B14,"") | CC15: =IF($CC$11<>"",B14,"") | CD15: =IF($CD$11<>"",B14,"") | CE15: =IF($CE$11<>"",B14,"") | CF15: =IF($CF$11<>"",B14,"") | CG15: =IF($CG$11<>"",B14,"") | CH15: =IF($CH$11<>"",B14,"") | CI15: =IF($CI$11<>"",B14,"") | CJ15: =IF($CJ$11<>"",B14,"") | CK15: =IF($CK$11<>"",B14,"") | CL15: =IF($CL$11<>"",B14,"") | CM15: =IF($CM$11<>"",B14,"") | CN15: =IF($CN$11<>"",B14,"") | CO15: =IF($CO$11<>"",B14,"") | CP15: =IF($CP$11<>"",B14,"") | CQ15: =IF($CQ$11<>"",B14,"") | CR15: =IF($CR$11<>"",B14,"") | CS15: =IF(CS14<>"",$B$14,"") | CT15: =IF($CT$11<>"",B14,"") | CU15: =IF($CU$11<>"",B14,"") | CV15: =IF($CV$11<>"",B14,"") | CW15: =IF($CW$11<>"",B14,"") | CX15: =IF($CX$11<>"",B14,"") | CY15: =IF($CY$11<>"",B14,"") | CZ15: =IF($CZ$11<>"",B14,"") | DA15: =IF($DA$11<>"",B14,"") | DB15: =IF($DB$11<>"",B14,"") | DC15: =IF($DC$11<>"",B14,"") | DD15: =IF($DD$11<>"",B14,"") | DE15: =IF($DE$11<>"",B14,"") | DF15: =IF($DF$11<>"",B14,"") | DG15: =IF($DG$11<>"",B14,"") | DH15: =IF($DH$11<>"",B14,"") | DI15: =IF($DI$11<>"",B14,"") | DJ15: =IF($DJ$11<>"",B14,"") | DK15: =IF($DK$11<>"",$B14,"") | DL15: =IF($DL$11<>"",$B14,"") | DM15: =IF($DM$11<>"",$B14,"") | DN15: =IF($DN$11<>"",$B14,"") | DO15: =IF($DO$11<>"",$B14,"") | DP15: =IF($DP$11<>"",$B14,"") | DQ15: =IF($DQ$11<>"",$B14,"") | DR15: =IF($DR$11<>"",$B14,"") | DS15: =IF($DS$11<>"",$B14,"") | DT15: =IF($DT$11<>"",$B14,"") | DU15: =IF($DU$11<>"",$B14,"") | DV15: =IF($DV$11<>"",$B14,"") | DY15: BABY LOOK INFANTIL | DZ15: BAHIA | EA15: A F FELIPE | EB15: ALGIERS BLUE | EC15: 360 TO WALK
A16: =IF(PEDIDO!C41<>"",PEDIDO!B41,"") | B16: =IF(PEDIDO!X41<>"",PEDIDO!X41,"") | C16: =IF(PEDIDO!AA41<>"",PEDIDO!AA41,"") | D16: =IF(PEDIDO!AD41<>"",PEDIDO!AD41,"") | E16: =IF(PEDIDO!AG41<>"",PEDIDO!AG41,"") | F16: =IF(PEDIDO!AJ41<>"",PEDIDO!AJ41,"") | J16: =IF(PEDIDO!C40<>"",PEDIDO!B40,"") | K16: =IF($K$11<>"",B15,"") | L16: =IF($L$11<>"",B15,"") | M16: =IF($M$11<>"",B15,"") | N16: =IF($N$11<>"",B15,"") | O16: =IF($O$11<>"",B15,"") | P16: =IF($P$11<>"",B15,"") | Q16: =IF($Q$11<>"",B15,"") | R16: =IF($R$11<>"",B15,"") | S16: =IF($S$11<>"",B15,"") | T16: =IF($T$11<>"",B15,"") | U16: =IF($U$11<>"",B15,"") | V16: =IF($V$11<>"",B15,"") | W16: =IF($W$11<>"",B15,"") | X16: =IF($X$11<>"",B15,"") | Y16: =IF($Y$11<>"",B15,"") | Z16: =IF($Z$11<>"",B15,"") | AA16: =IF($AA$11<>"",B15,"") | AB16: =IF($AB$11<>"",B15,"") | AC16: =IF($AC$11<>"",B15,"") | AD16: =IF($AD$11<>"",B15,"") | AE16: =IF($AE$11<>"",B15,"") | AF16: =IF($AF$11<>"",B15,"") | AG16: =IF($AG$11<>"",B15,"") | AH16: =IF($AH$11<>"",B15,"") | AI16: =IF($AI$11<>"",B15,"") | AJ16: =IF($AJ$11<>"",B15,"") | AK16: =IF($AK$11<>"",B15,"") | AL16: =IF($AL$11<>"",B15,"") | AM16: =IF($AM$11<>"",B15,"") | AN16: =IF($AN$11<>"",B15,"") | AO16: =IF($AO$11<>"",B15,"") | AP16: =IF($AP$11<>"",B15,"") | AQ16: =IF($AQ$11<>"",B15,"") | AR16: =IF($AR$11<>"",B15,"") | AS16: =IF($AS$11<>"",B15,"") | AT16: =IF($AT$11<>"",B15,"") | AU16: =IF($AU$11<>"",B15,"") | AV16: =IF($AV$11<>"",B15,"") | AW16: =IF($AW$11<>"",B15,"") | AX16: =IF($AX$11<>"",B15,"") | AY16: =IF($AY$11<>"",B15,"") | AZ16: =IF($AZ$11<>"",B15,"") | BA16: =IF($BA$11<>"",B15,"") | BB16: =IF($BB$11<>"",B15,"") | BC16: =IF($BC$11<>"",B15,"") | BD16: =IF($BD$11<>"",B15,"") | BE16: =IF($BE$11<>"",B15,"") | BF16: =IF($BF$11<>"",B15,"") | BG16: =IF($BG$11<>"",B15,"") | BH16: =IF($BH$11<>"",B15,"") | BI16: =IF($BI$11<>"",B15,"") | BJ16: =IF($BJ$11<>"",B15,"") | BK16: =IF($BK$11<>"",B15,"") | BL16: =IF($BL$11<>"",B15,"") | BM16: =IF($BM$11<>"",B15,"") | BN16: =IF($BN$11<>"",B15,"") | BO16: =IF($BO$11<>"",B15,"") | BP16: =IF($BP$11<>"",B15,"") | BQ16: =IF($BQ$11<>"",B15,"") | BR16: =IF($BR$11<>"",B15,"") | BS16: =IF($BS$11<>"",B15,"") | BT16: =IF($BT$11<>"",B15,"") | BU16: =IF($BU$11<>"",B15,"") | BV16: =IF($BV$11<>"",B15,"") | BW16: =IF($BW$11<>"",B15,"") | BX16: =IF($BX$11<>"",B15,"") | BY16: =IF($BY$11<>"",B15,"") | BZ16: =IF($BZ$11<>"",B15,"") | CA16: =IF($CA$11<>"",B15,"") | CB16: =IF($CB$11<>"",B15,"") | CC16: =IF($CC$11<>"",B15,"") | CD16: =IF($CD$11<>"",B15,"") | CE16: =IF($CE$11<>"",B15,"") | CF16: =IF($CF$11<>"",B15,"") | CG16: =IF($CG$11<>"",B15,"") | CH16: =IF($CH$11<>"",B15,"") | CI16: =IF($CI$11<>"",B15,"") | CJ16: =IF($CJ$11<>"",B15,"") | CK16: =IF($CK$11<>"",B15,"") | CL16: =IF($CL$11<>"",B15,"") | CM16: =IF($CM$11<>"",B15,"") | CN16: =IF($CN$11<>"",B15,"") | CO16: =IF($CO$11<>"",B15,"") | CP16: =IF($CP$11<>"",B15,"") | CQ16: =IF($CQ$11<>"",B15,"") | CR16: =IF($CR$11<>"",B15,"") | CS16: =IF(CS15<>"",$B$15,"") | CT16: =IF($CT$11<>"",B15,"") | CU16: =IF($CU$11<>"",B15,"") | CV16: =IF($CV$11<>"",B15,"") | CW16: =IF($CW$11<>"",B15,"") | CX16: =IF($CX$11<>"",B15,"") | CY16: =IF($CY$11<>"",B15,"") | CZ16: =IF($CZ$11<>"",B15,"") | DA16: =IF($DA$11<>"",B15,"") | DB16: =IF($DB$11<>"",B15,"") | DC16: =IF($DC$11<>"",B15,"") | DD16: =IF($DD$11<>"",B15,"") | DE16: =IF($DE$11<>"",B15,"") | DF16: =IF($DF$11<>"",B15,"") | DG16: =IF($DG$11<>"",B15,"") | DH16: =IF($DH$11<>"",B15,"") | DI16: =IF($DI$11<>"",B15,"") | DJ16: =IF($DJ$11<>"",B15,"") | DK16: =IF($DK$11<>"",$B15,"") | DL16: =IF($DL$11<>"",$B15,"") | DM16: =IF($DM$11<>"",$B15,"") | DN16: =IF($DN$11<>"",$B15,"") | DO16: =IF($DO$11<>"",$B15,"") | DP16: =IF($DP$11<>"",$B15,"") | DQ16: =IF($DQ$11<>"",$B15,"") | DR16: =IF($DR$11<>"",$B15,"") | DS16: =IF($DS$11<>"",$B15,"") | DT16: =IF($DT$11<>"",$B15,"") | DU16: =IF($DU$11<>"",$B15,"") | DV16: =IF($DV$11<>"",$B15,"") | DY16: BAG | DZ16: NEW BALANCE | EA16: A PÉ | EB16: ALGODAO | EC16: 360 ZAFIRA 2T
A17: =IF(PEDIDO!C42<>"",PEDIDO!B42,"") | B17: =IF(PEDIDO!X42<>"",PEDIDO!X42,"") | C17: =IF(PEDIDO!AA42<>"",PEDIDO!AA42,"") | D17: =IF(PEDIDO!AD42<>"",PEDIDO!AD42,"") | E17: =IF(PEDIDO!AG42<>"",PEDIDO!AG42,"") | F17: =IF(PEDIDO!AJ42<>"",PEDIDO!AJ42,"") | J17: =IF(PEDIDO!C41<>"",PEDIDO!B41,"") | K17: =IF($K$11<>"",B16,"") | L17: =IF($L$11<>"",B16,"") | M17: =IF($M$11<>"",B16,"") | N17: =IF($N$11<>"",B16,"") | O17: =IF($O$11<>"",B16,"") | P17: =IF($P$11<>"",B16,"") | Q17: =IF($Q$11<>"",B16,"") | R17: =IF($R$11<>"",B16,"") | S17: =IF($S$11<>"",B16,"") | T17: =IF($T$11<>"",B16,"") | U17: =IF($U$11<>"",B16,"") | V17: =IF($V$11<>"",B16,"") | W17: =IF($W$11<>"",B16,"") | X17: =IF($X$11<>"",B16,"") | Y17: =IF($Y$11<>"",B16,"") | Z17: =IF($Z$11<>"",B16,"") | AA17: =IF($AA$11<>"",B16,"") | AB17: =IF($AB$11<>"",B16,"") | AC17: =IF($AC$11<>"",B16,"") | AD17: =IF($AD$11<>"",B16,"") | AE17: =IF($AE$11<>"",B16,"") | AF17: =IF($AF$11<>"",B16,"") | AG17: =IF($AG$11<>"",B16,"") | AH17: =IF($AH$11<>"",B16,"") | AI17: =IF($AI$11<>"",B16,"") | AJ17: =IF($AJ$11<>"",B16,"") | AK17: =IF($AK$11<>"",B16,"") | AL17: =IF($AL$11<>"",B16,"") | AM17: =IF($AM$11<>"",B16,"") | AN17: =IF($AN$11<>"",B16,"") | AO17: =IF($AO$11<>"",B16,"") | AP17: =IF($AP$11<>"",B16,"") | AQ17: =IF($AQ$11<>"",B16,"") | AR17: =IF($AR$11<>"",B16,"") | AS17: =IF($AS$11<>"",B16,"") | AT17: =IF($AT$11<>"",B16,"") | AU17: =IF($AU$11<>"",B16,"") | AV17: =IF($AV$11<>"",B16,"") | AW17: =IF($AW$11<>"",B16,"") | AX17: =IF($AX$11<>"",B16,"") | AY17: =IF($AY$11<>"",B16,"") | AZ17: =IF($AZ$11<>"",B16,"") | BA17: =IF($BA$11<>"",B16,"") | BB17: =IF($BB$11<>"",B16,"") | BC17: =IF($BC$11<>"",B16,"") | BD17: =IF($BD$11<>"",B16,"") | BE17: =IF($BE$11<>"",B16,"") | BF17: =IF($BF$11<>"",B16,"") | BG17: =IF($BG$11<>"",B16,"") | BH17: =IF($BH$11<>"",B16,"") | BI17: =IF($BI$11<>"",B16,"") | BJ17: =IF($BJ$11<>"",B16,"") | BK17: =IF($BK$11<>"",B16,"") | BL17: =IF($BL$11<>"",B16,"") | BM17: =IF($BM$11<>"",B16,"") | BN17: =IF($BN$11<>"",B16,"") | BO17: =IF($BO$11<>"",B16,"") | BP17: =IF($BP$11<>"",B16,"") | BQ17: =IF($BQ$11<>"",B16,"") | BR17: =IF($BR$11<>"",B16,"") | BS17: =IF($BS$11<>"",B16,"") | BT17: =IF($BT$11<>"",B16,"") | BU17: =IF($BU$11<>"",B16,"") | BV17: =IF($BV$11<>"",B16,"") | BW17: =IF($BW$11<>"",B16,"") | BX17: =IF($BX$11<>"",B16,"") | BY17: =IF($BY$11<>"",B16,"") | BZ17: =IF($BZ$11<>"",B16,"") | CA17: =IF($CA$11<>"",B16,"") | CB17: =IF($CB$11<>"",B16,"") | CC17: =IF($CC$11<>"",B16,"") | CD17: =IF($CD$11<>"",B16,"") | CE17: =IF($CE$11<>"",B16,"") | CF17: =IF($CF$11<>"",B16,"") | CG17: =IF($CG$11<>"",B16,"") | CH17: =IF($CH$11<>"",B16,"") | CI17: =IF($CI$11<>"",B16,"") | CJ17: =IF($CJ$11<>"",B16,"") | CK17: =IF($CK$11<>"",B16,"") | CL17: =IF($CL$11<>"",B16,"") | CM17: =IF($CM$11<>"",B16,"") | CN17: =IF($CN$11<>"",B16,"") | CO17: =IF($CO$11<>"",B16,"") | CP17: =IF($CP$11<>"",B16,"") | CQ17: =IF($CQ$11<>"",B16,"") | CR17: =IF($CR$11<>"",B16,"") | CS17: =IF(CS16<>"",B$16,"") | CT17: =IF($CT$11<>"",B16,"") | CU17: =IF($CU$11<>"",B16,"") | CV17: =IF($CV$11<>"",B16,"") | CW17: =IF($CW$11<>"",B16,"") | CX17: =IF($CX$11<>"",B16,"") | CY17: =IF($CY$11<>"",B16,"") | CZ17: =IF($CZ$11<>"",B16,"") | DA17: =IF($DA$11<>"",B16,"") | DB17: =IF($DB$11<>"",B16,"") | DC17: =IF($DC$11<>"",B16,"") | DD17: =IF($DD$11<>"",B16,"") | DE17: =IF($DE$11<>"",B16,"") | DF17: =IF($DF$11<>"",B16,"") | DG17: =IF($DG$11<>"",B16,"") | DH17: =IF($DH$11<>"",B16,"") | DI17: =IF($DI$11<>"",B16,"") | DJ17: =IF($DJ$11<>"",B16,"") | DK17: =IF($DK$11<>"",$B16,"") | DL17: =IF($DL$11<>"",$B16,"") | DM17: =IF($DM$11<>"",$B16,"") | DN17: =IF($DN$11<>"",$B16,"") | DO17: =IF($DO$11<>"",$B16,"") | DP17: =IF($DP$11<>"",$B16,"") | DQ17: =IF($DQ$11<>"",$B16,"") | DR17: =IF($DR$11<>"",$B16,"") | DS17: =IF($DS$11<>"",$B16,"") | DT17: =IF($DT$11<>"",$B16,"") | DU17: =IF($DU$11<>"",$B16,"") | DV17: =IF($DV$11<>"",$B16,"") | DY17: BANCO | DZ17: SOCIALLE | EA17: A&E | EB17: ALIGATOR | EC17: 360 ZIGMA
A18: =IF(PEDIDO!C43<>"",PEDIDO!B43,"") | B18: =IF(PEDIDO!X43<>"",PEDIDO!X43,"") | C18: =IF(PEDIDO!AA43<>"",PEDIDO!AA43,"") | D18: =IF(PEDIDO!AD43<>"",PEDIDO!AD43,"") | E18: =IF(PEDIDO!AG43<>"",PEDIDO!AG43,"") | F18: =IF(PEDIDO!AJ43<>"",PEDIDO!AJ43,"") | J18: =IF(PEDIDO!C42<>"",PEDIDO!B42,"") | K18: =IF($K$11<>"",B17,"") | L18: =IF($L$11<>"",B17,"") | M18: =IF($M$11<>"",B17,"") | N18: =IF($N$11<>"",B17,"") | O18: =IF($O$11<>"",B17,"") | P18: =IF($P$11<>"",B17,"") | Q18: =IF($Q$11<>"",B17,"") | R18: =IF($R$11<>"",B17,"") | S18: =IF($S$11<>"",B17,"") | T18: =IF($T$11<>"",B17,"") | U18: =IF($U$11<>"",B17,"") | V18: =IF($V$11<>"",B17,"") | X18: =IF($X$11<>"",B17,"") | Y18: =IF($Y$11<>"",B17,"") | Z18: =IF($Z$11<>"",B17,"") | AA18: =IF($AA$11<>"",B17,"") | AB18: =IF($AB$11<>"",B17,"") | AC18: =IF($AC$11<>"",B17,"") | AD18: =IF($AD$11<>"",B17,"") | AE18: =IF($AE$11<>"",B17,"") | AF18: =IF($AF$11<>"",B17,"") | AG18: =IF($AG$11<>"",B17,"") | AH18: =IF($AH$11<>"",B17,"") | AI18: =IF($AI$11<>"",B17,"") | AJ18: =IF($AJ$11<>"",B17,"") | AK18: =IF($AK$11<>"",B17,"") | AL18: =IF($AL$11<>"",B17,"") | AM18: =IF($AM$11<>"",B17,"") | AN18: =IF($AN$11<>"",B17,"") | AO18: =IF($AO$11<>"",B17,"") | AP18: =IF($AP$11<>"",B17,"") | AQ18: =IF($AQ$11<>"",B17,"") | AR18: =IF($AR$11<>"",B17,"") | AS18: =IF($AS$11<>"",B17,"") | AT18: =IF($AT$11<>"",B17,"") | AU18: =IF($AU$11<>"",B17,"") | AV18: =IF($AV$11<>"",B17,"") | AW18: =IF($AW$11<>"",B17,"") | AX18: =IF($AX$11<>"",B17,"") | AY18: =IF($AY$11<>"",B17,"") | AZ18: =IF($AZ$11<>"",B17,"") | BA18: =IF($BA$11<>"",B17,"") | BB18: =IF($BB$11<>"",B17,"") | BC18: =IF($BC$11<>"",B17,"") | BD18: =IF($BD$11<>"",B17,"") | BE18: =IF($BE$11<>"",B17,"") | BF18: =IF($BF$11<>"",B17,"") | BG18: =IF($BG$11<>"",B17,"") | BH18: =IF($BH$11<>"",B17,"") | BI18: =IF($BI$11<>"",B17,"") | BJ18: =IF($BJ$11<>"",B17,"") | BK18: =IF($BK$11<>"",B17,"") | BL18: =IF($BL$11<>"",B17,"") | BM18: =IF($BM$11<>"",B17,"") | BN18: =IF($BN$11<>"",B17,"") | BO18: =IF($BO$11<>"",B17,"") | BP18: =IF($BP$11<>"",B17,"") | BQ18: =IF($BQ$11<>"",B17,"") | BR18: =IF($BR$11<>"",B17,"") | BS18: =IF($BS$11<>"",B17,"") | BT18: =IF($BT$11<>"",B17,"") | BU18: =IF($BU$11<>"",B17,"") | BV18: =IF($BV$11<>"",B17,"") | BW18: =IF($BW$11<>"",B17,"") | BX18: =IF($BX$11<>"",B17,"") | BY18: =IF($BY$11<>"",B17,"") | BZ18: =IF($BZ$11<>"",B17,"") | CA18: =IF($CA$11<>"",B17,"") | CB18: =IF($CB$11<>"",B17,"") | CC18: =IF($CC$11<>"",B17,"") | CD18: =IF($CD$11<>"",B17,"") | CE18: =IF($CE$11<>"",B17,"") | CF18: =IF($CF$11<>"",B17,"") | CG18: =IF($CG$11<>"",B17,"") | CH18: =IF($CH$11<>"",B17,"") | CI18: =IF($CI$11<>"",B17,"") | CJ18: =IF($CJ$11<>"",B17,"") | CK18: =IF($CK$11<>"",B17,"") | CL18: =IF($CL$11<>"",B17,"") | CM18: =IF($CM$11<>"",B17,"") | CN18: =IF($CN$11<>"",B17,"") | CO18: =IF($CO$11<>"",B17,"") | CP18: =IF($CP$11<>"",B17,"") | CQ18: =IF($CQ$11<>"",B17,"") | CR18: =IF($CR$11<>"",B17,"") | CS18: =IF(CS17<>"",B$17,"") | CT18: =IF($CT$11<>"",B17,"") | CU18: =IF($CU$11<>"",B17,"") | CV18: =IF($CV$11<>"",B17,"") | CW18: =IF($CW$11<>"",B17,"") | CX18: =IF($CX$11<>"",B17,"") | CY18: =IF($CY$11<>"",B17,"") | CZ18: =IF($CZ$11<>"",B17,"") | DA18: =IF($DA$11<>"",B17,"") | DB18: =IF($DB$11<>"",B17,"") | DC18: =IF($DC$11<>"",B17,"") | DD18: =IF($DD$11<>"",B17,"") | DE18: =IF($DE$11<>"",B17,"") | DF18: =IF($DF$11<>"",B17,"") | DG18: =IF($DG$11<>"",B17,"") | DH18: =IF($DH$11<>"",B17,"") | DI18: =IF($DI$11<>"",B17,"") | DJ18: =IF($DJ$11<>"",B17,"") | DK18: =IF($DK$11<>"",$B17,"") | DL18: =IF($DL$11<>"",$B17,"") | DM18: =IF($DM$11<>"",$B17,"") | DN18: =IF($DN$11<>"",$B17,"") | DO18: =IF($DO$11<>"",$B17,"") | DP18: =IF($DP$11<>"",$B17,"") | DQ18: =IF($DQ$11<>"",$B17,"") | DR18: =IF($DR$11<>"",$B17,"") | DS18: =IF($DS$11<>"",$B17,"") | DT18: =IF($DT$11<>"",$B17,"") | DU18: =IF($DU$11<>"",$B17,"") | DV18: =IF($DV$11<>"",$B17,"") | DY18: BANDANA | DZ18: AMARLO LTDA | EA18: A1 | EB18: ALL BLACK | EC18: 530 ML
A19: =IF(PEDIDO!C44<>"",PEDIDO!B44,"") | B19: =IF(PEDIDO!X44<>"",PEDIDO!X44,"") | C19: =IF(PEDIDO!AA44<>"",PEDIDO!AA44,"") | D19: =IF(PEDIDO!AD44<>"",PEDIDO!AD44,"") | E19: =IF(PEDIDO!AG44<>"",PEDIDO!AG44,"") | F19: =IF(PEDIDO!AJ44<>"",PEDIDO!AJ44,"") | J19: =IF(PEDIDO!C43<>"",PEDIDO!B43,"") | K19: =IF($K$11<>"",B18,"") | L19: =IF($L$11<>"",B18,"") | M19: =IF($M$11<>"",B18,"") | N19: =IF($N$11<>"",B18,"") | O19: =IF($O$11<>"",B18,"") | P19: =IF($P$11<>"",B18,"") | Q19: =IF($Q$11<>"",B18,"") | R19: =IF($R$11<>"",B18,"") | S19: =IF($S$11<>"",B18,"") | T19: =IF($T$11<>"",B18,"") | U19: =IF($U$11<>"",B18,"") | V19: =IF($V$11<>"",B18,"") | X19: =IF($X$11<>"",B18,"") | Y19: =IF($Y$11<>"",B18,"") | Z19: =IF($Z$11<>"",B18,"") | AA19: =IF($AA$11<>"",B18,"") | AB19: =IF($AB$11<>"",B18,"") | AC19: =IF($AC$11<>"",B18,"") | AD19: =IF($AD$11<>"",B18,"") | AE19: =IF($AE$11<>"",B18,"") | AF19: =IF($AF$11<>"",B18,"") | AG19: =IF($AG$11<>"",B18,"") | AH19: =IF($AH$11<>"",B18,"") | AI19: =IF($AI$11<>"",B18,"") | AJ19: =IF($AJ$11<>"",B18,"") | AK19: =IF($AK$11<>"",B18,"") | AL19: =IF($AL$11<>"",B18,"") | AM19: =IF($AM$11<>"",B18,"") | AN19: =IF($AN$11<>"",B18,"") | AO19: =IF($AO$11<>"",B18,"") | AP19: =IF($AP$11<>"",B18,"") | AQ19: =IF($AQ$11<>"",B18,"") | AR19: =IF($AR$11<>"",B18,"") | AS19: =IF($AS$11<>"",B18,"") | AT19: =IF($AT$11<>"",B18,"") | AU19: =IF($AU$11<>"",B18,"") | AV19: =IF($AV$11<>"",B18,"") | AW19: =IF($AW$11<>"",B18,"") | AX19: =IF($AX$11<>"",B18,"") | AY19: =IF($AY$11<>"",B18,"") | AZ19: =IF($AZ$11<>"",B18,"") | BA19: =IF($BA$11<>"",B18,"") | BB19: =IF($BB$11<>"",B18,"") | BC19: =IF($BC$11<>"",B18,"") | BD19: =IF($BD$11<>"",B18,"") | BE19: =IF($BE$11<>"",B18,"") | BF19: =IF($BF$11<>"",B18,"") | BG19: =IF($BG$11<>"",B18,"") | BH19: =IF($BH$11<>"",B18,"") | BI19: =IF($BI$11<>"",B18,"") | BJ19: =IF($BJ$11<>"",B18,"") | BK19: =IF($BK$11<>"",B18,"") | BL19: =IF($BL$11<>"",B18,"") | BM19: =IF($BM$11<>"",B18,"") | BN19: =IF($BN$11<>"",B18,"") | BO19: =IF($BO$11<>"",B18,"") | BP19: =IF($BP$11<>"",B18,"") | BQ19: =IF($BQ$11<>"",B18,"") | BR19: =IF($BR$11<>"",B18,"") | BS19: =IF($BS$11<>"",B18,"") | BT19: =IF($BT$11<>"",B18,"") | BU19: =IF($BU$11<>"",B18,"") | BV19: =IF($BV$11<>"",B18,"") | BW19: =IF($BW$11<>"",B18,"") | BX19: =IF($BX$11<>"",B18,"") | BY19: =IF($BY$11<>"",B18,"") | BZ19: =IF($BZ$11<>"",B18,"") | CA19: =IF($CA$11<>"",B18,"") | CB19: =IF($CB$11<>"",B18,"") | CC19: =IF($CC$11<>"",B18,"") | CD19: =IF($CD$11<>"",B18,"") | CE19: =IF($CE$11<>"",B18,"") | CF19: =IF($CF$11<>"",B18,"") | CG19: =IF($CG$11<>"",B18,"") | CH19: =IF($CH$11<>"",B18,"") | CI19: =IF($CI$11<>"",B18,"") | CJ19: =IF($CJ$11<>"",B18,"") | CK19: =IF($CK$11<>"",B18,"") | CL19: =IF($CL$11<>"",B18,"") | CM19: =IF($CM$11<>"",B18,"") | CN19: =IF($CN$11<>"",B18,"") | CO19: =IF($CO$11<>"",B18,"") | CP19: =IF($CP$11<>"",B18,"") | CQ19: =IF($CQ$11<>"",B18,"") | CR19: =IF($CR$11<>"",B18,"") | CS19: =IF(CS18<>"",$B18,"") | CT19: =IF($CT$11<>"",B18,"") | CU19: =IF($CU$11<>"",B18,"") | CV19: =IF($CV$11<>"",B18,"") | CW19: =IF($CW$11<>"",B18,"") | CX19: =IF($CX$11<>"",B18,"") | CY19: =IF($CY$11<>"",B18,"") | CZ19: =IF($CZ$11<>"",B18,"") | DA19: =IF($DA$11<>"",B18,"") | DB19: =IF($DB$11<>"",B18,"") | DC19: =IF($DC$11<>"",B18,"") | DD19: =IF($DD$11<>"",B18,"") | DE19: =IF($DE$11<>"",B18,"") | DF19: =IF($DF$11<>"",B18,"") | DG19: =IF($DG$11<>"",B18,"") | DH19: =IF($DH$11<>"",B18,"") | DI19: =IF($DI$11<>"",B18,"") | DJ19: =IF($DJ$11<>"",B18,"") | DK19: =IF($DK$11<>"",$B18,"") | DL19: =IF($DL$11<>"",$B18,"") | DM19: =IF($DM$11<>"",$B18,"") | DN19: =IF($DN$11<>"",$B18,"") | DO19: =IF($DO$11<>"",$B18,"") | DP19: =IF($DP$11<>"",$B18,"") | DQ19: =IF($DQ$11<>"",$B18,"") | DR19: =IF($DR$11<>"",$B18,"") | DS19: =IF($DS$11<>"",$B18,"") | DT19: =IF($DT$11<>"",$B18,"") | DU19: =IF($DU$11<>"",$B18,"") | DV19: =IF($DV$11<>"",$B18,"") | DY19: BATA | DZ19: KAPAZI | EA19: A7SK | EB19: ALL WHITE | EC19: 680ML
A20: =IF(PEDIDO!C45<>"",PEDIDO!B45,"") | B20: =IF(PEDIDO!X45<>"",PEDIDO!X45,"") | C20: =IF(PEDIDO!AA45<>"",PEDIDO!AA45,"") | D20: =IF(PEDIDO!AD45<>"",PEDIDO!AD45,"") | E20: =IF(PEDIDO!AG45<>"",PEDIDO!AG45,"") | F20: =IF(PEDIDO!AJ45<>"",PEDIDO!AJ45,"") | J20: =IF(PEDIDO!C44<>"",PEDIDO!B44,"") | K20: =IF($K$11<>"",B19,"") | L20: =IF($L$11<>"",B19,"") | M20: =IF($M$11<>"",B19,"") | N20: =IF($N$11<>"",B19,"") | O20: =IF($O$11<>"",B19,"") | P20: =IF($P$11<>"",B19,"") | Q20: =IF($Q$11<>"",B19,"") | R20: =IF($R$11<>"",B19,"") | S20: =IF($S$11<>"",B19,"") | T20: =IF($T$11<>"",B19,"") | U20: =IF($U$11<>"",B19,"") | V20: =IF($V$11<>"",B19,"") | X20: =IF($X$11<>"",B19,"") | Y20: =IF($Y$11<>"",B19,"") | Z20: =IF($Z$11<>"",B19,"") | AA20: =IF($AA$11<>"",B19,"") | AB20: =IF($AB$11<>"",B19,"") | AC20: =IF($AC$11<>"",B19,"") | AD20: =IF($AD$11<>"",B19,"") | AE20: =IF($AE$11<>"",B19,"") | AF20: =IF($AF$11<>"",B19,"") | AG20: =IF($AG$11<>"",B19,"") | AH20: =IF($AH$11<>"",B19,"") | AI20: =IF($AI$11<>"",B19,"") | AJ20: =IF($AJ$11<>"",B19,"") | AK20: =IF($AK$11<>"",B19,"") | AL20: =IF($AL$11<>"",B19,"") | AM20: =IF($AM$11<>"",B19,"") | AN20: =IF($AN$11<>"",B19,"") | AO20: =IF($AO$11<>"",B19,"") | AP20: =IF($AP$11<>"",B19,"") | AQ20: =IF($AQ$11<>"",B19,"") | AR20: =IF($AR$11<>"",B19,"") | AS20: =IF($AS$11<>"",B19,"") | AT20: =IF($AT$11<>"",B19,"") | AU20: =IF($AU$11<>"",B19,"") | AV20: =IF($AV$11<>"",B19,"") | AW20: =IF($AW$11<>"",B19,"") | AX20: =IF($AX$11<>"",B19,"") | AY20: =IF($AY$11<>"",B19,"") | AZ20: =IF($AZ$11<>"",B19,"") | BA20: =IF($BA$11<>"",B19,"") | BB20: =IF($BB$11<>"",B19,"") | BC20: =IF($BC$11<>"",B19,"") | BD20: =IF($BD$11<>"",B19,"") | BE20: =IF($BE$11<>"",B19,"") | BF20: =IF($BF$11<>"",B19,"") | BG20: =IF($BG$11<>"",B19,"") | BH20: =IF($BH$11<>"",B19,"") | BI20: =IF($BI$11<>"",B19,"") | BJ20: =IF($BJ$11<>"",B19,"") | BK20: =IF($BK$11<>"",B19,"") | BL20: =IF($BL$11<>"",B19,"") | BM20: =IF($BM$11<>"",B19,"") | BN20: =IF($BN$11<>"",B19,"") | BO20: =IF($BO$11<>"",B19,"") | BP20: =IF($BP$11<>"",B19,"") | BQ20: =IF($BQ$11<>"",B19,"") | BR20: =IF($BR$11<>"",B19,"") | BS20: =IF($BS$11<>"",B19,"") | BT20: =IF($BT$11<>"",B19,"") | BU20: =IF($BU$11<>"",B19,"") | BV20: =IF($BV$11<>"",B19,"") | BW20: =IF($BW$11<>"",B19,"") | BX20: =IF($BX$11<>"",B19,"") | BY20: =IF($BY$11<>"",B19,"") | BZ20: =IF($BZ$11<>"",B19,"") | CA20: =IF($CA$11<>"",B19,"") | CB20: =IF($CB$11<>"",B19,"") | CC20: =IF($CC$11<>"",B19,"") | CD20: =IF($CD$11<>"",B19,"") | CE20: =IF($CE$11<>"",B19,"") | CF20: =IF($CF$11<>"",B19,"") | CG20: =IF($CG$11<>"",B19,"") | CH20: =IF($CH$11<>"",B19,"") | CI20: =IF($CI$11<>"",B19,"") | CJ20: =IF($CJ$11<>"",B19,"") | CK20: =IF($CK$11<>"",B19,"") | CL20: =IF($CL$11<>"",B19,"") | CM20: =IF($CM$11<>"",B19,"") | CN20: =IF($CN$11<>"",B19,"") | CO20: =IF($CO$11<>"",B19,"") | CP20: =IF($CP$11<>"",B19,"") | CQ20: =IF($CQ$11<>"",B19,"") | CR20: =IF($CR$11<>"",B19,"") | CS20: =IF(CS19<>"",B$19,"") | CT20: =IF($CT$11<>"",B19,"") | CU20: =IF($CU$11<>"",B19,"") | CV20: =IF($CV$11<>"",B19,"") | CW20: =IF($CW$11<>"",B19,"") | CX20: =IF($CX$11<>"",B19,"") | CY20: =IF($CY$11<>"",B19,"") | CZ20: =IF($CZ$11<>"",B19,"") | DA20: =IF($DA$11<>"",B19,"") | DB20: =IF($DB$11<>"",B19,"") | DC20: =IF($DC$11<>"",B19,"") | DD20: =IF($DD$11<>"",B19,"") | DE20: =IF($DE$11<>"",B19,"") | DF20: =IF($DF$11<>"",B19,"") | DG20: =IF($DG$11<>"",B19,"") | DH20: =IF($DH$11<>"",B19,"") | DI20: =IF($DI$11<>"",B19,"") | DJ20: =IF($DJ$11<>"",B19,"") | DK20: =IF($DK$11<>"",$B19,"") | DL20: =IF($DL$11<>"",$B19,"") | DM20: =IF($DM$11<>"",$B19,"") | DN20: =IF($DN$11<>"",$B19,"") | DO20: =IF($DO$11<>"",$B19,"") | DP20: =IF($DP$11<>"",$B19,"") | DQ20: =IF($DQ$11<>"",$B19,"") | DR20: =IF($DR$11<>"",$B19,"") | DS20: =IF($DS$11<>"",$B19,"") | DT20: =IF($DT$11<>"",$B19,"") | DU20: =IF($DU$11<>"",$B19,"") | DV20: =IF($DV$11<>"",$B19,"") | DY20: BATA INFANTIL | DZ20: REAL CALCADOS - LOJA 11 | EA20: ABC DA CONSTRUCAO | EB20: ALLOY | EC20: 700ML
A21: =IF(PEDIDO!C46<>"",PEDIDO!B46,"") | B21: =IF(PEDIDO!X46<>"",PEDIDO!X46,"") | C21: =IF(PEDIDO!AA46<>"",PEDIDO!AA46,"") | D21: =IF(PEDIDO!AD46<>"",PEDIDO!AD46,"") | E21: =IF(PEDIDO!AG46<>"",PEDIDO!AG46,"") | F21: =IF(PEDIDO!AJ46<>"",PEDIDO!AJ46,"") | J21: =IF(PEDIDO!C45<>"",PEDIDO!B45,"") | K21: =IF($K$11<>"",B20,"") | L21: =IF($L$11<>"",B20,"") | M21: =IF($M$11<>"",B20,"") | N21: =IF($N$11<>"",B20,"") | O21: =IF($O$11<>"",B20,"") | P21: =IF($P$11<>"",B20,"") | Q21: =IF($Q$11<>"",B20,"") | R21: =IF($R$11<>"",B20,"") | S21: =IF($S$11<>"",B20,"") | T21: =IF($T$11<>"",B20,"") | U21: =IF($U$11<>"",B20,"") | V21: =IF($V$11<>"",B20,"") | X21: =IF($X$11<>"",B20,"") | Y21: =IF($Y$11<>"",B20,"") | Z21: =IF($Z$11<>"",B20,"") | AA21: =IF($AA$11<>"",B20,"") | AB21: =IF($AB$11<>"",B20,"") | AC21: =IF($AC$11<>"",B20,"") | AD21: =IF($AD$11<>"",B20,"") | AE21: =IF($AE$11<>"",B20,"") | AF21: =IF($AF$11<>"",B20,"") | AG21: =IF($AG$11<>"",B20,"") | AH21: =IF($AH$11<>"",B20,"") | AI21: =IF($AI$11<>"",B20,"") | AJ21: =IF($AJ$11<>"",B20,"") | AK21: =IF($AK$11<>"",B20,"") | AL21: =IF($AL$11<>"",B20,"") | AM21: =IF($AM$11<>"",B20,"") | AN21: =IF($AN$11<>"",B20,"") | AO21: =IF($AO$11<>"",B20,"") | AP21: =IF($AP$11<>"",B20,"") | AQ21: =IF($AQ$11<>"",B20,"") | AR21: =IF($AR$11<>"",B20,"") | AS21: =IF($AS$11<>"",B20,"") | AT21: =IF($AT$11<>"",B20,"") | AU21: =IF($AU$11<>"",B20,"") | AV21: =IF($AV$11<>"",B20,"") | AW21: =IF($AW$11<>"",B20,"") | AX21: =IF($AX$11<>"",B20,"") | AY21: =IF($AY$11<>"",B20,"") | AZ21: =IF($AZ$11<>"",B20,"") | BA21: =IF($BA$11<>"",B20,"") | BB21: =IF($BB$11<>"",B20,"") | BC21: =IF($BC$11<>"",B20,"") | BD21: =IF($BD$11<>"",B20,"") | BE21: =IF($BE$11<>"",B20,"") | BF21: =IF($BF$11<>"",B20,"") | BG21: =IF($BG$11<>"",B20,"") | BH21: =IF($BH$11<>"",B20,"") | BI21: =IF($BI$11<>"",B20,"") | BJ21: =IF($BJ$11<>"",B20,"") | BK21: =IF($BK$11<>"",B20,"") | BL21: =IF($BL$11<>"",B20,"") | BM21: =IF($BM$11<>"",B20,"") | BN21: =IF($BN$11<>"",B20,"") | BO21: =IF($BO$11<>"",B20,"") | BP21: =IF($BP$11<>"",B20,"") | BQ21: =IF($BQ$11<>"",B20,"") | BR21: =IF($BR$11<>"",B20,"") | BS21: =IF($BS$11<>"",B20,"") | BT21: =IF($BT$11<>"",B20,"") | BU21: =IF($BU$11<>"",B20,"") | BV21: =IF($BV$11<>"",B20,"") | BW21: =IF($BW$11<>"",B20,"") | BX21: =IF($BX$11<>"",B20,"") | BY21: =IF($BY$11<>"",B20,"") | BZ21: =IF($BZ$11<>"",B20,"") | CA21: =IF($CA$11<>"",B20,"") | CB21: =IF($CB$11<>"",B20,"") | CC21: =IF($CC$11<>"",B20,"") | CD21: =IF($CD$11<>"",B20,"") | CE21: =IF($CE$11<>"",B20,"") | CF21: =IF($CF$11<>"",B20,"") | CG21: =IF($CG$11<>"",B20,"") | CH21: =IF($CH$11<>"",B20,"") | CI21: =IF($CI$11<>"",B20,"") | CJ21: =IF($CJ$11<>"",B20,"") | CK21: =IF($CK$11<>"",B20,"") | CL21: =IF($CL$11<>"",B20,"") | CM21: =IF($CM$11<>"",B20,"") | CN21: =IF($CN$11<>"",B20,"") | CO21: =IF($CO$11<>"",B20,"") | CP21: =IF($CP$11<>"",B20,"") | CQ21: =IF($CQ$11<>"",B20,"") | CR21: =IF($CR$11<>"",B20,"") | CS21: =IF(CS20<>"",B$20,"") | CT21: =IF($CT$11<>"",B20,"") | CU21: =IF($CU$11<>"",B20,"") | CV21: =IF($CV$11<>"",B20,"") | CW21: =IF($CW$11<>"",B20,"") | CX21: =IF($CX$11<>"",B20,"") | CY21: =IF($CY$11<>"",B20,"") | CZ21: =IF($CZ$11<>"",B20,"") | DA21: =IF($DA$11<>"",B20,"") | DB21: =IF($DB$11<>"",B20,"") | DC21: =IF($DC$11<>"",B20,"") | DD21: =IF($DD$11<>"",B20,"") | DE21: =IF($DE$11<>"",B20,"") | DF21: =IF($DF$11<>"",B20,"") | DG21: =IF($DG$11<>"",B20,"") | DH21: =IF($DH$11<>"",B20,"") | DI21: =IF($DI$11<>"",B20,"") | DJ21: =IF($DJ$11<>"",B20,"") | DK21: =IF($DK$11<>"",$B20,"") | DL21: =IF($DL$11<>"",$B20,"") | DM21: =IF($DM$11<>"",$B20,"") | DN21: =IF($DN$11<>"",$B20,"") | DO21: =IF($DO$11<>"",$B20,"") | DP21: =IF($DP$11<>"",$B20,"") | DQ21: =IF($DQ$11<>"",$B20,"") | DR21: =IF($DR$11<>"",$B20,"") | DS21: =IF($DS$11<>"",$B20,"") | DT21: =IF($DT$11<>"",$B20,"") | DU21: =IF($DU$11<>"",$B20,"") | DV21: =IF($DV$11<>"",$B20,"") | DY21: BATA INFANTIL MASCULINO | DZ21: EBAZAR.COM.BR.LTDA | EA21: ABRANGE | EB21: ALMERIA | EC21: 750ML
A22: =IF(PEDIDO!C47<>"",PEDIDO!B47,"") | B22: =IF(PEDIDO!X47<>"",PEDIDO!X47,"") | C22: =IF(PEDIDO!AA47<>"",PEDIDO!AA47,"") | D22: =IF(PEDIDO!AD47<>"",PEDIDO!AD47,"") | E22: =IF(PEDIDO!AG47<>"",PEDIDO!AG47,"") | F22: =IF(PEDIDO!AJ47<>"",PEDIDO!AJ47,"") | J22: =IF(PEDIDO!C46<>"",PEDIDO!B46,"") | K22: =IF($K$11<>"",B21,"") | L22: =IF($L$11<>"",B21,"") | M22: =IF($M$11<>"",B21,"") | N22: =IF($N$11<>"",B21,"") | O22: =IF($O$11<>"",B21,"") | P22: =IF($P$11<>"",B21,"") | Q22: =IF($Q$11<>"",B21,"") | R22: =IF($R$11<>"",B21,"") | S22: =IF($S$11<>"",B21,"") | T22: =IF($T$11<>"",B21,"") | U22: =IF($U$11<>"",B21,"") | V22: =IF($V$11<>"",B21,"") | X22: =IF($X$11<>"",B21,"") | Y22: =IF($Y$11<>"",B21,"") | Z22: =IF($Z$11<>"",B21,"") | AA22: =IF($AA$11<>"",B21,"") | AB22: =IF($AB$11<>"",B21,"") | AC22: =IF($AC$11<>"",B21,"") | AD22: =IF($AD$11<>"",B21,"") | AE22: =IF($AE$11<>"",B21,"") | AF22: =IF($AF$11<>"",B21,"") | AG22: =IF($AG$11<>"",B21,"") | AH22: =IF($AH$11<>"",B21,"") | AI22: =IF($AI$11<>"",B21,"") | AJ22: =IF($AJ$11<>"",B21,"") | AK22: =IF($AK$11<>"",B21,"") | AL22: =IF($AL$11<>"",B21,"") | AM22: =IF($AM$11<>"",B21,"") | AN22: =IF($AN$11<>"",B21,"") | AO22: =IF($AO$11<>"",B21,"") | AP22: =IF($AP$11<>"",B21,"") | AQ22: =IF($AQ$11<>"",B21,"") | AR22: =IF($AR$11<>"",B21,"") | AS22: =IF($AS$11<>"",B21,"") | AT22: =IF($AT$11<>"",B21,"") | AU22: =IF($AU$11<>"",B21,"") | AV22: =IF($AV$11<>"",B21,"") | AW22: =IF($AW$11<>"",B21,"") | AX22: =IF($AX$11<>"",B21,"") | AY22: =IF($AY$11<>"",B21,"") | AZ22: =IF($AZ$11<>"",B21,"") | BA22: =IF($BA$11<>"",B21,"") | BB22: =IF($BB$11<>"",B21,"") | BC22: =IF($BC$11<>"",B21,"") | BD22: =IF($BD$11<>"",B21,"") | BE22: =IF($BE$11<>"",B21,"") | BF22: =IF($BF$11<>"",B21,"") | BG22: =IF($BG$11<>"",B21,"") | BH22: =IF($BH$11<>"",B21,"") | BI22: =IF($BI$11<>"",B21,"") | BJ22: =IF($BJ$11<>"",B21,"") | BK22: =IF($BK$11<>"",B21,"") | BL22: =IF($BL$11<>"",B21,"") | BM22: =IF($BM$11<>"",B21,"") | BN22: =IF($BN$11<>"",B21,"") | BO22: =IF($BO$11<>"",B21,"") | BP22: =IF($BP$11<>"",B21,"") | BQ22: =IF($BQ$11<>"",B21,"") | BR22: =IF($BR$11<>"",B21,"") | BS22: =IF($BS$11<>"",B21,"") | BT22: =IF($BT$11<>"",B21,"") | BU22: =IF($BU$11<>"",B21,"") | BV22: =IF($BV$11<>"",B21,"") | BW22: =IF($BW$11<>"",B21,"") | BX22: =IF($BX$11<>"",B21,"") | BY22: =IF($BY$11<>"",B21,"") | BZ22: =IF($BZ$11<>"",B21,"") | CA22: =IF($CA$11<>"",B21,"") | CB22: =IF($CB$11<>"",B21,"") | CC22: =IF($CC$11<>"",B21,"") | CD22: =IF($CD$11<>"",B21,"") | CE22: =IF($CE$11<>"",B21,"") | CF22: =IF($CF$11<>"",B21,"") | CG22: =IF($CG$11<>"",B21,"") | CH22: =IF($CH$11<>"",B21,"") | CI22: =IF($CI$11<>"",B21,"") | CJ22: =IF($CJ$11<>"",B21,"") | CK22: =IF($CK$11<>"",B21,"") | CL22: =IF($CL$11<>"",B21,"") | CM22: =IF($CM$11<>"",B21,"") | CN22: =IF($CN$11<>"",B21,"") | CO22: =IF($CO$11<>"",B21,"") | CP22: =IF($CP$11<>"",B21,"") | CQ22: =IF($CQ$11<>"",B21,"") | CR22: =IF($CR$11<>"",B21,"") | CS22: =IF(CS21<>"",B$21,"") | CT22: =IF($CT$11<>"",B21,"") | CU22: =IF($CU$11<>"",B21,"") | CV22: =IF($CV$11<>"",B21,"") | CW22: =IF($CW$11<>"",B21,"") | CX22: =IF($CX$11<>"",B21,"") | CY22: =IF($CY$11<>"",B21,"") | CZ22: =IF($CZ$11<>"",B21,"") | DA22: =IF($DA$11<>"",B21,"") | DB22: =IF($DB$11<>"",B21,"") | DC22: =IF($DC$11<>"",B21,"") | DD22: =IF($DD$11<>"",B21,"") | DE22: =IF($DE$11<>"",B21,"") | DF22: =IF($DF$11<>"",B21,"") | DG22: =IF($DG$11<>"",B21,"") | DH22: =IF($DH$11<>"",B21,"") | DI22: =IF($DI$11<>"",B21,"") | DJ22: =IF($DJ$11<>"",B21,"") | DK22: =IF($DK$11<>"",$B21,"") | DL22: =IF($DL$11<>"",$B21,"") | DM22: =IF($DM$11<>"",$B21,"") | DN22: =IF($DN$11<>"",$B21,"") | DO22: =IF($DO$11<>"",$B21,"") | DP22: =IF($DP$11<>"",$B21,"") | DQ22: =IF($DQ$11<>"",$B21,"") | DR22: =IF($DR$11<>"",$B21,"") | DS22: =IF($DS$11<>"",$B21,"") | DT22: =IF($DT$11<>"",$B21,"") | DU22: =IF($DU$11<>"",$B21,"") | DV22: =IF($DV$11<>"",$B21,"") | DY22: BERMUDA | DZ22: MULTCABOS | EA22: ABRUZZO | EB22: ALMOND | EC22: 81 PRO
A23: =IF(PEDIDO!C48<>"",PEDIDO!B48,"") | B23: =IF(PEDIDO!X48<>"",PEDIDO!X48,"") | C23: =IF(PEDIDO!AA48<>"",PEDIDO!AA48,"") | D23: =IF(PEDIDO!AD48<>"",PEDIDO!AD48,"") | E23: =IF(PEDIDO!AG48<>"",PEDIDO!AG48,"") | F23: =IF(PEDIDO!AJ48<>"",PEDIDO!AJ48,"") | J23: =IF(PEDIDO!C47<>"",PEDIDO!B47,"") | K23: =IF($K$11<>"",B22,"") | L23: =IF($L$11<>"",B22,"") | M23: =IF($M$11<>"",B22,"") | N23: =IF($N$11<>"",B22,"") | O23: =IF($O$11<>"",B22,"") | P23: =IF($P$11<>"",B22,"") | Q23: =IF($Q$11<>"",B22,"") | R23: =IF($R$11<>"",B22,"") | S23: =IF($S$11<>"",B22,"") | T23: =IF($T$11<>"",B22,"") | U23: =IF($U$11<>"",B22,"") | V23: =IF($V$11<>"",B22,"") | X23: =IF($X$11<>"",B22,"") | Y23: =IF($Y$11<>"",B22,"") | Z23: =IF($Z$11<>"",B22,"") | AA23: =IF($AA$11<>"",B22,"") | AB23: =IF($AB$11<>"",B22,"") | AC23: =IF($AC$11<>"",B22,"") | AD23: =IF($AD$11<>"",B22,"") | AE23: =IF($AE$11<>"",B22,"") | AF23: =IF($AF$11<>"",B22,"") | AG23: =IF($AG$11<>"",B22,"") | AH23: =IF($AH$11<>"",B22,"") | AI23: =IF($AI$11<>"",B22,"") | AJ23: =IF($AJ$11<>"",B22,"") | AK23: =IF($AK$11<>"",B22,"") | AL23: =IF($AL$11<>"",B22,"") | AM23: =IF($AM$11<>"",B22,"") | AN23: =IF($AN$11<>"",B22,"") | AO23: =IF($AO$11<>"",B22,"") | AP23: =IF($AP$11<>"",B22,"") | AQ23: =IF($AQ$11<>"",B22,"") | AR23: =IF($AR$11<>"",B22,"") | AS23: =IF($AS$11<>"",B22,"") | AT23: =IF($AT$11<>"",B22,"") | AU23: =IF($AU$11<>"",B22,"") | AV23: =IF($AV$11<>"",B22,"") | AW23: =IF($AW$11<>"",B22,"") | AX23: =IF($AX$11<>"",B22,"") | AY23: =IF($AY$11<>"",B22,"") | AZ23: =IF($AZ$11<>"",B22,"") | BA23: =IF($BA$11<>"",B22,"") | BB23: =IF($BB$11<>"",B22,"") | BC23: =IF($BC$11<>"",B22,"") | BD23: =IF($BD$11<>"",B22,"") | BE23: =IF($BE$11<>"",B22,"") | BF23: =IF($BF$11<>"",B22,"") | BG23: =IF($BG$11<>"",B22,"") | BH23: =IF($BH$11<>"",B22,"") | BI23: =IF($BI$11<>"",B22,"") | BJ23: =IF($BJ$11<>"",B22,"") | BK23: =IF($BK$11<>"",B22,"") | BL23: =IF($BL$11<>"",B22,"") | BM23: =IF($BM$11<>"",B22,"") | BN23: =IF($BN$11<>"",B22,"") | BO23: =IF($BO$11<>"",B22,"") | BP23: =IF($BP$11<>"",B22,"") | BQ23: =IF($BQ$11<>"",B22,"") | BR23: =IF($BR$11<>"",B22,"") | BS23: =IF($BS$11<>"",B22,"") | BT23: =IF($BT$11<>"",B22,"") | BU23: =IF($BU$11<>"",B22,"") | BV23: =IF($BV$11<>"",B22,"") | BW23: =IF($BW$11<>"",B22,"") | BX23: =IF($BX$11<>"",B22,"") | BY23: =IF($BY$11<>"",B22,"") | BZ23: =IF($BZ$11<>"",B22,"") | CA23: =IF($CA$11<>"",B22,"") | CB23: =IF($CB$11<>"",B22,"") | CC23: =IF($CC$11<>"",B22,"") | CD23: =IF($CD$11<>"",B22,"") | CE23: =IF($CE$11<>"",B22,"") | CF23: =IF($CF$11<>"",B22,"") | CG23: =IF($CG$11<>"",B22,"") | CH23: =IF($CH$11<>"",B22,"") | CI23: =IF($CI$11<>"",B22,"") | CJ23: =IF($CJ$11<>"",B22,"") | CK23: =IF($CK$11<>"",B22,"") | CL23: =IF($CL$11<>"",B22,"") | CM23: =IF($CM$11<>"",B22,"") | CN23: =IF($CN$11<>"",B22,"") | CO23: =IF($CO$11<>"",B22,"") | CP23: =IF($CP$11<>"",B22,"") | CQ23: =IF($CQ$11<>"",B22,"") | CR23: =IF($CR$11<>"",B22,"") | CS23: =IF(CS22<>"",B$22,"") | CT23: =IF($CT$11<>"",B22,"") | CU23: =IF($CU$11<>"",B22,"") | CV23: =IF($CV$11<>"",B22,"") | CW23: =IF($CW$11<>"",B22,"") | CX23: =IF($CX$11<>"",B22,"") | CY23: =IF($CY$11<>"",B22,"") | CZ23: =IF($CZ$11<>"",B22,"") | DA23: =IF($DA$11<>"",B22,"") | DB23: =IF($DB$11<>"",B22,"") | DC23: =IF($DC$11<>"",B22,"") | DD23: =IF($DD$11<>"",B22,"") | DE23: =IF($DE$11<>"",B22,"") | DF23: =IF($DF$11<>"",B22,"") | DG23: =IF($DG$11<>"",B22,"") | DH23: =IF($DH$11<>"",B22,"") | DI23: =IF($DI$11<>"",B22,"") | DJ23: =IF($DJ$11<>"",B22,"") | DK23: =IF($DK$11<>"",$B22,"") | DL23: =IF($DL$11<>"",$B22,"") | DM23: =IF($DM$11<>"",$B22,"") | DN23: =IF($DN$11<>"",$B22,"") | DO23: =IF($DO$11<>"",$B22,"") | DP23: =IF($DP$11<>"",$B22,"") | DQ23: =IF($DQ$11<>"",$B22,"") | DR23: =IF($DR$11<>"",$B22,"") | DS23: =IF($DS$11<>"",$B22,"") | DT23: =IF($DT$11<>"",$B22,"") | DU23: =IF($DU$11<>"",$B22,"") | DV23: =IF($DV$11<>"",$B22,"") | DY23: BERMUDA CICLISTA | DZ23: LOJA DAS ETIQUETAS | EA23: ABS | EB23: ALOHA | EC23: 81 THUNDER
A24: =IF(PEDIDO!C49<>"",PEDIDO!B49,"") | B24: =IF(PEDIDO!X49<>"",PEDIDO!X49,"") | C24: =IF(PEDIDO!AA49<>"",PEDIDO!AA49,"") | D24: =IF(PEDIDO!AD49<>"",PEDIDO!AD49,"") | E24: =IF(PEDIDO!AG49<>"",PEDIDO!AG49,"") | F24: =IF(PEDIDO!AJ49<>"",PEDIDO!AJ49,"") | J24: =IF(PEDIDO!C48<>"",PEDIDO!B48,"") | K24: =IF($K$11<>"",B23,"") | L24: =IF($L$11<>"",B23,"") | M24: =IF($M$11<>"",B23,"") | N24: =IF($N$11<>"",B23,"") | O24: =IF($O$11<>"",B23,"") | P24: =IF($P$11<>"",B23,"") | Q24: =IF($Q$11<>"",B23,"") | R24: =IF($R$11<>"",B23,"") | S24: =IF($S$11<>"",B23,"") | T24: =IF($T$11<>"",B23,"") | U24: =IF($U$11<>"",B23,"") | V24: =IF($V$11<>"",B23,"") | X24: =IF($X$11<>"",B23,"") | Y24: =IF($Y$11<>"",B23,"") | Z24: =IF($Z$11<>"",B23,"") | AA24: =IF($AA$11<>"",B23,"") | AB24: =IF($AB$11<>"",B23,"") | AC24: =IF($AC$11<>"",B23,"") | AD24: =IF($AD$11<>"",B23,"") | AE24: =IF($AE$11<>"",B23,"") | AF24: =IF($AF$11<>"",B23,"") | AG24: =IF($AG$11<>"",B23,"") | AH24: =IF($AH$11<>"",B23,"") | AI24: =IF($AI$11<>"",B23,"") | AJ24: =IF($AJ$11<>"",B23,"") | AK24: =IF($AK$11<>"",B23,"") | AL24: =IF($AL$11<>"",B23,"") | AM24: =IF($AM$11<>"",B23,"") | AN24: =IF($AN$11<>"",B23,"") | AO24: =IF($AO$11<>"",B23,"") | AP24: =IF($AP$11<>"",B23,"") | AQ24: =IF($AQ$11<>"",B23,"") | AR24: =IF($AR$11<>"",B23,"") | AS24: =IF($AS$11<>"",B23,"") | AT24: =IF($AT$11<>"",B23,"") | AU24: =IF($AU$11<>"",B23,"") | AV24: =IF($AV$11<>"",B23,"") | AW24: =IF($AW$11<>"",B23,"") | AX24: =IF($AX$11<>"",B23,"") | AY24: =IF($AY$11<>"",B23,"") | AZ24: =IF($AZ$11<>"",B23,"") | BA24: =IF($BA$11<>"",B23,"") | BB24: =IF($BB$11<>"",B23,"") | BC24: =IF($BC$11<>"",B23,"") | BD24: =IF($BD$11<>"",B23,"") | BE24: =IF($BE$11<>"",B23,"") | BF24: =IF($BF$11<>"",B23,"") | BG24: =IF($BG$11<>"",B23,"") | BH24: =IF($BH$11<>"",B23,"") | BI24: =IF($BI$11<>"",B23,"") | BJ24: =IF($BJ$11<>"",B23,"") | BK24: =IF($BK$11<>"",B23,"") | BL24: =IF($BL$11<>"",B23,"") | BM24: =IF($BM$11<>"",B23,"") | BN24: =IF($BN$11<>"",B23,"") | BO24: =IF($BO$11<>"",B23,"") | BP24: =IF($BP$11<>"",B23,"") | BQ24: =IF($BQ$11<>"",B23,"") | BR24: =IF($BR$11<>"",B23,"") | BS24: =IF($BS$11<>"",B23,"") | BT24: =IF($BT$11<>"",B23,"") | BU24: =IF($BU$11<>"",B23,"") | BV24: =IF($BV$11<>"",B23,"") | BW24: =IF($BW$11<>"",B23,"") | BX24: =IF($BX$11<>"",B23,"") | BY24: =IF($BY$11<>"",B23,"") | BZ24: =IF($BZ$11<>"",B23,"") | CA24: =IF($CA$11<>"",B23,"") | CB24: =IF($CB$11<>"",B23,"") | CC24: =IF($CC$11<>"",B23,"") | CD24: =IF($CD$11<>"",B23,"") | CE24: =IF($CE$11<>"",B23,"") | CF24: =IF($CF$11<>"",B23,"") | CG24: =IF($CG$11<>"",B23,"") | CH24: =IF($CH$11<>"",B23,"") | CI24: =IF($CI$11<>"",B23,"") | CJ24: =IF($CJ$11<>"",B23,"") | CK24: =IF($CK$11<>"",B23,"") | CL24: =IF($CL$11<>"",B23,"") | CM24: =IF($CM$11<>"",B23,"") | CN24: =IF($CN$11<>"",B23,"") | CO24: =IF($CO$11<>"",B23,"") | CP24: =IF($CP$11<>"",B23,"") | CQ24: =IF($CQ$11<>"",B23,"") | CR24: =IF($CR$11<>"",B23,"") | CS24: =IF(CS23<>"",B$23,"") | CT24: =IF($CT$11<>"",B23,"") | CU24: =IF($CU$11<>"",B23,"") | CV24: =IF($CV$11<>"",B23,"") | CW24: =IF($CW$11<>"",B23,"") | CX24: =IF($CX$11<>"",B23,"") | CY24: =IF($CY$11<>"",B23,"") | CZ24: =IF($CZ$11<>"",B23,"") | DA24: =IF($DA$11<>"",B23,"") | DB24: =IF($DB$11<>"",B23,"") | DC24: =IF($DC$11<>"",B23,"") | DD24: =IF($DD$11<>"",B23,"") | DE24: =IF($DE$11<>"",B23,"") | DF24: =IF($DF$11<>"",B23,"") | DG24: =IF($DG$11<>"",B23,"") | DH24: =IF($DH$11<>"",B23,"") | DI24: =IF($DI$11<>"",B23,"") | DJ24: =IF($DJ$11<>"",B23,"") | DK24: =IF($DK$11<>"",$B23,"") | DL24: =IF($DL$11<>"",$B23,"") | DM24: =IF($DM$11<>"",$B23,"") | DN24: =IF($DN$11<>"",$B23,"") | DO24: =IF($DO$11<>"",$B23,"") | DP24: =IF($DP$11<>"",$B23,"") | DQ24: =IF($DQ$11<>"",$B23,"") | DR24: =IF($DR$11<>"",$B23,"") | DS24: =IF($DS$11<>"",$B23,"") | DT24: =IF($DT$11<>"",$B23,"") | DU24: =IF($DU$11<>"",$B23,"") | DV24: =IF($DV$11<>"",$B23,"") | DY24: BERMUDA CICLISTA FEMININO | DZ24: MALENTACCHINEWS | EA24: ACELORMITTAL BRASIL | EB24: ALVEJADO | EC24: A CASA MAGICA DE GABBY
A25: =IF(PEDIDO!C50<>"",PEDIDO!B50,"") | B25: =IF(PEDIDO!X50<>"",PEDIDO!X50,"") | C25: =IF(PEDIDO!AA50<>"",PEDIDO!AA50,"") | D25: =IF(PEDIDO!AD50<>"",PEDIDO!AD50,"") | E25: =IF(PEDIDO!AG50<>"",PEDIDO!AG50,"") | F25: =IF(PEDIDO!AJ50<>"",PEDIDO!AJ50,"") | J25: =IF(PEDIDO!C49<>"",PEDIDO!B49,"") | K25: =IF($K$11<>"",B24,"") | L25: =IF($L$11<>"",B24,"") | M25: =IF($M$11<>"",B24,"") | N25: =IF($N$11<>"",B24,"") | O25: =IF($O$11<>"",B24,"") | P25: =IF($P$11<>"",B24,"") | Q25: =IF($Q$11<>"",B24,"") | R25: =IF($R$11<>"",B24,"") | S25: =IF($S$11<>"",B24,"") | T25: =IF($T$11<>"",B24,"") | U25: =IF($U$11<>"",B24,"") | V25: =IF($V$11<>"",B24,"") | X25: =IF($X$11<>"",B24,"") | Y25: =IF($Y$11<>"",B24,"") | Z25: =IF($Z$11<>"",B24,"") | AA25: =IF($AA$11<>"",B24,"") | AB25: =IF($AB$11<>"",B24,"") | AC25: =IF($AC$11<>"",B24,"") | AD25: =IF($AD$11<>"",B24,"") | AE25: =IF($AE$11<>"",B24,"") | AF25: =IF($AF$11<>"",B24,"") | AG25: =IF($AG$11<>"",B24,"") | AH25: =IF($AH$11<>"",B24,"") | AI25: =IF($AI$11<>"",B24,"") | AJ25: =IF($AJ$11<>"",B24,"") | AK25: =IF($AK$11<>"",B24,"") | AL25: =IF($AL$11<>"",B24,"") | AM25: =IF($AM$11<>"",B24,"") | AN25: =IF($AN$11<>"",B24,"") | AO25: =IF($AO$11<>"",B24,"") | AP25: =IF($AP$11<>"",B24,"") | AQ25: =IF($AQ$11<>"",B24,"") | AR25: =IF($AR$11<>"",B24,"") | AS25: =IF($AS$11<>"",B24,"") | AT25: =IF($AT$11<>"",B24,"") | AU25: =IF($AU$11<>"",B24,"") | AV25: =IF($AV$11<>"",B24,"") | AW25: =IF($AW$11<>"",B24,"") | AX25: =IF($AX$11<>"",B24,"") | AY25: =IF($AY$11<>"",B24,"") | AZ25: =IF($AZ$11<>"",B24,"") | BA25: =IF($BA$11<>"",B24,"") | BB25: =IF($BB$11<>"",B24,"") | BC25: =IF($BC$11<>"",B24,"") | BD25: =IF($BD$11<>"",B24,"") | BE25: =IF($BE$11<>"",B24,"") | BF25: =IF($BF$11<>"",B24,"") | BG25: =IF($BG$11<>"",B24,"") | BH25: =IF($BH$11<>"",B24,"") | BI25: =IF($BI$11<>"",B24,"") | BJ25: =IF($BJ$11<>"",B24,"") | BK25: =IF($BK$11<>"",B24,"") | BL25: =IF($BL$11<>"",B24,"") | BM25: =IF($BM$11<>"",B24,"") | BN25: =IF($BN$11<>"",B24,"") | BO25: =IF($BO$11<>"",B24,"") | BP25: =IF($BP$11<>"",B24,"") | BQ25: =IF($BQ$11<>"",B24,"") | BR25: =IF($BR$11<>"",B24,"") | BS25: =IF($BS$11<>"",B24,"") | BT25: =IF($BT$11<>"",B24,"") | BU25: =IF($BU$11<>"",B24,"") | BV25: =IF($BV$11<>"",B24,"") | BW25: =IF($BW$11<>"",B24,"") | BX25: =IF($BX$11<>"",B24,"") | BY25: =IF($BY$11<>"",B24,"") | BZ25: =IF($BZ$11<>"",B24,"") | CA25: =IF($CA$11<>"",B24,"") | CB25: =IF($CB$11<>"",B24,"") | CC25: =IF($CC$11<>"",B24,"") | CD25: =IF($CD$11<>"",B24,"") | CE25: =IF($CE$11<>"",B24,"") | CF25: =IF($CF$11<>"",B24,"") | CG25: =IF($CG$11<>"",B24,"") | CH25: =IF($CH$11<>"",B24,"") | CI25: =IF($CI$11<>"",B24,"") | CJ25: =IF($CJ$11<>"",B24,"") | CK25: =IF($CK$11<>"",B24,"") | CL25: =IF($CL$11<>"",B24,"") | CM25: =IF($CM$11<>"",B24,"") | CN25: =IF($CN$11<>"",B24,"") | CO25: =IF($CO$11<>"",B24,"") | CP25: =IF($CP$11<>"",B24,"") | CQ25: =IF($CQ$11<>"",B24,"") | CR25: =IF($CR$11<>"",B24,"") | CS25: =IF(CS24<>"",$B24,"") | CT25: =IF($CT$11<>"",B24,"") | CU25: =IF($CU$11<>"",B24,"") | CV25: =IF($CV$11<>"",B24,"") | CW25: =IF($CW$11<>"",B24,"") | CX25: =IF($CX$11<>"",B24,"") | CY25: =IF($CY$11<>"",B24,"") | CZ25: =IF($CZ$11<>"",B24,"") | DA25: =IF($DA$11<>"",B24,"") | DB25: =IF($DB$11<>"",B24,"") | DC25: =IF($DC$11<>"",B24,"") | DD25: =IF($DD$11<>"",B24,"") | DE25: =IF($DE$11<>"",B24,"") | DF25: =IF($DF$11<>"",B24,"") | DG25: =IF($DG$11<>"",B24,"") | DH25: =IF($DH$11<>"",B24,"") | DI25: =IF($DI$11<>"",B24,"") | DJ25: =IF($DJ$11<>"",B24,"") | DK25: =IF($DK$11<>"",$B24,"") | DL25: =IF($DL$11<>"",$B24,"") | DM25: =IF($DM$11<>"",$B24,"") | DN25: =IF($DN$11<>"",$B24,"") | DO25: =IF($DO$11<>"",$B24,"") | DP25: =IF($DP$11<>"",$B24,"") | DQ25: =IF($DQ$11<>"",$B24,"") | DR25: =IF($DR$11<>"",$B24,"") | DS25: =IF($DS$11<>"",$B24,"") | DT25: =IF($DT$11<>"",$B24,"") | DU25: =IF($DU$11<>"",$B24,"") | DV25: =IF($DV$11<>"",$B24,"") | DY25: BERMUDA CICLISTA MASCULINO | DZ25: BRASIL INTER | EA25: ACLAMADO | EB25: AMACIADA | EC25: A PEQUENA SEREIA
A26: =IF(PEDIDO!C51<>"",PEDIDO!B51,"") | B26: =IF(PEDIDO!X51<>"",PEDIDO!X51,"") | C26: =IF(PEDIDO!AA51<>"",PEDIDO!AA51,"") | D26: =IF(PEDIDO!AD51<>"",PEDIDO!AD51,"") | E26: =IF(PEDIDO!AG51<>"",PEDIDO!AG51,"") | F26: =IF(PEDIDO!AJ51<>"",PEDIDO!AJ51,"") | J26: =IF(PEDIDO!C50<>"",PEDIDO!B50,"") | K26: =IF($K$11<>"",B25,"") | L26: =IF($L$11<>"",B25,"") | M26: =IF($M$11<>"",B25,"") | N26: =IF($N$11<>"",B25,"") | O26: =IF($O$11<>"",B25,"") | P26: =IF($P$11<>"",B25,"") | Q26: =IF($Q$11<>"",B25,"") | R26: =IF($R$11<>"",B25,"") | S26: =IF($S$11<>"",B25,"") | T26: =IF($T$11<>"",B25,"") | U26: =IF($U$11<>"",B25,"") | V26: =IF($V$11<>"",B25,"") | X26: =IF($X$11<>"",B25,"") | Y26: =IF($Y$11<>"",B25,"") | Z26: =IF($Z$11<>"",B25,"") | AA26: =IF($AA$11<>"",B25,"") | AB26: =IF($AB$11<>"",B25,"") | AC26: =IF($AC$11<>"",B25,"") | AD26: =IF($AD$11<>"",B25,"") | AE26: =IF($AE$11<>"",B25,"") | AF26: =IF($AF$11<>"",B25,"") | AG26: =IF($AG$11<>"",B25,"") | AH26: =IF($AH$11<>"",B25,"") | AI26: =IF($AI$11<>"",B25,"") | AJ26: =IF($AJ$11<>"",B25,"") | AK26: =IF($AK$11<>"",B25,"") | AL26: =IF($AL$11<>"",B25,"") | AM26: =IF($AM$11<>"",B25,"") | AN26: =IF($AN$11<>"",B25,"") | AO26: =IF($AO$11<>"",B25,"") | AP26: =IF($AP$11<>"",B25,"") | AQ26: =IF($AQ$11<>"",B25,"") | AR26: =IF($AR$11<>"",B25,"") | AS26: =IF($AS$11<>"",B25,"") | AT26: =IF($AT$11<>"",B25,"") | AU26: =IF($AU$11<>"",B25,"") | AV26: =IF($AV$11<>"",B25,"") | AW26: =IF($AW$11<>"",B25,"") | AX26: =IF($AX$11<>"",B25,"") | AY26: =IF($AY$11<>"",B25,"") | AZ26: =IF($AZ$11<>"",B25,"") | BA26: =IF($BA$11<>"",B25,"") | BB26: =IF($BB$11<>"",B25,"") | BC26: =IF($BC$11<>"",B25,"") | BD26: =IF($BD$11<>"",B25,"") | BE26: =IF($BE$11<>"",B25,"") | BF26: =IF($BF$11<>"",B25,"") | BG26: =IF($BG$11<>"",B25,"") | BH26: =IF($BH$11<>"",B25,"") | BI26: =IF($BI$11<>"",B25,"") | BJ26: =IF($BJ$11<>"",B25,"") | BK26: =IF($BK$11<>"",B25,"") | BL26: =IF($BL$11<>"",B25,"") | BM26: =IF($BM$11<>"",B25,"") | BN26: =IF($BN$11<>"",B25,"") | BO26: =IF($BO$11<>"",B25,"") | BP26: =IF($BP$11<>"",B25,"") | BQ26: =IF($BQ$11<>"",B25,"") | BR26: =IF($BR$11<>"",B25,"") | BS26: =IF($BS$11<>"",B25,"") | BT26: =IF($BT$11<>"",B25,"") | BU26: =IF($BU$11<>"",B25,"") | BV26: =IF($BV$11<>"",B25,"") | BW26: =IF($BW$11<>"",B25,"") | BX26: =IF($BX$11<>"",B25,"") | BY26: =IF($BY$11<>"",B25,"") | BZ26: =IF($BZ$11<>"",B25,"") | CA26: =IF($CA$11<>"",B25,"") | CB26: =IF($CB$11<>"",B25,"") | CC26: =IF($CC$11<>"",B25,"") | CD26: =IF($CD$11<>"",B25,"") | CE26: =IF($CE$11<>"",B25,"") | CF26: =IF($CF$11<>"",B25,"") | CG26: =IF($CG$11<>"",B25,"") | CH26: =IF($CH$11<>"",B25,"") | CI26: =IF($CI$11<>"",B25,"") | CJ26: =IF($CJ$11<>"",B25,"") | CK26: =IF($CK$11<>"",B25,"") | CL26: =IF($CL$11<>"",B25,"") | CM26: =IF($CM$11<>"",B25,"") | CN26: =IF($CN$11<>"",B25,"") | CO26: =IF($CO$11<>"",B25,"") | CP26: =IF($CP$11<>"",B25,"") | CQ26: =IF($CQ$11<>"",B25,"") | CR26: =IF($CR$11<>"",B25,"") | CS26: =IF(CS25<>"",$B25,"") | CT26: =IF($CT$11<>"",B25,"") | CU26: =IF($CU$11<>"",B25,"") | CV26: =IF($CV$11<>"",B25,"") | CW26: =IF($CW$11<>"",B25,"") | CX26: =IF($CX$11<>"",B25,"") | CY26: =IF($CY$11<>"",B25,"") | CZ26: =IF($CZ$11<>"",B25,"") | DA26: =IF($DA$11<>"",B25,"") | DB26: =IF($DB$11<>"",B25,"") | DC26: =IF($DC$11<>"",B25,"") | DD26: =IF($DD$11<>"",B25,"") | DE26: =IF($DE$11<>"",B25,"") | DF26: =IF($DF$11<>"",B25,"") | DG26: =IF($DG$11<>"",B25,"") | DH26: =IF($DH$11<>"",B25,"") | DI26: =IF($DI$11<>"",B25,"") | DJ26: =IF($DJ$11<>"",B25,"") | DK26: =IF($DK$11<>"",$B25,"") | DL26: =IF($DL$11<>"",$B25,"") | DM26: =IF($DM$11<>"",$B25,"") | DN26: =IF($DN$11<>"",$B25,"") | DO26: =IF($DO$11<>"",$B25,"") | DP26: =IF($DP$11<>"",$B25,"") | DQ26: =IF($DQ$11<>"",$B25,"") | DR26: =IF($DR$11<>"",$B25,"") | DS26: =IF($DS$11<>"",$B25,"") | DT26: =IF($DT$11<>"",$B25,"") | DU26: =IF($DU$11<>"",$B25,"") | DV26: =IF($DV$11<>"",$B25,"") | DY26: BERMUDA ERGONOMIC | DZ26: GASHOP | EA26: ACOSTAMENTO | EB26: AMARANTO | EC26: ACO INOX
A27: =IF(PEDIDO!C52<>"",PEDIDO!B52,"") | B27: =IF(PEDIDO!X52<>"",PEDIDO!X52,"") | C27: =IF(PEDIDO!AA52<>"",PEDIDO!AA52,"") | D27: =IF(PEDIDO!AD52<>"",PEDIDO!AD52,"") | E27: =IF(PEDIDO!AG52<>"",PEDIDO!AG52,"") | F27: =IF(PEDIDO!AJ52<>"",PEDIDO!AJ52,"") | J27: =IF(PEDIDO!C51<>"",PEDIDO!B51,"") | K27: =IF($K$11<>"",B26,"") | L27: =IF($L$11<>"",B26,"") | M27: =IF($M$11<>"",B26,"") | N27: =IF($N$11<>"",B26,"") | O27: =IF($O$11<>"",B26,"") | P27: =IF($P$11<>"",B26,"") | Q27: =IF($Q$11<>"",B26,"") | R27: =IF($R$11<>"",B26,"") | S27: =IF($S$11<>"",B26,"") | T27: =IF($T$11<>"",B26,"") | U27: =IF($U$11<>"",B26,"") | V27: =IF($V$11<>"",B26,"") | X27: =IF($X$11<>"",B26,"") | Y27: =IF($Y$11<>"",B26,"") | Z27: =IF($Z$11<>"",B26,"") | AA27: =IF($AA$11<>"",B26,"") | AB27: =IF($AB$11<>"",B26,"") | AC27: =IF($AC$11<>"",B26,"") | AD27: =IF($AD$11<>"",B26,"") | AE27: =IF($AE$11<>"",B26,"") | AF27: =IF($AF$11<>"",B26,"") | AG27: =IF($AG$11<>"",B26,"") | AH27: =IF($AH$11<>"",B26,"") | AI27: =IF($AI$11<>"",B26,"") | AJ27: =IF($AJ$11<>"",B26,"") | AK27: =IF($AK$11<>"",B26,"") | AL27: =IF($AL$11<>"",B26,"") | AM27: =IF($AM$11<>"",B26,"") | AN27: =IF($AN$11<>"",B26,"") | AO27: =IF($AO$11<>"",B26,"") | AP27: =IF($AP$11<>"",B26,"") | AQ27: =IF($AQ$11<>"",B26,"") | AR27: =IF($AR$11<>"",B26,"") | AS27: =IF($AS$11<>"",B26,"") | AT27: =IF($AT$11<>"",B26,"") | AU27: =IF($AU$11<>"",B26,"") | AV27: =IF($AV$11<>"",B26,"") | AW27: =IF($AW$11<>"",B26,"") | AX27: =IF($AX$11<>"",B26,"") | AY27: =IF($AY$11<>"",B26,"") | AZ27: =IF($AZ$11<>"",B26,"") | BA27: =IF($BA$11<>"",B26,"") | BB27: =IF($BB$11<>"",B26,"") | BC27: =IF($BC$11<>"",B26,"") | BD27: =IF($BD$11<>"",B26,"") | BE27: =IF($BE$11<>"",B26,"") | BF27: =IF($BF$11<>"",B26,"") | BG27: =IF($BG$11<>"",B26,"") | BH27: =IF($BH$11<>"",B26,"") | BI27: =IF($BI$11<>"",B26,"") | BJ27: =IF($BJ$11<>"",B26,"") | BK27: =IF($BK$11<>"",B26,"") | BL27: =IF($BL$11<>"",B26,"") | BM27: =IF($BM$11<>"",B26,"") | BN27: =IF($BN$11<>"",B26,"") | BO27: =IF($BO$11<>"",B26,"") | BP27: =IF($BP$11<>"",B26,"") | BQ27: =IF($BQ$11<>"",B26,"") | BR27: =IF($BR$11<>"",B26,"") | BS27: =IF($BS$11<>"",B26,"") | BT27: =IF($BT$11<>"",B26,"") | BU27: =IF($BU$11<>"",B26,"") | BV27: =IF($BV$11<>"",B26,"") | BW27: =IF($BW$11<>"",B26,"") | BX27: =IF($BX$11<>"",B26,"") | BY27: =IF($BY$11<>"",B26,"") | BZ27: =IF($BZ$11<>"",B26,"") | CA27: =IF($CA$11<>"",B26,"") | CB27: =IF($CB$11<>"",B26,"") | CC27: =IF($CC$11<>"",B26,"") | CD27: =IF($CD$11<>"",B26,"") | CE27: =IF($CE$11<>"",B26,"") | CF27: =IF($CF$11<>"",B26,"") | CG27: =IF($CG$11<>"",B26,"") | CH27: =IF($CH$11<>"",B26,"") | CI27: =IF($CI$11<>"",B26,"") | CJ27: =IF($CJ$11<>"",B26,"") | CK27: =IF($CK$11<>"",B26,"") | CL27: =IF($CL$11<>"",B26,"") | CM27: =IF($CM$11<>"",B26,"") | CN27: =IF($CN$11<>"",B26,"") | CO27: =IF($CO$11<>"",B26,"") | CP27: =IF($CP$11<>"",B26,"") | CQ27: =IF($CQ$11<>"",B26,"") | CR27: =IF($CR$11<>"",B26,"") | CS27: =IF(CS26<>"",$B26,"") | CT27: =IF($CT$11<>"",B26,"") | CU27: =IF($CU$11<>"",B26,"") | CV27: =IF($CV$11<>"",B26,"") | CW27: =IF($CW$11<>"",B26,"") | CX27: =IF($CX$11<>"",B26,"") | CY27: =IF($CY$11<>"",B26,"") | CZ27: =IF($CZ$11<>"",B26,"") | DA27: =IF($DA$11<>"",B26,"") | DB27: =IF($DB$11<>"",B26,"") | DC27: =IF($DC$11<>"",B26,"") | DD27: =IF($DD$11<>"",B26,"") | DE27: =IF($DE$11<>"",B26,"") | DF27: =IF($DF$11<>"",B26,"") | DG27: =IF($DG$11<>"",B26,"") | DH27: =IF($DH$11<>"",B26,"") | DI27: =IF($DI$11<>"",B26,"") | DJ27: =IF($DJ$11<>"",B26,"") | DK27: =IF($DK$11<>"",$B26,"") | DL27: =IF($DL$11<>"",$B26,"") | DM27: =IF($DM$11<>"",$B26,"") | DN27: =IF($DN$11<>"",$B26,"") | DO27: =IF($DO$11<>"",$B26,"") | DP27: =IF($DP$11<>"",$B26,"") | DQ27: =IF($DQ$11<>"",$B26,"") | DR27: =IF($DR$11<>"",$B26,"") | DS27: =IF($DS$11<>"",$B26,"") | DT27: =IF($DT$11<>"",$B26,"") | DU27: =IF($DU$11<>"",$B26,"") | DV27: =IF($DV$11<>"",$B26,"") | DY27: BERMUDA FEMININO | DZ27: AMARAL | EA27: ACOSTAMENTO KIDS | EB27: AMARELO | EC27: ACONCHEGO
A28: =IF(PEDIDO!C53<>"",PEDIDO!B53,"") | B28: =IF(PEDIDO!X53<>"",PEDIDO!X53,"") | C28: =IF(PEDIDO!AA53<>"",PEDIDO!AA53,"") | D28: =IF(PEDIDO!AD53<>"",PEDIDO!AD53,"") | E28: =IF(PEDIDO!AG53<>"",PEDIDO!AG53,"") | F28: =IF(PEDIDO!AJ53<>"",PEDIDO!AJ53,"") | J28: =IF(PEDIDO!C52<>"",PEDIDO!B52,"") | K28: =IF($K$11<>"",B27,"") | L28: =IF($L$11<>"",B27,"") | M28: =IF($M$11<>"",B27,"") | N28: =IF($N$11<>"",B27,"") | O28: =IF($O$11<>"",B27,"") | P28: =IF($P$11<>"",B27,"") | Q28: =IF($Q$11<>"",B27,"") | R28: =IF($R$11<>"",B27,"") | S28: =IF($S$11<>"",B27,"") | T28: =IF($T$11<>"",B27,"") | U28: =IF($U$11<>"",B27,"") | V28: =IF($V$11<>"",B27,"") | X28: =IF($X$11<>"",B27,"") | Y28: =IF($Y$11<>"",B27,"") | Z28: =IF($Z$11<>"",B27,"") | AA28: =IF($AA$11<>"",B27,"") | AB28: =IF($AB$11<>"",B27,"") | AC28: =IF($AC$11<>"",B27,"") | AD28: =IF($AD$11<>"",B27,"") | AE28: =IF($AE$11<>"",B27,"") | AF28: =IF($AF$11<>"",B27,"") | AG28: =IF($AG$11<>"",B27,"") | AH28: =IF($AH$11<>"",B27,"") | AI28: =IF($AI$11<>"",B27,"") | AJ28: =IF($AJ$11<>"",B27,"") | AK28: =IF($AK$11<>"",B27,"") | AL28: =IF($AL$11<>"",B27,"") | AM28: =IF($AM$11<>"",B27,"") | AN28: =IF($AN$11<>"",B27,"") | AO28: =IF($AO$11<>"",B27,"") | AP28: =IF($AP$11<>"",B27,"") | AQ28: =IF($AQ$11<>"",B27,"") | AR28: =IF($AR$11<>"",B27,"") | AS28: =IF($AS$11<>"",B27,"") | AT28: =IF($AT$11<>"",B27,"") | AU28: =IF($AU$11<>"",B27,"") | AV28: =IF($AV$11<>"",B27,"") | AW28: =IF($AW$11<>"",B27,"") | AX28: =IF($AX$11<>"",B27,"") | AY28: =IF($AY$11<>"",B27,"") | AZ28: =IF($AZ$11<>"",B27,"") | BA28: =IF($BA$11<>"",B27,"") | BB28: =IF($BB$11<>"",B27,"") | BC28: =IF($BC$11<>"",B27,"") | BD28: =IF($BD$11<>"",B27,"") | BE28: =IF($BE$11<>"",B27,"") | BF28: =IF($BF$11<>"",B27,"") | BG28: =IF($BG$11<>"",B27,"") | BH28: =IF($BH$11<>"",B27,"") | BI28: =IF($BI$11<>"",B27,"") | BJ28: =IF($BJ$11<>"",B27,"") | BK28: =IF($BK$11<>"",B27,"") | BL28: =IF($BL$11<>"",B27,"") | BM28: =IF($BM$11<>"",B27,"") | BN28: =IF($BN$11<>"",B27,"") | BO28: =IF($BO$11<>"",B27,"") | BP28: =IF($BP$11<>"",B27,"") | BQ28: =IF($BQ$11<>"",B27,"") | BR28: =IF($BR$11<>"",B27,"") | BS28: =IF($BS$11<>"",B27,"") | BT28: =IF($BT$11<>"",B27,"") | BU28: =IF($BU$11<>"",B27,"") | BV28: =IF($BV$11<>"",B27,"") | BW28: =IF($BW$11<>"",B27,"") | BX28: =IF($BX$11<>"",B27,"") | BY28: =IF($BY$11<>"",B27,"") | BZ28: =IF($BZ$11<>"",B27,"") | CA28: =IF($CA$11<>"",B27,"") | CB28: =IF($CB$11<>"",B27,"") | CC28: =IF($CC$11<>"",B27,"") | CD28: =IF($CD$11<>"",B27,"") | CE28: =IF($CE$11<>"",B27,"") | CF28: =IF($CF$11<>"",B27,"") | CG28: =IF($CG$11<>"",B27,"") | CH28: =IF($CH$11<>"",B27,"") | CI28: =IF($CI$11<>"",B27,"") | CJ28: =IF($CJ$11<>"",B27,"") | CK28: =IF($CK$11<>"",B27,"") | CL28: =IF($CL$11<>"",B27,"") | CM28: =IF($CM$11<>"",B27,"") | CN28: =IF($CN$11<>"",B27,"") | CO28: =IF($CO$11<>"",B27,"") | CP28: =IF($CP$11<>"",B27,"") | CQ28: =IF($CQ$11<>"",B27,"") | CR28: =IF($CR$11<>"",B27,"") | CS28: =IF(CS27<>"",$B27,"") | CT28: =IF($CT$11<>"",B27,"") | CU28: =IF($CU$11<>"",B27,"") | CV28: =IF($CV$11<>"",B27,"") | CW28: =IF($CW$11<>"",B27,"") | CX28: =IF($CX$11<>"",B27,"") | CY28: =IF($CY$11<>"",B27,"") | CZ28: =IF($CZ$11<>"",B27,"") | DA28: =IF($DA$11<>"",B27,"") | DB28: =IF($DB$11<>"",B27,"") | DC28: =IF($DC$11<>"",B27,"") | DD28: =IF($DD$11<>"",B27,"") | DE28: =IF($DE$11<>"",B27,"") | DF28: =IF($DF$11<>"",B27,"") | DG28: =IF($DG$11<>"",B27,"") | DH28: =IF($DH$11<>"",B27,"") | DI28: =IF($DI$11<>"",B27,"") | DJ28: =IF($DJ$11<>"",B27,"") | DK28: =IF($DK$11<>"",$B27,"") | DL28: =IF($DL$11<>"",$B27,"") | DM28: =IF($DM$11<>"",$B27,"") | DN28: =IF($DN$11<>"",$B27,"") | DO28: =IF($DO$11<>"",$B27,"") | DP28: =IF($DP$11<>"",$B27,"") | DQ28: =IF($DQ$11<>"",$B27,"") | DR28: =IF($DR$11<>"",$B27,"") | DS28: =IF($DS$11<>"",$B27,"") | DT28: =IF($DT$11<>"",$B27,"") | DU28: =IF($DU$11<>"",$B27,"") | DV28: =IF($DV$11<>"",$B27,"") | DY28: BERMUDA INFANTIL | DZ28: OLIST | EA28: ACOSTAMENTO YOUNG | EB28: AMARELO ABACAXI | EC28: ADRI
A29: =IF(PEDIDO!C54<>"",PEDIDO!B54,"") | B29: =IF(PEDIDO!X54<>"",PEDIDO!X54,"") | C29: =IF(PEDIDO!AA54<>"",PEDIDO!AA54,"") | D29: =IF(PEDIDO!AD54<>"",PEDIDO!AD54,"") | E29: =IF(PEDIDO!AG54<>"",PEDIDO!AG54,"") | F29: =IF(PEDIDO!AJ54<>"",PEDIDO!AJ54,"") | J29: =IF(PEDIDO!C53<>"",PEDIDO!B53,"") | K29: =IF($K$11<>"",B28,"") | L29: =IF($L$11<>"",B28,"") | M29: =IF($M$11<>"",B28,"") | N29: =IF($N$11<>"",B28,"") | O29: =IF($O$11<>"",B28,"") | P29: =IF($P$11<>"",B28,"") | Q29: =IF($Q$11<>"",B28,"") | R29: =IF($R$11<>"",B28,"") | S29: =IF($S$11<>"",B28,"") | T29: =IF($T$11<>"",B28,"") | U29: =IF($U$11<>"",B28,"") | V29: =IF($V$11<>"",B28,"") | X29: =IF($X$11<>"",B28,"") | Y29: =IF($Y$11<>"",B28,"") | Z29: =IF($Z$11<>"",B28,"") | AA29: =IF($AA$11<>"",B28,"") | AB29: =IF($AB$11<>"",B28,"") | AC29: =IF($AC$11<>"",B28,"") | AD29: =IF($AD$11<>"",B28,"") | AE29: =IF($AE$11<>"",B28,"") | AF29: =IF($AF$11<>"",B28,"") | AG29: =IF($AG$11<>"",B28,"") | AH29: =IF($AH$11<>"",B28,"") | AI29: =IF($AI$11<>"",B28,"") | AJ29: =IF($AJ$11<>"",B28,"") | AK29: =IF($AK$11<>"",B28,"") | AL29: =IF($AL$11<>"",B28,"") | AM29: =IF($AM$11<>"",B28,"") | AN29: =IF($AN$11<>"",B28,"") | AO29: =IF($AO$11<>"",B28,"") | AP29: =IF($AP$11<>"",B28,"") | AQ29: =IF($AQ$11<>"",B28,"") | AR29: =IF($AR$11<>"",B28,"") | AS29: =IF($AS$11<>"",B28,"") | AT29: =IF($AT$11<>"",B28,"") | AU29: =IF($AU$11<>"",B28,"") | AV29: =IF($AV$11<>"",B28,"") | AW29: =IF($AW$11<>"",B28,"") | AX29: =IF($AX$11<>"",B28,"") | AY29: =IF($AY$11<>"",B28,"") | AZ29: =IF($AZ$11<>"",B28,"") | BA29: =IF($BA$11<>"",B28,"") | BB29: =IF($BB$11<>"",B28,"") | BC29: =IF($BC$11<>"",B28,"") | BD29: =IF($BD$11<>"",B28,"") | BE29: =IF($BE$11<>"",B28,"") | BF29: =IF($BF$11<>"",B28,"") | BG29: =IF($BG$11<>"",B28,"") | BH29: =IF($BH$11<>"",B28,"") | BI29: =IF($BI$11<>"",B28,"") | BJ29: =IF($BJ$11<>"",B28,"") | BK29: =IF($BK$11<>"",B28,"") | BL29: =IF($BL$11<>"",B28,"") | BM29: =IF($BM$11<>"",B28,"") | BN29: =IF($BN$11<>"",B28,"") | BO29: =IF($BO$11<>"",B28,"") | BP29: =IF($BP$11<>"",B28,"") | BQ29: =IF($BQ$11<>"",B28,"") | BR29: =IF($BR$11<>"",B28,"") | BS29: =IF($BS$11<>"",B28,"") | BT29: =IF($BT$11<>"",B28,"") | BU29: =IF($BU$11<>"",B28,"") | BV29: =IF($BV$11<>"",B28,"") | BW29: =IF($BW$11<>"",B28,"") | BX29: =IF($BX$11<>"",B28,"") | BY29: =IF($BY$11<>"",B28,"") | BZ29: =IF($BZ$11<>"",B28,"") | CA29: =IF($CA$11<>"",B28,"") | CB29: =IF($CB$11<>"",B28,"") | CC29: =IF($CC$11<>"",B28,"") | CD29: =IF($CD$11<>"",B28,"") | CE29: =IF($CE$11<>"",B28,"") | CF29: =IF($CF$11<>"",B28,"") | CG29: =IF($CG$11<>"",B28,"") | CH29: =IF($CH$11<>"",B28,"") | CI29: =IF($CI$11<>"",B28,"") | CJ29: =IF($CJ$11<>"",B28,"") | CK29: =IF($CK$11<>"",B28,"") | CL29: =IF($CL$11<>"",B28,"") | CM29: =IF($CM$11<>"",B28,"") | CN29: =IF($CN$11<>"",B28,"") | CO29: =IF($CO$11<>"",B28,"") | CP29: =IF($CP$11<>"",B28,"") | CQ29: =IF($CQ$11<>"",B28,"") | CR29: =IF($CR$11<>"",B28,"") | CS29: =IF(CS28<>"",$B28,"") | CT29: =IF($CT$11<>"",B28,"") | CU29: =IF($CU$11<>"",B28,"") | CV29: =IF($CV$11<>"",B28,"") | CW29: =IF($CW$11<>"",B28,"") | CX29: =IF($CX$11<>"",B28,"") | CY29: =IF($CY$11<>"",B28,"") | CZ29: =IF($CZ$11<>"",B28,"") | DA29: =IF($DA$11<>"",B28,"") | DB29: =IF($DB$11<>"",B28,"") | DC29: =IF($DC$11<>"",B28,"") | DD29: =IF($DD$11<>"",B28,"") | DE29: =IF($DE$11<>"",B28,"") | DF29: =IF($DF$11<>"",B28,"") | DG29: =IF($DG$11<>"",B28,"") | DH29: =IF($DH$11<>"",B28,"") | DI29: =IF($DI$11<>"",B28,"") | DJ29: =IF($DJ$11<>"",B28,"") | DK29: =IF($DK$11<>"",$B28,"") | DL29: =IF($DL$11<>"",$B28,"") | DM29: =IF($DM$11<>"",$B28,"") | DN29: =IF($DN$11<>"",$B28,"") | DO29: =IF($DO$11<>"",$B28,"") | DP29: =IF($DP$11<>"",$B28,"") | DQ29: =IF($DQ$11<>"",$B28,"") | DR29: =IF($DR$11<>"",$B28,"") | DS29: =IF($DS$11<>"",$B28,"") | DT29: =IF($DT$11<>"",$B28,"") | DU29: =IF($DU$11<>"",$B28,"") | DV29: =IF($DV$11<>"",$B28,"") | DY29: BERMUDA INFANTIL FEMININO | DZ29: SILVESTRE | EA29: ACQUA MARINE | EB29: AMARELO BEBE | EC29: AIR FLOW
A30: =IF(PEDIDO!C55<>"",PEDIDO!B55,"") | B30: =IF(PEDIDO!X55<>"",PEDIDO!X55,"") | C30: =IF(PEDIDO!AA55<>"",PEDIDO!AA55,"") | D30: =IF(PEDIDO!AD55<>"",PEDIDO!AD55,"") | E30: =IF(PEDIDO!AG55<>"",PEDIDO!AG55,"") | F30: =IF(PEDIDO!AJ55<>"",PEDIDO!AJ55,"") | J30: =IF(PEDIDO!C54<>"",PEDIDO!B54,"") | K30: =IF($K$11<>"",B29,"") | L30: =IF($L$11<>"",B29,"") | M30: =IF($M$11<>"",B29,"") | N30: =IF($N$11<>"",B29,"") | O30: =IF($O$11<>"",B29,"") | P30: =IF($P$11<>"",B29,"") | Q30: =IF($Q$11<>"",B29,"") | R30: =IF($R$11<>"",B29,"") | S30: =IF($S$11<>"",B29,"") | T30: =IF($T$11<>"",B29,"") | U30: =IF($U$11<>"",B29,"") | V30: =IF($V$11<>"",B29,"") | X30: =IF($X$11<>"",B29,"") | Y30: =IF($Y$11<>"",B29,"") | Z30: =IF($Z$11<>"",B29,"") | AA30: =IF($AA$11<>"",B29,"") | AB30: =IF($AB$11<>"",B29,"") | AC30: =IF($AC$11<>"",B29,"") | AD30: =IF($AD$11<>"",B29,"") | AE30: =IF($AE$11<>"",B29,"") | AF30: =IF($AF$11<>"",B29,"") | AG30: =IF($AG$11<>"",B29,"") | AH30: =IF($AH$11<>"",B29,"") | AI30: =IF($AI$11<>"",B29,"") | AJ30: =IF($AJ$11<>"",B29,"") | AK30: =IF($AK$11<>"",B29,"") | AL30: =IF($AL$11<>"",B29,"") | AM30: =IF($AM$11<>"",B29,"") | AN30: =IF($AN$11<>"",B29,"") | AO30: =IF($AO$11<>"",B29,"") | AP30: =IF($AP$11<>"",B29,"") | AQ30: =IF($AQ$11<>"",B29,"") | AR30: =IF($AR$11<>"",B29,"") | AS30: =IF($AS$11<>"",B29,"") | AT30: =IF($AT$11<>"",B29,"") | AU30: =IF($AU$11<>"",B29,"") | AV30: =IF($AV$11<>"",B29,"") | AW30: =IF($AW$11<>"",B29,"") | AX30: =IF($AX$11<>"",B29,"") | AY30: =IF($AY$11<>"",B29,"") | AZ30: =IF($AZ$11<>"",B29,"") | BA30: =IF($BA$11<>"",B29,"") | BB30: =IF($BB$11<>"",B29,"") | BC30: =IF($BC$11<>"",B29,"") | BD30: =IF($BD$11<>"",B29,"") | BE30: =IF($BE$11<>"",B29,"") | BF30: =IF($BF$11<>"",B29,"") | BG30: =IF($BG$11<>"",B29,"") | BH30: =IF($BH$11<>"",B29,"") | BI30: =IF($BI$11<>"",B29,"") | BJ30: =IF($BJ$11<>"",B29,"") | BK30: =IF($BK$11<>"",B29,"") | BL30: =IF($BL$11<>"",B29,"") | BM30: =IF($BM$11<>"",B29,"") | BN30: =IF($BN$11<>"",B29,"") | BO30: =IF($BO$11<>"",B29,"") | BP30: =IF($BP$11<>"",B29,"") | BQ30: =IF($BQ$11<>"",B29,"") | BR30: =IF($BR$11<>"",B29,"") | BS30: =IF($BS$11<>"",B29,"") | BT30: =IF($BT$11<>"",B29,"") | BU30: =IF($BU$11<>"",B29,"") | BV30: =IF($BV$11<>"",B29,"") | BW30: =IF($BW$11<>"",B29,"") | BX30: =IF($BX$11<>"",B29,"") | BY30: =IF($BY$11<>"",B29,"") | BZ30: =IF($BZ$11<>"",B29,"") | CA30: =IF($CA$11<>"",B29,"") | CB30: =IF($CB$11<>"",B29,"") | CC30: =IF($CC$11<>"",B29,"") | CD30: =IF($CD$11<>"",B29,"") | CE30: =IF($CE$11<>"",B29,"") | CF30: =IF($CF$11<>"",B29,"") | CG30: =IF($CG$11<>"",B29,"") | CH30: =IF($CH$11<>"",B29,"") | CI30: =IF($CI$11<>"",B29,"") | CJ30: =IF($CJ$11<>"",B29,"") | CK30: =IF($CK$11<>"",B29,"") | CL30: =IF($CL$11<>"",B29,"") | CM30: =IF($CM$11<>"",B29,"") | CN30: =IF($CN$11<>"",B29,"") | CO30: =IF($CO$11<>"",B29,"") | CP30: =IF($CP$11<>"",B29,"") | CQ30: =IF($CQ$11<>"",B29,"") | CR30: =IF($CR$11<>"",B29,"") | CS30: =IF(CS29<>"",$B29,"") | CT30: =IF($CT$11<>"",B29,"") | CU30: =IF($CU$11<>"",B29,"") | CV30: =IF($CV$11<>"",B29,"") | CW30: =IF($CW$11<>"",B29,"") | CX30: =IF($CX$11<>"",B29,"") | CY30: =IF($CY$11<>"",B29,"") | CZ30: =IF($CZ$11<>"",B29,"") | DA30: =IF($DA$11<>"",B29,"") | DB30: =IF($DB$11<>"",B29,"") | DC30: =IF($DC$11<>"",B29,"") | DD30: =IF($DD$11<>"",B29,"") | DE30: =IF($DE$11<>"",B29,"") | DF30: =IF($DF$11<>"",B29,"") | DG30: =IF($DG$11<>"",B29,"") | DH30: =IF($DH$11<>"",B29,"") | DI30: =IF($DI$11<>"",B29,"") | DJ30: =IF($DJ$11<>"",B29,"") | DK30: =IF($DK$11<>"",$B29,"") | DL30: =IF($DL$11<>"",$B29,"") | DM30: =IF($DM$11<>"",$B29,"") | DN30: =IF($DN$11<>"",$B29,"") | DO30: =IF($DO$11<>"",$B29,"") | DP30: =IF($DP$11<>"",$B29,"") | DQ30: =IF($DQ$11<>"",$B29,"") | DR30: =IF($DR$11<>"",$B29,"") | DS30: =IF($DS$11<>"",$B29,"") | DT30: =IF($DT$11<>"",$B29,"") | DU30: =IF($DU$11<>"",$B29,"") | DV30: =IF($DV$11<>"",$B29,"") | DY30: BERMUDA INFANTIL MASCULINO | DZ30: ART FLEX | EA30: ACQUALARA | EB30: AMARELO CANDY | EC30: ALABAMA
A31: =IF(PEDIDO!C56<>"",PEDIDO!B56,"") | B31: =IF(PEDIDO!X56<>"",PEDIDO!X56,"") | C31: =IF(PEDIDO!AA56<>"",PEDIDO!AA56,"") | D31: =IF(PEDIDO!AD56<>"",PEDIDO!AD56,"") | E31: =IF(PEDIDO!AG56<>"",PEDIDO!AG56,"") | F31: =IF(PEDIDO!AJ56<>"",PEDIDO!AJ56,"") | J31: =IF(PEDIDO!C55<>"",PEDIDO!B55,"") | K31: =IF($K$11<>"",B30,"") | L31: =IF($L$11<>"",B30,"") | M31: =IF($M$11<>"",B30,"") | N31: =IF($N$11<>"",B30,"") | O31: =IF($O$11<>"",B30,"") | P31: =IF($P$11<>"",B30,"") | Q31: =IF($Q$11<>"",B30,"") | R31: =IF($R$11<>"",B30,"") | S31: =IF($S$11<>"",B30,"") | T31: =IF($T$11<>"",B30,"") | U31: =IF($U$11<>"",B30,"") | V31: =IF($V$11<>"",B30,"") | X31: =IF($X$11<>"",B30,"") | Y31: =IF($Y$11<>"",B30,"") | Z31: =IF($Z$11<>"",B30,"") | AA31: =IF($AA$11<>"",B30,"") | AB31: =IF($AB$11<>"",B30,"") | AC31: =IF($AC$11<>"",B30,"") | AD31: =IF($AD$11<>"",B30,"") | AE31: =IF($AE$11<>"",B30,"") | AF31: =IF($AF$11<>"",B30,"") | AG31: =IF($AG$11<>"",B30,"") | AH31: =IF($AH$11<>"",B30,"") | AI31: =IF($AI$11<>"",B30,"") | AJ31: =IF($AJ$11<>"",B30,"") | AK31: =IF($AK$11<>"",B30,"") | AL31: =IF($AL$11<>"",B30,"") | AM31: =IF($AM$11<>"",B30,"") | AN31: =IF($AN$11<>"",B30,"") | AO31: =IF($AO$11<>"",B30,"") | AP31: =IF($AP$11<>"",B30,"") | AQ31: =IF($AQ$11<>"",B30,"") | AR31: =IF($AR$11<>"",B30,"") | AS31: =IF($AS$11<>"",B30,"") | AT31: =IF($AT$11<>"",B30,"") | AU31: =IF($AU$11<>"",B30,"") | AV31: =IF($AV$11<>"",B30,"") | AW31: =IF($AW$11<>"",B30,"") | AX31: =IF($AX$11<>"",B30,"") | AY31: =IF($AY$11<>"",B30,"") | AZ31: =IF($AZ$11<>"",B30,"") | BA31: =IF($BA$11<>"",B30,"") | BB31: =IF($BB$11<>"",B30,"") | BC31: =IF($BC$11<>"",B30,"") | BD31: =IF($BD$11<>"",B30,"") | BE31: =IF($BE$11<>"",B30,"") | BF31: =IF($BF$11<>"",B30,"") | BG31: =IF($BG$11<>"",B30,"") | BH31: =IF($BH$11<>"",B30,"") | BI31: =IF($BI$11<>"",B30,"") | BJ31: =IF($BJ$11<>"",B30,"") | BK31: =IF($BK$11<>"",B30,"") | BL31: =IF($BL$11<>"",B30,"") | BM31: =IF($BM$11<>"",B30,"") | BN31: =IF($BN$11<>"",B30,"") | BO31: =IF($BO$11<>"",B30,"") | BP31: =IF($BP$11<>"",B30,"") | BQ31: =IF($BQ$11<>"",B30,"") | BR31: =IF($BR$11<>"",B30,"") | BS31: =IF($BS$11<>"",B30,"") | BT31: =IF($BT$11<>"",B30,"") | BU31: =IF($BU$11<>"",B30,"") | BV31: =IF($BV$11<>"",B30,"") | BW31: =IF($BW$11<>"",B30,"") | BX31: =IF($BX$11<>"",B30,"") | BY31: =IF($BY$11<>"",B30,"") | BZ31: =IF($BZ$11<>"",B30,"") | CA31: =IF($CA$11<>"",B30,"") | CB31: =IF($CB$11<>"",B30,"") | CC31: =IF($CC$11<>"",B30,"") | CD31: =IF($CD$11<>"",B30,"") | CE31: =IF($CE$11<>"",B30,"") | CF31: =IF($CF$11<>"",B30,"") | CG31: =IF($CG$11<>"",B30,"") | CH31: =IF($CH$11<>"",B30,"") | CI31: =IF($CI$11<>"",B30,"") | CJ31: =IF($CJ$11<>"",B30,"") | CK31: =IF($CK$11<>"",B30,"") | CL31: =IF($CL$11<>"",B30,"") | CM31: =IF($CM$11<>"",B30,"") | CN31: =IF($CN$11<>"",B30,"") | CO31: =IF($CO$11<>"",B30,"") | CP31: =IF($CP$11<>"",B30,"") | CQ31: =IF($CQ$11<>"",B30,"") | CR31: =IF($CR$11<>"",B30,"") | CS31: =IF(CS30<>"",$B30,"") | CT31: =IF($CT$11<>"",B30,"") | CU31: =IF($CU$11<>"",B30,"") | CV31: =IF($CV$11<>"",B30,"") | CW31: =IF($CW$11<>"",B30,"") | CX31: =IF($CX$11<>"",B30,"") | CY31: =IF($CY$11<>"",B30,"") | CZ31: =IF($CZ$11<>"",B30,"") | DA31: =IF($DA$11<>"",B30,"") | DB31: =IF($DB$11<>"",B30,"") | DC31: =IF($DC$11<>"",B30,"") | DD31: =IF($DD$11<>"",B30,"") | DE31: =IF($DE$11<>"",B30,"") | DF31: =IF($DF$11<>"",B30,"") | DG31: =IF($DG$11<>"",B30,"") | DH31: =IF($DH$11<>"",B30,"") | DI31: =IF($DI$11<>"",B30,"") | DJ31: =IF($DJ$11<>"",B30,"") | DK31: =IF($DK$11<>"",$B30,"") | DL31: =IF($DL$11<>"",$B30,"") | DM31: =IF($DM$11<>"",$B30,"") | DN31: =IF($DN$11<>"",$B30,"") | DO31: =IF($DO$11<>"",$B30,"") | DP31: =IF($DP$11<>"",$B30,"") | DQ31: =IF($DQ$11<>"",$B30,"") | DR31: =IF($DR$11<>"",$B30,"") | DS31: =IF($DS$11<>"",$B30,"") | DT31: =IF($DT$11<>"",$B30,"") | DU31: =IF($DU$11<>"",$B30,"") | DV31: =IF($DV$11<>"",$B30,"") | DY31: BERMUDA MASCULINO | DZ31: MR DISTTIBUICAO | EA31: ACQUALEV | EB31: AMARELO CITRICO | EC31: ALCA DUPLA
A32: =IF(PEDIDO!C57<>"",PEDIDO!B57,"") | B32: =IF(PEDIDO!X57<>"",PEDIDO!X57,"") | C32: =IF(PEDIDO!AA57<>"",PEDIDO!AA57,"") | D32: =IF(PEDIDO!AD57<>"",PEDIDO!AD57,"") | E32: =IF(PEDIDO!AG57<>"",PEDIDO!AG57,"") | F32: =IF(PEDIDO!AJ57<>"",PEDIDO!AJ57,"") | J32: =IF(PEDIDO!C56<>"",PEDIDO!B56,"") | K32: =IF($K$11<>"",B31,"") | L32: =IF($L$11<>"",B31,"") | M32: =IF($M$11<>"",B31,"") | N32: =IF($N$11<>"",B31,"") | O32: =IF($O$11<>"",B31,"") | P32: =IF($P$11<>"",B31,"") | Q32: =IF($Q$11<>"",B31,"") | R32: =IF($R$11<>"",B31,"") | S32: =IF($S$11<>"",B31,"") | T32: =IF($T$11<>"",B31,"") | U32: =IF($U$11<>"",B31,"") | V32: =IF($V$11<>"",B31,"") | X32: =IF($X$11<>"",B31,"") | Y32: =IF($Y$11<>"",B31,"") | Z32: =IF($Z$11<>"",B31,"") | AA32: =IF($AA$11<>"",B31,"") | AB32: =IF($AB$11<>"",B31,"") | AC32: =IF($AC$11<>"",B31,"") | AD32: =IF($AD$11<>"",B31,"") | AE32: =IF($AE$11<>"",B31,"") | AF32: =IF($AF$11<>"",B31,"") | AG32: =IF($AG$11<>"",B31,"") | AH32: =IF($AH$11<>"",B31,"") | AI32: =IF($AI$11<>"",B31,"") | AJ32: =IF($AJ$11<>"",B31,"") | AK32: =IF($AK$11<>"",B31,"") | AL32: =IF($AL$11<>"",B31,"") | AM32: =IF($AM$11<>"",B31,"") | AN32: =IF($AN$11<>"",B31,"") | AO32: =IF($AO$11<>"",B31,"") | AP32: =IF($AP$11<>"",B31,"") | AQ32: =IF($AQ$11<>"",B31,"") | AR32: =IF($AR$11<>"",B31,"") | AS32: =IF($AS$11<>"",B31,"") | AT32: =IF($AT$11<>"",B31,"") | AU32: =IF($AU$11<>"",B31,"") | AV32: =IF($AV$11<>"",B31,"") | AW32: =IF($AW$11<>"",B31,"") | AX32: =IF($AX$11<>"",B31,"") | AY32: =IF($AY$11<>"",B31,"") | AZ32: =IF($AZ$11<>"",B31,"") | BA32: =IF($BA$11<>"",B31,"") | BB32: =IF($BB$11<>"",B31,"") | BC32: =IF($BC$11<>"",B31,"") | BD32: =IF($BD$11<>"",B31,"") | BE32: =IF($BE$11<>"",B31,"") | BF32: =IF($BF$11<>"",B31,"") | BG32: =IF($BG$11<>"",B31,"") | BH32: =IF($BH$11<>"",B31,"") | BI32: =IF($BI$11<>"",B31,"") | BJ32: =IF($BJ$11<>"",B31,"") | BK32: =IF($BK$11<>"",B31,"") | BL32: =IF($BL$11<>"",B31,"") | BM32: =IF($BM$11<>"",B31,"") | BN32: =IF($BN$11<>"",B31,"") | BO32: =IF($BO$11<>"",B31,"") | BP32: =IF($BP$11<>"",B31,"") | BQ32: =IF($BQ$11<>"",B31,"") | BR32: =IF($BR$11<>"",B31,"") | BS32: =IF($BS$11<>"",B31,"") | BT32: =IF($BT$11<>"",B31,"") | BU32: =IF($BU$11<>"",B31,"") | BV32: =IF($BV$11<>"",B31,"") | BW32: =IF($BW$11<>"",B31,"") | BX32: =IF($BX$11<>"",B31,"") | BY32: =IF($BY$11<>"",B31,"") | BZ32: =IF($BZ$11<>"",B31,"") | CA32: =IF($CA$11<>"",B31,"") | CB32: =IF($CB$11<>"",B31,"") | CC32: =IF($CC$11<>"",B31,"") | CD32: =IF($CD$11<>"",B31,"") | CE32: =IF($CE$11<>"",B31,"") | CF32: =IF($CF$11<>"",B31,"") | CG32: =IF($CG$11<>"",B31,"") | CH32: =IF($CH$11<>"",B31,"") | CI32: =IF($CI$11<>"",B31,"") | CJ32: =IF($CJ$11<>"",B31,"") | CK32: =IF($CK$11<>"",B31,"") | CL32: =IF($CL$11<>"",B31,"") | CM32: =IF($CM$11<>"",B31,"") | CN32: =IF($CN$11<>"",B31,"") | CO32: =IF($CO$11<>"",B31,"") | CP32: =IF($CP$11<>"",B31,"") | CQ32: =IF($CQ$11<>"",B31,"") | CR32: =IF($CR$11<>"",B31,"") | CS32: =IF(CS31<>"",$B31,"") | CT32: =IF($CT$11<>"",B31,"") | CU32: =IF($CU$11<>"",B31,"") | CV32: =IF($CV$11<>"",B31,"") | CW32: =IF($CW$11<>"",B31,"") | CX32: =IF($CX$11<>"",B31,"") | CY32: =IF($CY$11<>"",B31,"") | CZ32: =IF($CZ$11<>"",B31,"") | DA32: =IF($DA$11<>"",B31,"") | DB32: =IF($DB$11<>"",B31,"") | DC32: =IF($DC$11<>"",B31,"") | DD32: =IF($DD$11<>"",B31,"") | DE32: =IF($DE$11<>"",B31,"") | DF32: =IF($DF$11<>"",B31,"") | DG32: =IF($DG$11<>"",B31,"") | DH32: =IF($DH$11<>"",B31,"") | DI32: =IF($DI$11<>"",B31,"") | DJ32: =IF($DJ$11<>"",B31,"") | DK32: =IF($DK$11<>"",$B31,"") | DL32: =IF($DL$11<>"",$B31,"") | DM32: =IF($DM$11<>"",$B31,"") | DN32: =IF($DN$11<>"",$B31,"") | DO32: =IF($DO$11<>"",$B31,"") | DP32: =IF($DP$11<>"",$B31,"") | DQ32: =IF($DQ$11<>"",$B31,"") | DR32: =IF($DR$11<>"",$B31,"") | DS32: =IF($DS$11<>"",$B31,"") | DT32: =IF($DT$11<>"",$B31,"") | DU32: =IF($DU$11<>"",$B31,"") | DV32: =IF($DV$11<>"",$B31,"") | DY32: BERMUDA MASCULINO PLUS | DZ32: INFINIT TECH | EA32: ACTIVITTA | EB32: AMARELO CITRUS | EC32: ALFAIATARIA
A33: =IF(PEDIDO!C58<>"",PEDIDO!B58,"") | B33: =IF(PEDIDO!X58<>"",PEDIDO!X58,"") | C33: =IF(PEDIDO!AA58<>"",PEDIDO!AA58,"") | D33: =IF(PEDIDO!AD58<>"",PEDIDO!AD58,"") | E33: =IF(PEDIDO!AG58<>"",PEDIDO!AG58,"") | F33: =IF(PEDIDO!AJ58<>"",PEDIDO!AJ58,"") | J33: =IF(PEDIDO!C57<>"",PEDIDO!B57,"") | K33: =IF($K$11<>"",B32,"") | L33: =IF($L$11<>"",B32,"") | M33: =IF($M$11<>"",B32,"") | N33: =IF($N$11<>"",B32,"") | O33: =IF($O$11<>"",B32,"") | P33: =IF($P$11<>"",B32,"") | Q33: =IF($Q$11<>"",B32,"") | R33: =IF($R$11<>"",B32,"") | S33: =IF($S$11<>"",B32,"") | T33: =IF($T$11<>"",B32,"") | U33: =IF($U$11<>"",B32,"") | V33: =IF($V$11<>"",B32,"") | X33: =IF($X$11<>"",B32,"") | Y33: =IF($Y$11<>"",B32,"") | Z33: =IF($Z$11<>"",B32,"") | AA33: =IF($AA$11<>"",B32,"") | AB33: =IF($AB$11<>"",B32,"") | AC33: =IF($AC$11<>"",B32,"") | AD33: =IF($AD$11<>"",B32,"") | AE33: =IF($AE$11<>"",B32,"") | AF33: =IF($AF$11<>"",B32,"") | AG33: =IF($AG$11<>"",B32,"") | AH33: =IF($AH$11<>"",B32,"") | AI33: =IF($AI$11<>"",B32,"") | AJ33: =IF($AJ$11<>"",B32,"") | AK33: =IF($AK$11<>"",B32,"") | AL33: =IF($AL$11<>"",B32,"") | AM33: =IF($AM$11<>"",B32,"") | AN33: =IF($AN$11<>"",B32,"") | AO33: =IF($AO$11<>"",B32,"") | AP33: =IF($AP$11<>"",B32,"") | AQ33: =IF($AQ$11<>"",B32,"") | AR33: =IF($AR$11<>"",B32,"") | AS33: =IF($AS$11<>"",B32,"") | AT33: =IF($AT$11<>"",B32,"") | AU33: =IF($AU$11<>"",B32,"") | AV33: =IF($AV$11<>"",B32,"") | AW33: =IF($AW$11<>"",B32,"") | AX33: =IF($AX$11<>"",B32,"") | AY33: =IF($AY$11<>"",B32,"") | AZ33: =IF($AZ$11<>"",B32,"") | BA33: =IF($BA$11<>"",B32,"") | BB33: =IF($BB$11<>"",B32,"") | BC33: =IF($BC$11<>"",B32,"") | BD33: =IF($BD$11<>"",B32,"") | BE33: =IF($BE$11<>"",B32,"") | BF33: =IF($BF$11<>"",B32,"") | BG33: =IF($BG$11<>"",B32,"") | BH33: =IF($BH$11<>"",B32,"") | BI33: =IF($BI$11<>"",B32,"") | BJ33: =IF($BJ$11<>"",B32,"") | BK33: =IF($BK$11<>"",B32,"") | BL33: =IF($BL$11<>"",B32,"") | BM33: =IF($BM$11<>"",B32,"") | BN33: =IF($BN$11<>"",B32,"") | BO33: =IF($BO$11<>"",B32,"") | BP33: =IF($BP$11<>"",B32,"") | BQ33: =IF($BQ$11<>"",B32,"") | BR33: =IF($BR$11<>"",B32,"") | BS33: =IF($BS$11<>"",B32,"") | BT33: =IF($BT$11<>"",B32,"") | BU33: =IF($BU$11<>"",B32,"") | BV33: =IF($BV$11<>"",B32,"") | BW33: =IF($BW$11<>"",B32,"") | BX33: =IF($BX$11<>"",B32,"") | BY33: =IF($BY$11<>"",B32,"") | BZ33: =IF($BZ$11<>"",B32,"") | CA33: =IF($CA$11<>"",B32,"") | CB33: =IF($CB$11<>"",B32,"") | CC33: =IF($CC$11<>"",B32,"") | CD33: =IF($CD$11<>"",B32,"") | CE33: =IF($CE$11<>"",B32,"") | CF33: =IF($CF$11<>"",B32,"") | CG33: =IF($CG$11<>"",B32,"") | CH33: =IF($CH$11<>"",B32,"") | CI33: =IF($CI$11<>"",B32,"") | CJ33: =IF($CJ$11<>"",B32,"") | CK33: =IF($CK$11<>"",B32,"") | CL33: =IF($CL$11<>"",B32,"") | CM33: =IF($CM$11<>"",B32,"") | CN33: =IF($CN$11<>"",B32,"") | CO33: =IF($CO$11<>"",B32,"") | CP33: =IF($CP$11<>"",B32,"") | CQ33: =IF($CQ$11<>"",B32,"") | CR33: =IF($CR$11<>"",B32,"") | CS33: =IF(CS32<>"",$B32,"") | CT33: =IF($CT$11<>"",B32,"") | CU33: =IF($CU$11<>"",B32,"") | CV33: =IF($CV$11<>"",B32,"") | CW33: =IF($CW$11<>"",B32,"") | CX33: =IF($CX$11<>"",B32,"") | CY33: =IF($CY$11<>"",B32,"") | CZ33: =IF($CZ$11<>"",B32,"") | DA33: =IF($DA$11<>"",B32,"") | DB33: =IF($DB$11<>"",B32,"") | DC33: =IF($DC$11<>"",B32,"") | DD33: =IF($DD$11<>"",B32,"") | DE33: =IF($DE$11<>"",B32,"") | DF33: =IF($DF$11<>"",B32,"") | DG33: =IF($DG$11<>"",B32,"") | DH33: =IF($DH$11<>"",B32,"") | DI33: =IF($DI$11<>"",B32,"") | DJ33: =IF($DJ$11<>"",B32,"") | DK33: =IF($DK$11<>"",$B32,"") | DL33: =IF($DL$11<>"",$B32,"") | DM33: =IF($DM$11<>"",$B32,"") | DN33: =IF($DN$11<>"",$B32,"") | DO33: =IF($DO$11<>"",$B32,"") | DP33: =IF($DP$11<>"",$B32,"") | DQ33: =IF($DQ$11<>"",$B32,"") | DR33: =IF($DR$11<>"",$B32,"") | DS33: =IF($DS$11<>"",$B32,"") | DT33: =IF($DT$11<>"",$B32,"") | DU33: =IF($DU$11<>"",$B32,"") | DV33: =IF($DV$11<>"",$B32,"") | DY33: BERMUDA TERMICA | DZ33: MACR | EA33: ACUCENA | EB33: AMARELO CLARO | EC33: ALKO
A34: =IF(PEDIDO!C59<>"",PEDIDO!B59,"") | B34: =IF(PEDIDO!X59<>"",PEDIDO!X59,"") | C34: =IF(PEDIDO!AA59<>"",PEDIDO!AA59,"") | D34: =IF(PEDIDO!AD59<>"",PEDIDO!AD59,"") | E34: =IF(PEDIDO!AG59<>"",PEDIDO!AG59,"") | F34: =IF(PEDIDO!AJ59<>"",PEDIDO!AJ59,"") | J34: =IF(PEDIDO!C58<>"",PEDIDO!B58,"") | K34: =IF($K$11<>"",B33,"") | L34: =IF($L$11<>"",B33,"") | M34: =IF($M$11<>"",B33,"") | N34: =IF($N$11<>"",B33,"") | O34: =IF($O$11<>"",B33,"") | P34: =IF($P$11<>"",B33,"") | Q34: =IF($Q$11<>"",B33,"") | R34: =IF($R$11<>"",B33,"") | S34: =IF($S$11<>"",B33,"") | T34: =IF($T$11<>"",B33,"") | U34: =IF($U$11<>"",B33,"") | V34: =IF($V$11<>"",B33,"") | X34: =IF($X$11<>"",B33,"") | Y34: =IF($Y$11<>"",B33,"") | Z34: =IF($Z$11<>"",B33,"") | AA34: =IF($AA$11<>"",B33,"") | AB34: =IF($AB$11<>"",B33,"") | AC34: =IF($AC$11<>"",B33,"") | AD34: =IF($AD$11<>"",B33,"") | AE34: =IF($AE$11<>"",B33,"") | AF34: =IF($AF$11<>"",B33,"") | AG34: =IF($AG$11<>"",B33,"") | AH34: =IF($AH$11<>"",B33,"") | AI34: =IF($AI$11<>"",B33,"") | AJ34: =IF($AJ$11<>"",B33,"") | AK34: =IF($AK$11<>"",B33,"") | AL34: =IF($AL$11<>"",B33,"") | AM34: =IF($AM$11<>"",B33,"") | AN34: =IF($AN$11<>"",B33,"") | AO34: =IF($AO$11<>"",B33,"") | AP34: =IF($AP$11<>"",B33,"") | AQ34: =IF($AQ$11<>"",B33,"") | AR34: =IF($AR$11<>"",B33,"") | AS34: =IF($AS$11<>"",B33,"") | AT34: =IF($AT$11<>"",B33,"") | AU34: =IF($AU$11<>"",B33,"") | AV34: =IF($AV$11<>"",B33,"") | AW34: =IF($AW$11<>"",B33,"") | AX34: =IF($AX$11<>"",B33,"") | AY34: =IF($AY$11<>"",B33,"") | AZ34: =IF($AZ$11<>"",B33,"") | BA34: =IF($BA$11<>"",B33,"") | BB34: =IF($BB$11<>"",B33,"") | BC34: =IF($BC$11<>"",B33,"") | BD34: =IF($BD$11<>"",B33,"") | BE34: =IF($BE$11<>"",B33,"") | BF34: =IF($BF$11<>"",B33,"") | BG34: =IF($BG$11<>"",B33,"") | BH34: =IF($BH$11<>"",B33,"") | BI34: =IF($BI$11<>"",B33,"") | BJ34: =IF($BJ$11<>"",B33,"") | BK34: =IF($BK$11<>"",B33,"") | BL34: =IF($BL$11<>"",B33,"") | BM34: =IF($BM$11<>"",B33,"") | BN34: =IF($BN$11<>"",B33,"") | BO34: =IF($BO$11<>"",B33,"") | BP34: =IF($BP$11<>"",B33,"") | BQ34: =IF($BQ$11<>"",B33,"") | BR34: =IF($BR$11<>"",B33,"") | BS34: =IF($BS$11<>"",B33,"") | BT34: =IF($BT$11<>"",B33,"") | BU34: =IF($BU$11<>"",B33,"") | BV34: =IF($BV$11<>"",B33,"") | BW34: =IF($BW$11<>"",B33,"") | BX34: =IF($BX$11<>"",B33,"") | BY34: =IF($BY$11<>"",B33,"") | BZ34: =IF($BZ$11<>"",B33,"") | CA34: =IF($CA$11<>"",B33,"") | CB34: =IF($CB$11<>"",B33,"") | CC34: =IF($CC$11<>"",B33,"") | CD34: =IF($CD$11<>"",B33,"") | CE34: =IF($CE$11<>"",B33,"") | CF34: =IF($CF$11<>"",B33,"") | CG34: =IF($CG$11<>"",B33,"") | CH34: =IF($CH$11<>"",B33,"") | CI34: =IF($CI$11<>"",B33,"") | CJ34: =IF($CJ$11<>"",B33,"") | CK34: =IF($CK$11<>"",B33,"") | CL34: =IF($CL$11<>"",B33,"") | CM34: =IF($CM$11<>"",B33,"") | CN34: =IF($CN$11<>"",B33,"") | CO34: =IF($CO$11<>"",B33,"") | CP34: =IF($CP$11<>"",B33,"") | CQ34: =IF($CQ$11<>"",B33,"") | CR34: =IF($CR$11<>"",B33,"") | CS34: =IF(CS33<>"",$B33,"") | CT34: =IF($CT$11<>"",B33,"") | CU34: =IF($CU$11<>"",B33,"") | CV34: =IF($CV$11<>"",B33,"") | CW34: =IF($CW$11<>"",B33,"") | CX34: =IF($CX$11<>"",B33,"") | CY34: =IF($CY$11<>"",B33,"") | CZ34: =IF($CZ$11<>"",B33,"") | DA34: =IF($DA$11<>"",B33,"") | DB34: =IF($DB$11<>"",B33,"") | DC34: =IF($DC$11<>"",B33,"") | DD34: =IF($DD$11<>"",B33,"") | DE34: =IF($DE$11<>"",B33,"") | DF34: =IF($DF$11<>"",B33,"") | DG34: =IF($DG$11<>"",B33,"") | DH34: =IF($DH$11<>"",B33,"") | DI34: =IF($DI$11<>"",B33,"") | DJ34: =IF($DJ$11<>"",B33,"") | DK34: =IF($DK$11<>"",$B33,"") | DL34: =IF($DL$11<>"",$B33,"") | DM34: =IF($DM$11<>"",$B33,"") | DN34: =IF($DN$11<>"",$B33,"") | DO34: =IF($DO$11<>"",$B33,"") | DP34: =IF($DP$11<>"",$B33,"") | DQ34: =IF($DQ$11<>"",$B33,"") | DR34: =IF($DR$11<>"",$B33,"") | DS34: =IF($DS$11<>"",$B33,"") | DT34: =IF($DT$11<>"",$B33,"") | DU34: =IF($DU$11<>"",$B33,"") | DV34: =IF($DV$11<>"",$B33,"") | DY34: BERMUDA TERMICA FEMININO | DZ34: COMPRE BEL | EA34: ADAGIO | EB34: AMARELO CURCUMA | EC34: ALL 4
A35: =IF(PEDIDO!C60<>"",PEDIDO!B60,"") | B35: =IF(PEDIDO!X60<>"",PEDIDO!X60,"") | C35: =IF(PEDIDO!AA60<>"",PEDIDO!AA60,"") | D35: =IF(PEDIDO!AD60<>"",PEDIDO!AD60,"") | E35: =IF(PEDIDO!AG60<>"",PEDIDO!AG60,"") | F35: =IF(PEDIDO!AJ60<>"",PEDIDO!AJ60,"") | J35: =IF(PEDIDO!C59<>"",PEDIDO!B59,"") | K35: =IF($K$11<>"",B34,"") | L35: =IF($L$11<>"",B34,"") | M35: =IF($M$11<>"",B34,"") | N35: =IF($N$11<>"",B34,"") | O35: =IF($O$11<>"",B34,"") | P35: =IF($P$11<>"",B34,"") | Q35: =IF($Q$11<>"",B34,"") | R35: =IF($R$11<>"",B34,"") | S35: =IF($S$11<>"",B34,"") | T35: =IF($T$11<>"",B34,"") | U35: =IF($U$11<>"",B34,"") | V35: =IF($V$11<>"",B34,"") | X35: =IF($X$11<>"",B34,"") | Y35: =IF($Y$11<>"",B34,"") | Z35: =IF($Z$11<>"",B34,"") | AA35: =IF($AA$11<>"",B34,"") | AB35: =IF($AB$11<>"",B34,"") | AC35: =IF($AC$11<>"",B34,"") | AD35: =IF($AD$11<>"",B34,"") | AE35: =IF($AE$11<>"",B34,"") | AF35: =IF($AF$11<>"",B34,"") | AG35: =IF($AG$11<>"",B34,"") | AH35: =IF($AH$11<>"",B34,"") | AI35: =IF($AI$11<>"",B34,"") | AJ35: =IF($AJ$11<>"",B34,"") | AK35: =IF($AK$11<>"",B34,"") | AL35: =IF($AL$11<>"",B34,"") | AM35: =IF($AM$11<>"",B34,"") | AN35: =IF($AN$11<>"",B34,"") | AO35: =IF($AO$11<>"",B34,"") | AP35: =IF($AP$11<>"",B34,"") | AQ35: =IF($AQ$11<>"",B34,"") | AR35: =IF($AR$11<>"",B34,"") | AS35: =IF($AS$11<>"",B34,"") | AT35: =IF($AT$11<>"",B34,"") | AU35: =IF($AU$11<>"",B34,"") | AV35: =IF($AV$11<>"",B34,"") | AW35: =IF($AW$11<>"",B34,"") | AX35: =IF($AX$11<>"",B34,"") | AY35: =IF($AY$11<>"",B34,"") | AZ35: =IF($AZ$11<>"",B34,"") | BA35: =IF($BA$11<>"",B34,"") | BB35: =IF($BB$11<>"",B34,"") | BC35: =IF($BC$11<>"",B34,"") | BD35: =IF($BD$11<>"",B34,"") | BE35: =IF($BE$11<>"",B34,"") | BF35: =IF($BF$11<>"",B34,"") | BG35: =IF($BG$11<>"",B34,"") | BH35: =IF($BH$11<>"",B34,"") | BI35: =IF($BI$11<>"",B34,"") | BJ35: =IF($BJ$11<>"",B34,"") | BK35: =IF($BK$11<>"",B34,"") | BL35: =IF($BL$11<>"",B34,"") | BM35: =IF($BM$11<>"",B34,"") | BN35: =IF($BN$11<>"",B34,"") | BO35: =IF($BO$11<>"",B34,"") | BP35: =IF($BP$11<>"",B34,"") | BQ35: =IF($BQ$11<>"",B34,"") | BR35: =IF($BR$11<>"",B34,"") | BS35: =IF($BS$11<>"",B34,"") | BT35: =IF($BT$11<>"",B34,"") | BU35: =IF($BU$11<>"",B34,"") | BV35: =IF($BV$11<>"",B34,"") | BW35: =IF($BW$11<>"",B34,"") | BX35: =IF($BX$11<>"",B34,"") | BY35: =IF($BY$11<>"",B34,"") | BZ35: =IF($BZ$11<>"",B34,"") | CA35: =IF($CA$11<>"",B34,"") | CB35: =IF($CB$11<>"",B34,"") | CC35: =IF($CC$11<>"",B34,"") | CD35: =IF($CD$11<>"",B34,"") | CE35: =IF($CE$11<>"",B34,"") | CF35: =IF($CF$11<>"",B34,"") | CG35: =IF($CG$11<>"",B34,"") | CH35: =IF($CH$11<>"",B34,"") | CI35: =IF($CI$11<>"",B34,"") | CJ35: =IF($CJ$11<>"",B34,"") | CK35: =IF($CK$11<>"",B34,"") | CL35: =IF($CL$11<>"",B34,"") | CM35: =IF($CM$11<>"",B34,"") | CN35: =IF($CN$11<>"",B34,"") | CO35: =IF($CO$11<>"",B34,"") | CP35: =IF($CP$11<>"",B34,"") | CQ35: =IF($CQ$11<>"",B34,"") | CR35: =IF($CR$11<>"",B34,"") | CS35: =IF(CS34<>"",$B34,"") | CT35: =IF($CT$11<>"",B34,"") | CU35: =IF($CU$11<>"",B34,"") | CV35: =IF($CV$11<>"",B34,"") | CW35: =IF($CW$11<>"",B34,"") | CX35: =IF($CX$11<>"",B34,"") | CY35: =IF($CY$11<>"",B34,"") | CZ35: =IF($CZ$11<>"",B34,"") | DA35: =IF($DA$11<>"",B34,"") | DB35: =IF($DB$11<>"",B34,"") | DC35: =IF($DC$11<>"",B34,"") | DD35: =IF($DD$11<>"",B34,"") | DE35: =IF($DE$11<>"",B34,"") | DF35: =IF($DF$11<>"",B34,"") | DG35: =IF($DG$11<>"",B34,"") | DH35: =IF($DH$11<>"",B34,"") | DI35: =IF($DI$11<>"",B34,"") | DJ35: =IF($DJ$11<>"",B34,"") | DK35: =IF($DK$11<>"",$B34,"") | DL35: =IF($DL$11<>"",$B34,"") | DM35: =IF($DM$11<>"",$B34,"") | DN35: =IF($DN$11<>"",$B34,"") | DO35: =IF($DO$11<>"",$B34,"") | DP35: =IF($DP$11<>"",$B34,"") | DQ35: =IF($DQ$11<>"",$B34,"") | DR35: =IF($DR$11<>"",$B34,"") | DS35: =IF($DS$11<>"",$B34,"") | DT35: =IF($DT$11<>"",$B34,"") | DU35: =IF($DU$11<>"",$B34,"") | DV35: =IF($DV$11<>"",$B34,"") | DY35: BERMUDA TERMICA MASCULINO | DZ35: SP | EA35: ADALTRO SEBASTIAO | EB35: AMARELO ESCURO | EC35: ALL 4T
A36: =IF(PEDIDO!C61<>"",PEDIDO!B61,"") | B36: =IF(PEDIDO!X61<>"",PEDIDO!X61,"") | C36: =IF(PEDIDO!AA61<>"",PEDIDO!AA61,"") | D36: =IF(PEDIDO!AD61<>"",PEDIDO!AD61,"") | E36: =IF(PEDIDO!AG61<>"",PEDIDO!AG61,"") | F36: =IF(PEDIDO!AJ61<>"",PEDIDO!AJ61,"") | J36: =IF(PEDIDO!C60<>"",PEDIDO!B60,"") | K36: =IF($K$11<>"",B35,"") | L36: =IF($L$11<>"",B35,"") | M36: =IF($M$11<>"",B35,"") | N36: =IF($N$11<>"",B35,"") | O36: =IF($O$11<>"",B35,"") | P36: =IF($P$11<>"",B35,"") | Q36: =IF($Q$11<>"",B35,"") | R36: =IF($R$11<>"",B35,"") | S36: =IF($S$11<>"",B35,"") | T36: =IF($T$11<>"",B35,"") | U36: =IF($U$11<>"",B35,"") | V36: =IF($V$11<>"",B35,"") | X36: =IF($X$11<>"",B35,"") | Y36: =IF($Y$11<>"",B35,"") | Z36: =IF($Z$11<>"",B35,"") | AA36: =IF($AA$11<>"",B35,"") | AB36: =IF($AB$11<>"",B35,"") | AC36: =IF($AC$11<>"",B35,"") | AD36: =IF($AD$11<>"",B35,"") | AE36: =IF($AE$11<>"",B35,"") | AF36: =IF($AF$11<>"",B35,"") | AG36: =IF($AG$11<>"",B35,"") | AH36: =IF($AH$11<>"",B35,"") | AI36: =IF($AI$11<>"",B35,"") | AJ36: =IF($AJ$11<>"",B35,"") | AK36: =IF($AK$11<>"",B35,"") | AL36: =IF($AL$11<>"",B35,"") | AM36: =IF($AM$11<>"",B35,"") | AN36: =IF($AN$11<>"",B35,"") | AO36: =IF($AO$11<>"",B35,"") | AP36: =IF($AP$11<>"",B35,"") | AQ36: =IF($AQ$11<>"",B35,"") | AR36: =IF($AR$11<>"",B35,"") | AS36: =IF($AS$11<>"",B35,"") | AT36: =IF($AT$11<>"",B35,"") | AU36: =IF($AU$11<>"",B35,"") | AV36: =IF($AV$11<>"",B35,"") | AW36: =IF($AW$11<>"",B35,"") | AX36: =IF($AX$11<>"",B35,"") | AY36: =IF($AY$11<>"",B35,"") | AZ36: =IF($AZ$11<>"",B35,"") | BA36: =IF($BA$11<>"",B35,"") | BB36: =IF($BB$11<>"",B35,"") | BC36: =IF($BC$11<>"",B35,"") | BD36: =IF($BD$11<>"",B35,"") | BE36: =IF($BE$11<>"",B35,"") | BF36: =IF($BF$11<>"",B35,"") | BG36: =IF($BG$11<>"",B35,"") | BH36: =IF($BH$11<>"",B35,"") | BI36: =IF($BI$11<>"",B35,"") | BJ36: =IF($BJ$11<>"",B35,"") | BK36: =IF($BK$11<>"",B35,"") | BL36: =IF($BL$11<>"",B35,"") | BM36: =IF($BM$11<>"",B35,"") | BN36: =IF($BN$11<>"",B35,"") | BO36: =IF($BO$11<>"",B35,"") | BP36: =IF($BP$11<>"",B35,"") | BQ36: =IF($BQ$11<>"",B35,"") | BR36: =IF($BR$11<>"",B35,"") | BS36: =IF($BS$11<>"",B35,"") | BT36: =IF($BT$11<>"",B35,"") | BU36: =IF($BU$11<>"",B35,"") | BV36: =IF($BV$11<>"",B35,"") | BW36: =IF($BW$11<>"",B35,"") | BX36: =IF($BX$11<>"",B35,"") | BY36: =IF($BY$11<>"",B35,"") | BZ36: =IF($BZ$11<>"",B35,"") | CA36: =IF($CA$11<>"",B35,"") | CB36: =IF($CB$11<>"",B35,"") | CC36: =IF($CC$11<>"",B35,"") | CD36: =IF($CD$11<>"",B35,"") | CE36: =IF($CE$11<>"",B35,"") | CF36: =IF($CF$11<>"",B35,"") | CG36: =IF($CG$11<>"",B35,"") | CH36: =IF($CH$11<>"",B35,"") | CI36: =IF($CI$11<>"",B35,"") | CJ36: =IF($CJ$11<>"",B35,"") | CK36: =IF($CK$11<>"",B35,"") | CL36: =IF($CL$11<>"",B35,"") | CM36: =IF($CM$11<>"",B35,"") | CN36: =IF($CN$11<>"",B35,"") | CO36: =IF($CO$11<>"",B35,"") | CP36: =IF($CP$11<>"",B35,"") | CQ36: =IF($CQ$11<>"",B35,"") | CR36: =IF($CR$11<>"",B35,"") | CS36: =IF(CS35<>"",$B35,"") | CT36: =IF($CT$11<>"",B35,"") | CU36: =IF($CU$11<>"",B35,"") | CV36: =IF($CV$11<>"",B35,"") | CW36: =IF($CW$11<>"",B35,"") | CX36: =IF($CX$11<>"",B35,"") | CY36: =IF($CY$11<>"",B35,"") | CZ36: =IF($CZ$11<>"",B35,"") | DA36: =IF($DA$11<>"",B35,"") | DB36: =IF($DB$11<>"",B35,"") | DC36: =IF($DC$11<>"",B35,"") | DD36: =IF($DD$11<>"",B35,"") | DE36: =IF($DE$11<>"",B35,"") | DF36: =IF($DF$11<>"",B35,"") | DG36: =IF($DG$11<>"",B35,"") | DH36: =IF($DH$11<>"",B35,"") | DI36: =IF($DI$11<>"",B35,"") | DJ36: =IF($DJ$11<>"",B35,"") | DK36: =IF($DK$11<>"",$B35,"") | DL36: =IF($DL$11<>"",$B35,"") | DM36: =IF($DM$11<>"",$B35,"") | DN36: =IF($DN$11<>"",$B35,"") | DO36: =IF($DO$11<>"",$B35,"") | DP36: =IF($DP$11<>"",$B35,"") | DQ36: =IF($DQ$11<>"",$B35,"") | DR36: =IF($DR$11<>"",$B35,"") | DS36: =IF($DS$11<>"",$B35,"") | DT36: =IF($DT$11<>"",$B35,"") | DU36: =IF($DU$11<>"",$B35,"") | DV36: =IF($DV$11<>"",$B35,"") | DY36: BERMUDAO | DZ36: ENIGMA | EA36: ADD | EB36: AMARELO FLOUR | EC36: ALMERIA
... A140: =IF(PEDIDO!C165<>"",PEDIDO!B165,"") | B140: =IF(PEDIDO!X165<>"",PEDIDO!X165,"") | C140: =IF(PEDIDO!AA165<>"",PEDIDO!AA165,"") | D140: =IF(PEDIDO!AD165<>"",PEDIDO!AD165,"") | E140: =IF(PEDIDO!AG165<>"",PEDIDO!AG165,"") | F140: =IF(PEDIDO!AJ165<>"",PEDIDO!AJ165,"") | J140: =IF(PEDIDO!C164<>"",PEDIDO!B164,"") | K140: =IF($K$11<>"",B139,"") | L140: =IF($L$11<>"",B139,"") | M140: =IF($M$11<>"",B139,"") | N140: =IF($N$11<>"",B139,"") | O140: =IF($O$11<>"",B139,"") | P140: =IF($P$11<>"",B139,"") | Q140: =IF($Q$11<>"",B139,"") | R140: =IF($R$11<>"",B139,"") | S140: =IF($S$11<>"",B139,"") | T140: =IF($T$11<>"",B139,"") | U140: =IF($U$11<>"",B139,"") | V140: =IF($V$11<>"",B139,"") | X140: =IF($X$11<>"",B139,"") | Y140: =IF($Y$11<>"",B139,"") | Z140: =IF($Z$11<>"",B139,"") | AA140: =IF($AA$11<>"",B139,"") | AB140: =IF($AB$11<>"",B139,"") | AC140: =IF($AC$11<>"",B139,"") | AD140: =IF($AD$11<>"",B139,"") | AE140: =IF($AE$11<>"",B139,"") | AF140: =IF($AF$11<>"",B139,"") | AG140: =IF($AG$11<>"",B139,"") | AH140: =IF($AH$11<>"",B139,"") | AI140: =IF($AI$11<>"",B139,"") | AJ140: =IF($AJ$11<>"",B139,"") | AK140: =IF($AK$11<>"",B139,"") | AL140: =IF($AL$11<>"",B139,"") | AM140: =IF($AM$11<>"",B139,"") | AN140: =IF($AN$11<>"",B139,"") | AO140: =IF($AO$11<>"",B139,"") | AP140: =IF($AP$11<>"",B139,"") | AQ140: =IF($AQ$11<>"",B139,"") | AR140: =IF($AR$11<>"",B139,"") | AS140: =IF($AS$11<>"",B139,"") | AT140: =IF($AT$11<>"",B139,"") | AU140: =IF($AU$11<>"",B139,"") | AV140: =IF($AV$11<>"",B139,"") | AW140: =IF($AW$11<>"",B139,"") | AX140: =IF($AX$11<>"",B139,"") | AY140: =IF($AY$11<>"",B139,"") | AZ140: =IF($AZ$11<>"",B139,"") | BA140: =IF($BA$11<>"",B139,"") | BB140: =IF($BB$11<>"",B139,"") | BC140: =IF($BC$11<>"",B139,"") | BD140: =IF($BD$11<>"",B139,"") | BE140: =IF($BE$11<>"",B139,"") | BF140: =IF($BF$11<>"",B139,"") | BG140: =IF($BG$11<>"",B139,"") | BH140: =IF($BH$11<>"",B139,"") | BI140: =IF($BI$11<>"",B139,"") | BJ140: =IF($BJ$11<>"",B139,"") | BK140: =IF($BK$11<>"",B139,"") | BL140: =IF($BL$11<>"",B139,"") | BM140: =IF($BM$11<>"",B139,"") | BN140: =IF($BN$11<>"",B139,"") | BO140: =IF($BO$11<>"",B139,"") | BP140: =IF($BP$11<>"",B139,"") | BQ140: =IF($BQ$11<>"",B139,"") | BR140: =IF($BR$11<>"",B139,"") | BS140: =IF($BS$11<>"",B139,"") | BT140: =IF($BT$11<>"",B139,"") | BU140: =IF($BU$11<>"",B139,"") | BV140: =IF($BV$11<>"",B139,"") | BW140: =IF($BW$11<>"",B139,"") | BX140: =IF($BX$11<>"",B139,"") | BY140: =IF($BY$11<>"",B139,"") | BZ140: =IF($BZ$11<>"",B139,"") | CA140: =IF($CA$11<>"",B139,"") | CB140: =IF($CB$11<>"",B139,"") | CC140: =IF($CC$11<>"",B139,"") | CD140: =IF($CD$11<>"",B139,"") | CE140: =IF($CE$11<>"",B139,"") | CF140: =IF($CF$11<>"",B139,"") | CG140: =IF($CG$11<>"",B139,"") | CH140: =IF($CH$11<>"",B139,"") | CI140: =IF($CI$11<>"",B139,"") | CJ140: =IF($CJ$11<>"",B139,"") | CK140: =IF($CK$11<>"",B139,"") | CL140: =IF($CL$11<>"",B139,"") | CM140: =IF($CM$11<>"",B139,"") | CN140: =IF($CN$11<>"",B139,"") | CO140: =IF($CO$11<>"",B139,"") | CP140: =IF($CP$11<>"",B139,"") | CQ140: =IF($CQ$11<>"",B139,"") | CR140: =IF($CR$11<>"",B139,"") | CS140: =IF(CS139<>"",$B139,"") | CT140: =IF($CT$11<>"",B139,"") | CU140: =IF($CU$11<>"",B139,"") | CV140: =IF($CV$11<>"",B139,"") | CW140: =IF($CW$11<>"",B139,"") | CX140: =IF($CX$11<>"",B139,"") | CY140: =IF($CY$11<>"",B139,"") | CZ140: =IF($CZ$11<>"",B139,"") | DA140: =IF($DA$11<>"",B139,"") | DB140: =IF($DB$11<>"",B139,"") | DC140: =IF($DC$11<>"",B139,"") | DD140: =IF($DD$11<>"",B139,"") | DE140: =IF($DE$11<>"",B139,"") | DF140: =IF($DF$11<>"",B139,"") | DG140: =IF($DG$11<>"",B139,"") | DH140: =IF($DH$11<>"",B139,"") | DI140: =IF($DI$11<>"",B139,"") | DJ140: =IF($DJ$11<>"",B139,"") | DK140: =IF($DK$11<>"",$B139,"") | DL140: =IF($DL$11<>"",$B139,"") | DM140: =IF($DM$11<>"",$B139,"") | DN140: =IF($DN$11<>"",$B139,"") | DO140: =IF($DO$11<>"",$B139,"") | DP140: =IF($DP$11<>"",$B139,"") | DQ140: =IF($DQ$11<>"",$B139,"") | DR140: =IF($DR$11<>"",$B139,"") | DS140: =IF($DS$11<>"",$B139,"") | DT140: =IF($DT$11<>"",$B139,"") | DU140: =IF($DU$11<>"",$B139,"") | DV140: =IF($DV$11<>"",$B139,"") | DY140: CAMISA MASCULINO | DZ140: SATÉLITE TECNOLOGIA E SEGURANÇA | EA140: AMERICA OXDDI | EB140: AZUL POLAR | EC140: BOLD PLUS
A141: =IF(PEDIDO!C402<>"",PEDIDO!B402,"") | B141: =IF(PEDIDO!X402<>"",PEDIDO!X402,"") | C141: =IF(PEDIDO!AA402<>"",PEDIDO!AA402,"") | D141: =IF(PEDIDO!AD402<>"",PEDIDO!AD402,"") | E141: =IF(PEDIDO!AG402<>"",PEDIDO!AG402,"") | F141: =IF(PEDIDO!AJ402<>"",PEDIDO!AJ402,"") | J141: =IF(PEDIDO!C401<>"",PEDIDO!B401,"") | K141: =IF($K$11<>"",#REF!,"") | L141: =IF($L$11<>"",#REF!,"") | M141: =IF($M$11<>"",#REF!,"") | N141: =IF($N$11<>"",#REF!,"") | O141: =IF($O$11<>"",#REF!,"") | P141: =IF($P$11<>"",#REF!,"") | Q141: =IF($Q$11<>"",#REF!,"") | R141: =IF($R$11<>"",#REF!,"") | S141: =IF($S$11<>"",#REF!,"") | T141: =IF($T$11<>"",#REF!,"") | U141: =IF($U$11<>"",#REF!,"") | V141: =IF($V$11<>"",#REF!,"") | X141: =IF($X$11<>"",#REF!,"") | Y141: =IF($Y$11<>"",#REF!,"") | Z141: =IF($Z$11<>"",#REF!,"") | AA141: =IF($AA$11<>"",#REF!,"") | AB141: =IF($AB$11<>"",#REF!,"") | AC141: =IF($AC$11<>"",#REF!,"") | AD141: =IF($AD$11<>"",#REF!,"") | AE141: =IF($AE$11<>"",#REF!,"") | AF141: =IF($AF$11<>"",#REF!,"") | AG141: =IF($AG$11<>"",#REF!,"") | AH141: =IF($AH$11<>"",#REF!,"") | AI141: =IF($AI$11<>"",#REF!,"") | AJ141: =IF($AJ$11<>"",#REF!,"") | AK141: =IF($AK$11<>"",#REF!,"") | AL141: =IF($AL$11<>"",#REF!,"") | AM141: =IF($AM$11<>"",#REF!,"") | AN141: =IF($AN$11<>"",#REF!,"") | AO141: =IF($AO$11<>"",#REF!,"") | AP141: =IF($AP$11<>"",#REF!,"") | AQ141: =IF($AQ$11<>"",#REF!,"") | AR141: =IF($AR$11<>"",#REF!,"") | AS141: =IF($AS$11<>"",#REF!,"") | AT141: =IF($AT$11<>"",#REF!,"") | AU141: =IF($AU$11<>"",#REF!,"") | AV141: =IF($AV$11<>"",#REF!,"") | AW141: =IF($AW$11<>"",#REF!,"") | AX141: =IF($AX$11<>"",#REF!,"") | AY141: =IF($AY$11<>"",#REF!,"") | AZ141: =IF($AZ$11<>"",#REF!,"") | BA141: =IF($BA$11<>"",#REF!,"") | BB141: =IF($BB$11<>"",#REF!,"") | BC141: =IF($BC$11<>"",#REF!,"") | BD141: =IF($BD$11<>"",#REF!,"") | BE141: =IF($BE$11<>"",#REF!,"") | BF141: =IF($BF$11<>"",#REF!,"") | BG141: =IF($BG$11<>"",#REF!,"") | BH141: =IF($BH$11<>"",#REF!,"") | BI141: =IF($BI$11<>"",#REF!,"") | BJ141: =IF($BJ$11<>"",#REF!,"") | BK141: =IF($BK$11<>"",#REF!,"") | BL141: =IF($BL$11<>"",#REF!,"") | BM141: =IF($BM$11<>"",#REF!,"") | BN141: =IF($BN$11<>"",#REF!,"") | BO141: =IF($BO$11<>"",#REF!,"") | BP141: =IF($BP$11<>"",#REF!,"") | BQ141: =IF($BQ$11<>"",#REF!,"") | BR141: =IF($BR$11<>"",#REF!,"") | BS141: =IF($BS$11<>"",#REF!,"") | BT141: =IF($BT$11<>"",#REF!,"") | BU141: =IF($BU$11<>"",#REF!,"") | BV141: =IF($BV$11<>"",#REF!,"") | BW141: =IF($BW$11<>"",#REF!,"") | BX141: =IF($BX$11<>"",#REF!,"") | BY141: =IF($BY$11<>"",#REF!,"") | BZ141: =IF($BZ$11<>"",#REF!,"") | CA141: =IF($CA$11<>"",#REF!,"") | CB141: =IF($CB$11<>"",#REF!,"") | CC141: =IF($CC$11<>"",#REF!,"") | CD141: =IF($CD$11<>"",#REF!,"") | CE141: =IF($CE$11<>"",#REF!,"") | CF141: =IF($CF$11<>"",#REF!,"") | CG141: =IF($CG$11<>"",#REF!,"") | CH141: =IF($CH$11<>"",#REF!,"") | CI141: =IF($CI$11<>"",#REF!,"") | CJ141: =IF($CJ$11<>"",#REF!,"") | CK141: =IF($CK$11<>"",#REF!,"") | CL141: =IF($CL$11<>"",#REF!,"") | CM141: =IF($CM$11<>"",#REF!,"") | CN141: =IF($CN$11<>"",#REF!,"") | CO141: =IF($CO$11<>"",#REF!,"") | CP141: =IF($CP$11<>"",#REF!,"") | CQ141: =IF($CQ$11<>"",#REF!,"") | CT141: =IF($CT$11<>"",B140,"") | CU141: =IF($CU$11<>"",#REF!,"") | CV141: =IF($CV$11<>"",#REF!,"") | CW141: =IF($CW$11<>"",#REF!,"") | CX141: =IF($CX$11<>"",#REF!,"") | CY141: =IF($CY$11<>"",#REF!,"") | CZ141: =IF($CZ$11<>"",#REF!,"") | DA141: =IF($DA$11<>"",#REF!,"") | DB141: =IF($DB$11<>"",#REF!,"") | DC141: =IF($DC$11<>"",#REF!,"") | DD141: =IF($DD$11<>"",#REF!,"") | DE141: =IF($DE$11<>"",#REF!,"") | DF141: =IF($DF$11<>"",#REF!,"") | DG141: =IF($DG$11<>"",#REF!,"") | DH141: =IF($DH$11<>"",#REF!,"") | DI141: =IF($DI$11<>"",#REF!,"") | DJ141: =IF($DJ$11<>"",#REF!,"") | DY141: CAMISA SOCIAL | DZ141: VIVO | EA141: AMICIA | EB141: AZUL RETRO | EC141: BOLEIRO V
A142: =IF(PEDIDO!C403<>"",PEDIDO!B403,"") | B142: =IF(PEDIDO!X403<>"",PEDIDO!X403,"") | C142: =IF(PEDIDO!AA403<>"",PEDIDO!AA403,"") | D142: =IF(PEDIDO!AD403<>"",PEDIDO!AD403,"") | E142: =IF(PEDIDO!AG403<>"",PEDIDO!AG403,"") | F142: =IF(PEDIDO!AJ403<>"",PEDIDO!AJ403,"") | J142: Lojas | K142: 1 | L142: 2 | M142: 3 | N142: 4 | O142: 5 | P142: 6 | Q142: 7 | R142: 8 | S142: 9 | T142: 10 | U142: 11 | V142: 12 | W142: 13 | X142: 14 | Y142: 15 | Z142: 19 | AA142: 20 | AB142: 21 | AC142: 22 | AD142: 23 | AE142: 24 | AF142: 25 | AG142: 26 | AH142: 27 | AI142: 28 | AJ142: 29 | AK142: 30 | AL142: 31 | AM142: 32 | AN142: 33 | AO142: 34 | AP142: 35 | AQ142: 36 | AR142: 37 | AS142: 38 | AT142: 39 | AU142: 40 | AV142: 41 | AW142: 42 | AX142: 43 | AY142: 44 | AZ142: 45 | BA142: 46 | BB142: 47 | BC142: 48 | BD142: 49 | BE142: 50 | BF142: 51 | BG142: 52 | BH142: 53 | BI142: 54 | BJ142: 56 | BK142: 57 | BL142: 58 | BM142: 59 | BN142: 60 | BO142: 61 | BP142: 62 | BQ142: 63 | BR142: 64 | BS142: 65 | BT142: 66 | BU142: 67 | BV142: 68 | BW142: 69 | BX142: 70 | BY142: 72 | BZ142: 73 | CA142: 74 | CB142: 75 | CC142: 76 | CD142: 77 | CE142: 78 | CF142: 79 | CG142: 80 | CH142: 81 | CI142: 82 | CJ142: 83 | CK142: 84 | CL142: 85 | CM142: 86 | CN142: 87 | CO142: 88 | CP142: 89 | CQ142: 90 | CR142: 91 | CS142: 92 | CT142: 93 | CU142: 94 | CV142: 95 | CW142: 96 | CX142: 97 | CY142: 98 | CZ142: 99 | DA142: 100 | DB142: 101 | DC142: 102 | DD142: 103 | DE142: 104 | DF142: 105 | DG142: 106 | DH142: 107 | DI142: 108 | DJ142: 999 | DK142: 109 | DL142: 110 | DM142: 111 | DN142: 112 | DO142: 113 | DP142: 114 | DQ142: 115 | DR142: 116 | DS142: 117 | DT142: 118 | DU142: 119 | DV142: 120 | DY142: CAMISA TERMICA | DZ142: MITTY | EA142: AMIL | EB142: AZUL ROYAL | EC142: BOLEIRO V FUTSAL
A143: =IF(PEDIDO!C404<>"",PEDIDO!B404,"") | B143: =IF(PEDIDO!X404<>"",PEDIDO!X404,"") | C143: =IF(PEDIDO!AA404<>"",PEDIDO!AA404,"") | D143: =IF(PEDIDO!AD404<>"",PEDIDO!AD404,"") | E143: =IF(PEDIDO!AG404<>"",PEDIDO!AG404,"") | F143: =IF(PEDIDO!AJ404<>"",PEDIDO!AJ404,"") | J143: Pedido 2 | K143: =IF(COUNTIF(PEDIDO!$D$24:$AO$24, K$10)>0, K$10, "") | L143: =IF(COUNTIF(PEDIDO!$D$24:$AO$24, L$10)>0, L$10, "") | M143: =IF(COUNTIF(PEDIDO!$D$24:$AO$24, M$10)>0, M$10, "") | N143: =IF(COUNTIF(PEDIDO!$D$24:$AO$24, N$10)>0, N$10, "") | O143: =IF(COUNTIF(PEDIDO!$D$24:$AO$24, O$10)>0, O$10, "") | P143: =IF(COUNTIF(PEDIDO!$D$24:$AO$24, P$10)>0, P$10, "") | Q143: =IF(COUNTIF(PEDIDO!$D$24:$AO$24, Q$10)>0, Q$10, "") | R143: =IF(COUNTIF(PEDIDO!$D$24:$AO$24, R$10)>0, R$10, "") | ... DV143: =IF(COUNTIF(PEDIDO!$D$24:$AO$24, DV$10)>0, DV$10, "") | DY143: CAMISA TERMICA INFANTIL | DZ143: PLACAS DE SINALIZAÇÃO | EA143: AMISKA | EB143: AZUL SPORT | EC143: BOLEIRO VI
A144: =IF(PEDIDO!C405<>"",PEDIDO!B405,"") | B144: =IF(PEDIDO!X405<>"",PEDIDO!X405,"") | C144: =IF(PEDIDO!AA405<>"",PEDIDO!AA405,"") | D144: =IF(PEDIDO!AD405<>"",PEDIDO!AD405,"") | E144: =IF(PEDIDO!AG405<>"",PEDIDO!AG405,"") | F144: =IF(PEDIDO!AJ405<>"",PEDIDO!AJ405,"") | J144: =IF(PEDIDO!C36<>"",PEDIDO!B36,"") | K144: =IF($K$143<>"",C11,"") | L144: =IF($L$143<>"",C11,"") | M144: =IF($M$143<>"",C11,"") | N144: =IF($N$143<>"",C11,"") | O144: =IF($O$143<>"",C11,"") | P144: =IF($P$143<>"",C11,"") | Q144: =IF($Q$143<>"",C11,"") | R144: =IF($R$143<>"",C11,"") | S144: =IF($S$143<>"",C11,"") | T144: =IF($T$143<>"",C11,"") | U144: =IF($U$143<>"",C11,"") | V144: =IF($V$143<>"",C11,"") | W144: =IF($W$143<>"",C11,"") | X144: =IF($X$143<>"",C11,"") | Y144: =IF($Y$143<>"",C11,"") | Z144: =IF($Z$143<>"",C11,"") | AA144: =IF($AA$143<>"",C11,"") | AB144: =IF($AB$143<>"",C11,"") | AC144: =IF($AC$143<>"",C11,"") | AD144: =IF($AD$143<>"",C11,"") | AE144: =IF($AE$143<>"",C11,"") | AF144: =IF($AF$143<>"",C11,"") | AG144: =IF($AG$143<>"",C11,"") | AH144: =IF($AH$143<>"",C11,"") | AI144: =IF($AI$143<>"",C11,"") | AJ144: =IF($AJ$143<>"",C11,"") | AK144: =IF($AK$143<>"",C11,"") | AL144: =IF($AL$143<>"",C11,"") | AM144: =IF($AM$143<>"",C11,"") | AN144: =IF($AN$143<>"",C11,"") | AO144: =IF($AO$143<>"",C11,"") | AP144: =IF($AP$143<>"",C11,"") | AQ144: =IF($AQ$143<>"",C11,"") | AR144: =IF($AR$143<>"",C11,"") | AS144: =IF($AS$143<>"",C11,"") | AT144: =IF($AT$143<>"",C11,"") | AU144: =IF($AU$143<>"",C11,"") | AV144: =IF($AV$143<>"",C11,"") | AW144: =IF($AW$143<>"",C11,"") | AX144: =IF($AX$143<>"",C11,"") | AY144: =IF($AY$143<>"",C11,"") | AZ144: =IF($AZ$143<>"",C11,"") | BA144: =IF(BA143<>"",$C$11,"") | BB144: =IF($BB$143<>"",C11,"") | BC144: =IF($BC$143<>"",C11,"") | BD144: =IF($BD$143<>"",C11,"") | BE144: =IF($BE$143<>"",C11,"") | BF144: =IF($BF$143<>"",C11,"") | BG144: =IF($BG$143<>"",C11,"") | BH144: =IF($BH$143<>"",C11,"") | BI144: =IF($BI$143<>"",C11,"") | BJ144: =IF($BJ$143<>"",C11,"") | BK144: =IF($BK$143<>"",C11,"") | BL144: =IF($BL$143<>"",C11,"") | BM144: =IF($BM$143<>"",C11,"") | BN144: =IF($BN$143<>"",C11,"") | BO144: =IF($BO$143<>"",C11,"") | BP144: =IF($BP$143<>"",C11,"") | BQ144: =IF($BQ$143<>"",C11,"") | BR144: =IF($BR$143<>"",C11,"") | BS144: =IF($BS$143<>"",C11,"") | BT144: =IF($BT$143<>"",C11,"") | BU144: =IF($BU$143<>"",C11,"") | BV144: =IF($BV$143<>"",C11,"") | BW144: =IF($BW$143<>"",C11,"") | BX144: =IF($BX$143<>"",C11,"") | BY144: =IF($BY$143<>"",C11,"") | BZ144: =IF($BZ$143<>"",C11,"") | CA144: =IF($CA$143<>"",C11,"") | CB144: =IF($CB$143<>"",C11,"") | CC144: =IF($CC$143<>"",C11,"") | CD144: =IF($CD$143<>"",C11,"") | CE144: =IF($CE$143<>"",C11,"") | CF144: =IF($CF$143<>"",C11,"") | CG144: =IF($CG$143<>"",C11,"") | CH144: =IF($CH$143<>"",C11,"") | CI144: =IF($CI$143<>"",C11,"") | CJ144: =IF($CJ$143<>"",C11,"") | CK144: =IF($CK$143<>"",C11,"") | CL144: =IF($CL$143<>"",C11,"") | CM144: =IF($CM$143<>"",C11,"") | CN144: =IF($CN$143<>"",C11,"") | CO144: =IF($CO$143<>"",C11,"") | CP144: =IF($CP$143<>"",C11,"") | CQ144: =IF($CQ$143<>"",C11,"") | CR144: =IF($CR$143<>"",C11,"") | CS144: =IF(CS143<>"",B$16,"") | CT144: =IF($CT$143<>"",C11,"") | CU144: =IF($CU$143<>"",C11,"") | CV144: =IF($CV$143<>"",C11,"") | CW144: =IF($CW$143<>"",C11,"") | CX144: =IF($CX$143<>"",C11,"") | CY144: =IF($CY$143<>"",C11,"") | CZ144: =IF($CZ$143<>"",C11,"") | DA144: =IF($DA$143<>"",C11,"") | DB144: =IF($DB$143<>"",C11,"") | DC144: =IF($DC$143<>"",C11,"") | DD144: =IF($DD$143<>"",C11,"") | DE144: =IF($DE$143<>"",C11,"") | DF144: =IF($DF$143<>"",C11,"") | DG144: =IF($DG$143<>"",C11,"") | DH144: =IF($DH$143<>"",C11,"") | DI144: =IF($DI$143<>"",C11,"") | DJ144: =IF($DJ$143<>"",C11,"") | DK144: =IF($DK$143<>"",$C11,"") | DL144: =IF($DL$143<>"",$C11,"") | DM144: =IF($DM$143<>"",$C11,"") | DN144: =IF($DN$143<>"",$C11,"") | DO144: =IF($DO$143<>"",$C11,"") | DP144: =IF($DP$143<>"",$C11,"") | DQ144: =IF($DQ$143<>"",$C11,"") | DR144: =IF($DR$143<>"",$C11,"") | DS144: =IF($DS$143<>"",$C11,"") | DT144: =IF($DT$143<>"",$C11,"") | DU144: =IF($DU$143<>"",$C11,"") | DV144: =IF($DV$143<>"",$C11,"") | DY144: CAMISA TERMICA INFANTIL MASCULINO | DZ144: LUMINARIAS DE EMERGENCIA | EA144: AMOFANY | EB144: AZUL STONE | EC144: BOLO FOFOS
A145: =IF(PEDIDO!C406<>"",PEDIDO!B406,"") | B145: =IF(PEDIDO!X406<>"",PEDIDO!X406,"") | C145: =IF(PEDIDO!AA406<>"",PEDIDO!AA406,"") | D145: =IF(PEDIDO!AD406<>"",PEDIDO!AD406,"") | E145: =IF(PEDIDO!AG406<>"",PEDIDO!AG406,"") | F145: =IF(PEDIDO!AJ406<>"",PEDIDO!AJ406,"") | J145: =IF(PEDIDO!C37<>"",PEDIDO!B37,"") | K145: =IF($K$143<>"",C12,"") | L145: =IF($L$143<>"",C12,"") | M145: =IF($M$143<>"",C12,"") | N145: =IF($N$143<>"",C12,"") | O145: =IF($O$143<>"",C12,"") | P145: =IF($P$143<>"",C12,"") | Q145: =IF($Q$143<>"",C12,"") | R145: =IF($R$143<>"",C12,"") | S145: =IF($S$143<>"",C12,"") | T145: =IF($T$143<>"",C12,"") | U145: =IF($U$143<>"",C12,"") | V145: =IF($V$143<>"",C12,"") | W145: =IF($W$143<>"",C12,"") | X145: =IF($X$143<>"",C12,"") | Y145: =IF($Y$143<>"",C12,"") | Z145: =IF($Z$143<>"",C12,"") | AA145: =IF($AA$143<>"",C12,"") | AB145: =IF($AB$143<>"",C12,"") | AC145: =IF($AC$143<>"",C12,"") | AD145: =IF($AD$143<>"",C12,"") | AE145: =IF($AE$143<>"",C12,"") | AF145: =IF($AF$143<>"",C12,"") | AG145: =IF($AG$143<>"",C12,"") | AH145: =IF($AH$143<>"",C12,"") | AI145: =IF($AI$143<>"",C12,"") | AJ145: =IF($AJ$143<>"",C12,"") | AK145: =IF($AK$143<>"",C12,"") | AL145: =IF($AL$143<>"",C12,"") | AM145: =IF($AM$143<>"",C12,"") | AN145: =IF($AN$143<>"",C12,"") | AO145: =IF($AO$143<>"",C12,"") | AP145: =IF($AP$143<>"",C12,"") | AQ145: =IF($AQ$143<>"",C12,"") | AR145: =IF($AR$143<>"",C12,"") | AS145: =IF($AS$143<>"",C12,"") | AT145: =IF($AT$143<>"",C12,"") | AU145: =IF($AU$143<>"",C12,"") | AV145: =IF($AV$143<>"",C12,"") | AW145: =IF($AW$143<>"",C12,"") | AX145: =IF($AX$143<>"",C12,"") | AY145: =IF($AY$143<>"",C12,"") | AZ145: =IF($AZ$143<>"",C12,"") | BA145: =IF(BA144<>"",$C$11,"") | BB145: =IF($BB$143<>"",C12,"") | BC145: =IF($BC$143<>"",C12,"") | BD145: =IF($BD$143<>"",C12,"") | BE145: =IF($BE$143<>"",C12,"") | BF145: =IF($BF$143<>"",C12,"") | BG145: =IF($BG$143<>"",C12,"") | BH145: =IF($BH$143<>"",C12,"") | BI145: =IF($BI$143<>"",C12,"") | BJ145: =IF($BJ$143<>"",C12,"") | BK145: =IF($BK$143<>"",C12,"") | BL145: =IF($BL$143<>"",C12,"") | BM145: =IF($BM$143<>"",C12,"") | BN145: =IF($BN$143<>"",C12,"") | BO145: =IF($BO$143<>"",C12,"") | BP145: =IF($BP$143<>"",C12,"") | BQ145: =IF($BQ$143<>"",C12,"") | BR145: =IF($BR$143<>"",C12,"") | BS145: =IF($BS$143<>"",C12,"") | BT145: =IF($BT$143<>"",C12,"") | BU145: =IF($BU$143<>"",C12,"") | BV145: =IF($BV$143<>"",C12,"") | BW145: =IF($BW$143<>"",C12,"") | BX145: =IF($BX$143<>"",C12,"") | BY145: =IF($BY$143<>"",C12,"") | BZ145: =IF($BZ$143<>"",C12,"") | CA145: =IF($CA$143<>"",C12,"") | CB145: =IF($CB$143<>"",C12,"") | CC145: =IF($CC$143<>"",C12,"") | CD145: =IF($CD$143<>"",C12,"") | CE145: =IF($CE$143<>"",C12,"") | CF145: =IF($CF$143<>"",C12,"") | CG145: =IF($CG$143<>"",C12,"") | CH145: =IF($CH$143<>"",C12,"") | CI145: =IF($CI$143<>"",C12,"") | CJ145: =IF($CJ$143<>"",C12,"") | CK145: =IF($CK$143<>"",C12,"") | CL145: =IF($CL$143<>"",C12,"") | CM145: =IF($CM$143<>"",C12,"") | CN145: =IF($CN$143<>"",C12,"") | CO145: =IF($CO$143<>"",C12,"") | CP145: =IF($CP$143<>"",C12,"") | CQ145: =IF($CQ$143<>"",C12,"") | CR145: =IF($CR$143<>"",C12,"") | CS145: =IF(CS144<>"",B$16,"") | CT145: =IF($CT$143<>"",C12,"") | CU145: =IF($CU$143<>"",C12,"") | CV145: =IF($CV$143<>"",C12,"") | CW145: =IF($CW$143<>"",C12,"") | CX145: =IF(CX143<>"",$C$12,"") | CY145: =IF($CY$143<>"",C12,"") | CZ145: =IF($CZ$143<>"",C12,"") | DA145: =IF($DA$143<>"",C12,"") | DB145: =IF($DB$143<>"",C12,"") | DC145: =IF($DC$143<>"",C12,"") | DD145: =IF($DD$143<>"",C12,"") | DE145: =IF($DE$143<>"",C12,"") | DF145: =IF($DF$143<>"",C12,"") | DG145: =IF($DG$143<>"",C12,"") | DH145: =IF($DH$143<>"",C12,"") | DI145: =IF($DI$143<>"",C12,"") | DJ145: =IF($DJ$143<>"",C12,"") | DK145: =IF($DK$143<>"",$C12,"") | DL145: =IF($DL$143<>"",$C12,"") | DM145: =IF($DM$143<>"",$C12,"") | DN145: =IF($DN$143<>"",$C12,"") | DO145: =IF($DO$143<>"",$C12,"") | DP145: =IF($DP$143<>"",$C12,"") | DQ145: =IF($DQ$143<>"",$C12,"") | DR145: =IF($DR$143<>"",$C12,"") | DS145: =IF($DS$143<>"",$C12,"") | DT145: =IF($DT$143<>"",$C12,"") | DU145: =IF($DU$143<>"",$C12,"") | DV145: =IF($DV$143<>"",$C12,"") | DY145: CAMISA TERMICA MASCULINO | DZ145: NOVOPE | EA145: AMOR AMOR | EB145: AZUL TURMALINA | EC145: BOMBEIRO
A146: =IF(PEDIDO!C407<>"",PEDIDO!B407,"") | B146: =IF(PEDIDO!X407<>"",PEDIDO!X407,"") | C146: =IF(PEDIDO!AA407<>"",PEDIDO!AA407,"") | D146: =IF(PEDIDO!AD407<>"",PEDIDO!AD407,"") | E146: =IF(PEDIDO!AG407<>"",PEDIDO!AG407,"") | F146: =IF(PEDIDO!AJ407<>"",PEDIDO!AJ407,"") | J146: =IF(PEDIDO!C38<>"",PEDIDO!B38,"") | K146: =IF($K$143<>"",C13,"") | L146: =IF($L$143<>"",C13,"") | M146: =IF($M$143<>"",C13,"") | N146: =IF($N$143<>"",C13,"") | O146: =IF($O$143<>"",C13,"") | P146: =IF($P$143<>"",C13,"") | Q146: =IF($Q$143<>"",C13,"") | R146: =IF($R$143<>"",C13,"") | S146: =IF($S$143<>"",C13,"") | T146: =IF($T$143<>"",C13,"") | U146: =IF($U$143<>"",C13,"") | V146: =IF($V$143<>"",C13,"") | W146: =IF($W$143<>"",C13,"") | X146: =IF($X$143<>"",C13,"") | Y146: =IF($Y$143<>"",C13,"") | Z146: =IF($Z$143<>"",C13,"") | AA146: =IF($AA$143<>"",C13,"") | AB146: =IF($AB$143<>"",C13,"") | AC146: =IF($AC$143<>"",C13,"") | AD146: =IF($AD$143<>"",C13,"") | AE146: =IF($AE$143<>"",C13,"") | AF146: =IF($AF$143<>"",C13,"") | AG146: =IF($AG$143<>"",C13,"") | AH146: =IF($AH$143<>"",C13,"") | AI146: =IF($AI$143<>"",C13,"") | AJ146: =IF($AJ$143<>"",C13,"") | AK146: =IF($AK$143<>"",C13,"") | AL146: =IF($AL$143<>"",C13,"") | AM146: =IF($AM$143<>"",C13,"") | AN146: =IF($AN$143<>"",C13,"") | AO146: =IF($AO$143<>"",C13,"") | AP146: =IF($AP$143<>"",C13,"") | AQ146: =IF($AQ$143<>"",C13,"") | AR146: =IF($AR$143<>"",C13,"") | AS146: =IF($AS$143<>"",C13,"") | AT146: =IF($AT$143<>"",C13,"") | AU146: =IF($AU$143<>"",C13,"") | AV146: =IF($AV$143<>"",C13,"") | AW146: =IF($AW$143<>"",C13,"") | AX146: =IF($AX$143<>"",C13,"") | AY146: =IF($AY$143<>"",C13,"") | AZ146: =IF($AZ$143<>"",C13,"") | BA146: =IF(BA145<>"",$C$11,"") | BB146: =IF($BB$143<>"",C13,"") | BC146: =IF($BC$143<>"",C13,"") | BD146: =IF($BD$143<>"",C13,"") | BE146: =IF($BE$143<>"",C13,"") | BF146: =IF($BF$143<>"",C13,"") | BG146: =IF($BG$143<>"",C13,"") | BH146: =IF($BH$143<>"",C13,"") | BI146: =IF($BI$143<>"",C13,"") | BJ146: =IF($BJ$143<>"",C13,"") | BK146: =IF($BK$143<>"",C13,"") | BL146: =IF($BL$143<>"",C13,"") | BM146: =IF($BM$143<>"",C13,"") | BN146: =IF($BN$143<>"",C13,"") | BO146: =IF($BO$143<>"",C13,"") | BP146: =IF($BP$143<>"",C13,"") | BQ146: =IF($BQ$143<>"",C13,"") | BR146: =IF($BR$143<>"",C13,"") | BS146: =IF($BS$143<>"",C13,"") | BT146: =IF($BT$143<>"",C13,"") | BU146: =IF($BU$143<>"",C13,"") | BV146: =IF($BV$143<>"",C13,"") | BW146: =IF($BW$143<>"",C13,"") | BX146: =IF($BX$143<>"",C13,"") | BY146: =IF($BY$143<>"",C13,"") | BZ146: =IF($BZ$143<>"",C13,"") | CA146: =IF($CA$143<>"",C13,"") | CB146: =IF($CB$143<>"",C13,"") | CC146: =IF($CC$143<>"",C13,"") | CD146: =IF($CD$143<>"",C13,"") | CE146: =IF($CE$143<>"",C13,"") | CF146: =IF($CF$143<>"",C13,"") | CG146: =IF($CG$143<>"",C13,"") | CH146: =IF($CH$143<>"",C13,"") | CI146: =IF($CI$143<>"",C13,"") | CJ146: =IF($CJ$143<>"",C13,"") | CK146: =IF($CK$143<>"",C13,"") | CL146: =IF($CL$143<>"",C13,"") | CM146: =IF($CM$143<>"",C13,"") | CN146: =IF($CN$143<>"",C13,"") | CO146: =IF($CO$143<>"",C13,"") | CP146: =IF($CP$143<>"",C13,"") | CQ146: =IF($CQ$143<>"",C13,"") | CR146: =IF($CR$143<>"",C13,"") | CS146: =IF(CS145<>"",B$16,"") | CT146: =IF($CT$143<>"",C13,"") | CU146: =IF($CU$143<>"",C13,"") | CV146: =IF($CV$143<>"",C13,"") | CW146: =IF($CW$143<>"",C13,"") | CX146: =IF(CX143<>"",$C$13,"") | CY146: =IF($CY$143<>"",C13,"") | CZ146: =IF($CZ$143<>"",C13,"") | DA146: =IF($DA$143<>"",C13,"") | DB146: =IF($DB$143<>"",C13,"") | DC146: =IF($DC$143<>"",C13,"") | DD146: =IF($DD$143<>"",C13,"") | DE146: =IF($DE$143<>"",C13,"") | DF146: =IF($DF$143<>"",C13,"") | DG146: =IF($DG$143<>"",C13,"") | DH146: =IF($DH$143<>"",C13,"") | DI146: =IF($DI$143<>"",C13,"") | DJ146: =IF($DJ$143<>"",C13,"") | DK146: =IF($DK$143<>"",$C13,"") | DL146: =IF($DL$143<>"",$C13,"") | DM146: =IF($DM$143<>"",$C13,"") | DN146: =IF($DN$143<>"",$C13,"") | DO146: =IF($DO$143<>"",$C13,"") | DP146: =IF($DP$143<>"",$C13,"") | DQ146: =IF($DQ$143<>"",$C13,"") | DR146: =IF($DR$143<>"",$C13,"") | DS146: =IF($DS$143<>"",$C13,"") | DT146: =IF($DT$143<>"",$C13,"") | DU146: =IF($DU$143<>"",$C13,"") | DV146: =IF($DV$143<>"",$C13,"") | DY146: CAMISAO | DZ146: TECNOSUL | EA146: AMOR AMOR TESTER | EB146: AZUL TURQUESA | EC146: BOMBER
A147: =IF(PEDIDO!C408<>"",PEDIDO!B408,"") | B147: =IF(PEDIDO!X408<>"",PEDIDO!X408,"") | C147: =IF(PEDIDO!AA408<>"",PEDIDO!AA408,"") | D147: =IF(PEDIDO!AD408<>"",PEDIDO!AD408,"") | E147: =IF(PEDIDO!AG408<>"",PEDIDO!AG408,"") | F147: =IF(PEDIDO!AJ408<>"",PEDIDO!AJ408,"") | J147: =IF(PEDIDO!C39<>"",PEDIDO!B39,"") | K147: =IF($K$143<>"",C14,"") | L147: =IF($L$143<>"",C14,"") | M147: =IF($M$143<>"",C14,"") | N147: =IF($N$143<>"",C14,"") | O147: =IF($O$143<>"",C14,"") | P147: =IF($P$143<>"",C14,"") | Q147: =IF($Q$143<>"",C14,"") | R147: =IF($R$143<>"",C14,"") | S147: =IF($S$143<>"",C14,"") | T147: =IF($T$143<>"",C14,"") | U147: =IF($U$143<>"",C14,"") | V147: =IF($V$143<>"",C14,"") | W147: =IF($W$143<>"",C14,"") | X147: =IF($X$143<>"",C14,"") | Y147: =IF($Y$143<>"",C14,"") | Z147: =IF($Z$143<>"",C14,"") | AA147: =IF($AA$143<>"",C14,"") | AB147: =IF($AB$143<>"",C14,"") | AC147: =IF($AC$143<>"",C14,"") | AD147: =IF($AD$143<>"",C14,"") | AE147: =IF($AE$143<>"",C14,"") | AF147: =IF($AF$143<>"",C14,"") | AG147: =IF($AG$143<>"",C14,"") | AH147: =IF($AH$143<>"",C14,"") | AI147: =IF($AI$143<>"",C14,"") | AJ147: =IF($AJ$143<>"",C14,"") | AK147: =IF($AK$143<>"",C14,"") | AL147: =IF($AL$143<>"",C14,"") | AM147: =IF($AM$143<>"",C14,"") | AN147: =IF($AN$143<>"",C14,"") | AO147: =IF($AO$143<>"",C14,"") | AP147: =IF($AP$143<>"",C14,"") | AQ147: =IF($AQ$143<>"",C14,"") | AR147: =IF($AR$143<>"",C14,"") | AS147: =IF($AS$143<>"",C14,"") | AT147: =IF($AT$143<>"",C14,"") | AU147: =IF($AU$143<>"",C14,"") | AV147: =IF($AV$143<>"",C14,"") | AW147: =IF($AW$143<>"",C14,"") | AX147: =IF($AX$143<>"",C14,"") | AY147: =IF($AY$143<>"",C14,"") | AZ147: =IF($AZ$143<>"",C14,"") | BA147: =IF(BA146<>"",$C$11,"") | BB147: =IF($BB$143<>"",C14,"") | BC147: =IF($BC$143<>"",C14,"") | BD147: =IF($BD$143<>"",C14,"") | BE147: =IF($BE$143<>"",C14,"") | BF147: =IF($BF$143<>"",C14,"") | BG147: =IF($BG$143<>"",C14,"") | BH147: =IF($BH$143<>"",C14,"") | BI147: =IF($BI$143<>"",C14,"") | BJ147: =IF($BJ$143<>"",C14,"") | BK147: =IF($BK$143<>"",C14,"") | BL147: =IF($BL$143<>"",C14,"") | BM147: =IF($BM$143<>"",C14,"") | BN147: =IF($BN$143<>"",C14,"") | BO147: =IF($BO$143<>"",C14,"") | BP147: =IF($BP$143<>"",C14,"") | BQ147: =IF($BQ$143<>"",C14,"") | BR147: =IF($BR$143<>"",C14,"") | BS147: =IF($BS$143<>"",C14,"") | BT147: =IF($BT$143<>"",C14,"") | BU147: =IF($BU$143<>"",C14,"") | BV147: =IF($BV$143<>"",C14,"") | BW147: =IF($BW$143<>"",C14,"") | BX147: =IF($BX$143<>"",C14,"") | BY147: =IF($BY$143<>"",C14,"") | BZ147: =IF($BZ$143<>"",C14,"") | CA147: =IF($CA$143<>"",C14,"") | CB147: =IF($CB$143<>"",C14,"") | CC147: =IF($CC$143<>"",C14,"") | CD147: =IF($CD$143<>"",C14,"") | CE147: =IF($CE$143<>"",C14,"") | CF147: =IF($CF$143<>"",C14,"") | CG147: =IF($CG$143<>"",C14,"") | CH147: =IF($CH$143<>"",C14,"") | CI147: =IF($CI$143<>"",C14,"") | CJ147: =IF($CJ$143<>"",C14,"") | CK147: =IF($CK$143<>"",C14,"") | CL147: =IF($CL$143<>"",C14,"") | CM147: =IF($CM$143<>"",C14,"") | CN147: =IF($CN$143<>"",C14,"") | CO147: =IF($CO$143<>"",C14,"") | CP147: =IF($CP$143<>"",C14,"") | CQ147: =IF($CQ$143<>"",C14,"") | CR147: =IF($CR$143<>"",C14,"") | CS147: =IF(CS146<>"",B$16,"") | CT147: =IF($CT$143<>"",C14,"") | CU147: =IF($CU$143<>"",C14,"") | CV147: =IF($CV$143<>"",C14,"") | CW147: =IF($CW$143<>"",C14,"") | CX147: =IF(CX143<>"",$C$14,"") | CY147: =IF($CY$143<>"",C14,"") | CZ147: =IF($CZ$143<>"",C14,"") | DA147: =IF($DA$143<>"",C14,"") | DB147: =IF($DB$143<>"",C14,"") | DC147: =IF($DC$143<>"",C14,"") | DD147: =IF($DD$143<>"",C14,"") | DE147: =IF($DE$143<>"",C14,"") | DF147: =IF($DF$143<>"",C14,"") | DG147: =IF($DG$143<>"",C14,"") | DH147: =IF($DH$143<>"",C14,"") | DI147: =IF($DI$143<>"",C14,"") | DJ147: =IF($DJ$143<>"",C14,"") | DK147: =IF($DK$143<>"",$C14,"") | DL147: =IF($DL$143<>"",$C14,"") | DM147: =IF($DM$143<>"",$C14,"") | DN147: =IF($DN$143<>"",$C14,"") | DO147: =IF($DO$143<>"",$C14,"") | DP147: =IF($DP$143<>"",$C14,"") | DQ147: =IF($DQ$143<>"",$C14,"") | DR147: =IF($DR$143<>"",$C14,"") | DS147: =IF($DS$143<>"",$C14,"") | DT147: =IF($DT$143<>"",$C14,"") | DU147: =IF($DU$143<>"",$C14,"") | DV147: =IF($DV$143<>"",$C14,"") | DY147: CAMISAO FEMININO | DZ147: JUSAMA | EA147: AMOR ETERNO | EB147: AZUL WORKS | EC147: BOOM
A148: =IF(PEDIDO!C409<>"",PEDIDO!B409,"") | B148: =IF(PEDIDO!X409<>"",PEDIDO!X409,"") | C148: =IF(PEDIDO!AA409<>"",PEDIDO!AA409,"") | D148: =IF(PEDIDO!AD409<>"",PEDIDO!AD409,"") | E148: =IF(PEDIDO!AG409<>"",PEDIDO!AG409,"") | F148: =IF(PEDIDO!AJ409<>"",PEDIDO!AJ409,"") | J148: =IF(PEDIDO!C40<>"",PEDIDO!B40,"") | K148: =IF($K$143<>"",C15,"") | L148: =IF($L$143<>"",C15,"") | M148: =IF($M$143<>"",C15,"") | N148: =IF($N$143<>"",C15,"") | O148: =IF($O$143<>"",C15,"") | P148: =IF($P$143<>"",C15,"") | Q148: =IF($Q$143<>"",C15,"") | R148: =IF($R$143<>"",C15,"") | S148: =IF($S$143<>"",C15,"") | T148: =IF($T$143<>"",C15,"") | U148: =IF($U$143<>"",C15,"") | V148: =IF($V$143<>"",C15,"") | W148: =IF($W$143<>"",C15,"") | X148: =IF($X$143<>"",C15,"") | Y148: =IF($Y$143<>"",C15,"") | Z148: =IF($Z$143<>"",C15,"") | AA148: =IF($AA$143<>"",C15,"") | AB148: =IF($AB$143<>"",C15,"") | AC148: =IF($AC$143<>"",C15,"") | AD148: =IF($AD$143<>"",C15,"") | AE148: =IF($AE$143<>"",C15,"") | AF148: =IF($AF$143<>"",C15,"") | AG148: =IF($AG$143<>"",C15,"") | AH148: =IF($AH$143<>"",C15,"") | AI148: =IF($AI$143<>"",C15,"") | AJ148: =IF($AJ$143<>"",C15,"") | AK148: =IF($AK$143<>"",C15,"") | AL148: =IF($AL$143<>"",C15,"") | AM148: =IF($AM$143<>"",C15,"") | AN148: =IF($AN$143<>"",C15,"") | AO148: =IF($AO$143<>"",C15,"") | AP148: =IF($AP$143<>"",C15,"") | AQ148: =IF($AQ$143<>"",C15,"") | AR148: =IF($AR$143<>"",C15,"") | AS148: =IF($AS$143<>"",C15,"") | AT148: =IF($AT$143<>"",C15,"") | AU148: =IF($AU$143<>"",C15,"") | AV148: =IF($AV$143<>"",C15,"") | AW148: =IF($AW$143<>"",C15,"") | AX148: =IF($AX$143<>"",C15,"") | AY148: =IF($AY$143<>"",C15,"") | AZ148: =IF($AZ$143<>"",C15,"") | BA148: =IF(BA147<>"",$C$11,"") | BB148: =IF($BB$143<>"",C15,"") | BC148: =IF($BC$143<>"",C15,"") | BD148: =IF($BD$143<>"",C15,"") | BE148: =IF($BE$143<>"",C15,"") | BF148: =IF($BF$143<>"",C15,"") | BG148: =IF($BG$143<>"",C15,"") | BH148: =IF($BH$143<>"",C15,"") | BI148: =IF($BI$143<>"",C15,"") | BJ148: =IF($BJ$143<>"",C15,"") | BK148: =IF($BK$143<>"",C15,"") | BL148: =IF($BL$143<>"",C15,"") | BM148: =IF($BM$143<>"",C15,"") | BN148: =IF($BN$143<>"",C15,"") | BO148: =IF($BO$143<>"",C15,"") | BP148: =IF($BP$143<>"",C15,"") | BQ148: =IF($BQ$143<>"",C15,"") | BR148: =IF($BR$143<>"",C15,"") | BS148: =IF($BS$143<>"",C15,"") | BT148: =IF($BT$143<>"",C15,"") | BU148: =IF($BU$143<>"",C15,"") | BV148: =IF($BV$143<>"",C15,"") | BW148: =IF($BW$143<>"",C15,"") | BX148: =IF($BX$143<>"",C15,"") | BY148: =IF($BY$143<>"",C15,"") | BZ148: =IF($BZ$143<>"",C15,"") | CA148: =IF($CA$143<>"",C15,"") | CB148: =IF($CB$143<>"",C15,"") | CC148: =IF($CC$143<>"",C15,"") | CD148: =IF($CD$143<>"",C15,"") | CE148: =IF($CE$143<>"",C15,"") | CF148: =IF($CF$143<>"",C15,"") | CG148: =IF($CG$143<>"",C15,"") | CH148: =IF($CH$143<>"",C15,"") | CI148: =IF($CI$143<>"",C15,"") | CJ148: =IF($CJ$143<>"",C15,"") | CK148: =IF($CK$143<>"",C15,"") | CL148: =IF($CL$143<>"",C15,"") | CM148: =IF($CM$143<>"",C15,"") | CN148: =IF($CN$143<>"",C15,"") | CO148: =IF($CO$143<>"",C15,"") | CP148: =IF($CP$143<>"",C15,"") | CQ148: =IF($CQ$143<>"",C15,"") | CR148: =IF($CR$143<>"",C15,"") | CS148: =IF(CS147<>"",B$16,"") | CT148: =IF($CT$143<>"",C15,"") | CU148: =IF($CU$143<>"",C15,"") | CV148: =IF($CV$143<>"",C15,"") | CW148: =IF($CW$143<>"",C15,"") | CX148: =IF(CX143<>"",$C$15,"") | CY148: =IF($CY$143<>"",C15,"") | CZ148: =IF($CZ$143<>"",C15,"") | DA148: =IF($DA$143<>"",C15,"") | DB148: =IF($DB$143<>"",C15,"") | DC148: =IF($DC$143<>"",C15,"") | DD148: =IF($DD$143<>"",C15,"") | DE148: =IF($DE$143<>"",C15,"") | DF148: =IF($DF$143<>"",C15,"") | DG148: =IF($DG$143<>"",C15,"") | DH148: =IF($DH$143<>"",C15,"") | DI148: =IF($DI$143<>"",C15,"") | DJ148: =IF($DJ$143<>"",C15,"") | DK148: =IF($DK$143<>"",$C15,"") | DL148: =IF($DL$143<>"",$C15,"") | DM148: =IF($DM$143<>"",$C15,"") | DN148: =IF($DN$143<>"",$C15,"") | DO148: =IF($DO$143<>"",$C15,"") | DP148: =IF($DP$143<>"",$C15,"") | DQ148: =IF($DQ$143<>"",$C15,"") | DR148: =IF($DR$143<>"",$C15,"") | DS148: =IF($DS$143<>"",$C15,"") | DT148: =IF($DT$143<>"",$C15,"") | DU148: =IF($DU$143<>"",$C15,"") | DV148: =IF($DV$143<>"",$C15,"") | DY148: CAMISAO INFANTIL | DZ148: CASA CAMPOS | EA148: AMORA MARIA | EB148: AZURE BLUE | EC148: BORDO RACER
A149: =IF(PEDIDO!C410<>"",PEDIDO!B410,"") | B149: =IF(PEDIDO!X410<>"",PEDIDO!X410,"") | C149: =IF(PEDIDO!AA410<>"",PEDIDO!AA410,"") | D149: =IF(PEDIDO!AD410<>"",PEDIDO!AD410,"") | E149: =IF(PEDIDO!AG410<>"",PEDIDO!AG410,"") | F149: =IF(PEDIDO!AJ410<>"",PEDIDO!AJ410,"") | J149: =IF(PEDIDO!C41<>"",PEDIDO!B41,"") | K149: =IF($K$143<>"",C16,"") | L149: =IF($L$143<>"",C16,"") | M149: =IF($M$143<>"",C16,"") | N149: =IF($N$143<>"",C16,"") | O149: =IF($O$143<>"",C16,"") | P149: =IF($P$143<>"",C16,"") | Q149: =IF($Q$143<>"",C16,"") | R149: =IF($R$143<>"",C16,"") | S149: =IF($S$143<>"",C16,"") | T149: =IF($T$143<>"",C16,"") | U149: =IF($U$143<>"",C16,"") | V149: =IF($V$143<>"",C16,"") | W149: =IF($W$143<>"",C16,"") | X149: =IF($X$143<>"",C16,"") | Y149: =IF($Y$143<>"",C16,"") | Z149: =IF($Z$143<>"",C16,"") | AA149: =IF($AA$143<>"",C16,"") | AB149: =IF($AB$143<>"",C16,"") | AC149: =IF($AC$143<>"",C16,"") | AD149: =IF($AD$143<>"",C16,"") | AE149: =IF($AE$143<>"",C16,"") | AF149: =IF($AF$143<>"",C16,"") | AG149: =IF($AG$143<>"",C16,"") | AH149: =IF($AH$143<>"",C16,"") | AI149: =IF($AI$143<>"",C16,"") | AJ149: =IF($AJ$143<>"",C16,"") | AK149: =IF($AK$143<>"",C16,"") | AL149: =IF($AL$143<>"",C16,"") | AM149: =IF($AM$143<>"",C16,"") | AN149: =IF($AN$143<>"",C16,"") | AO149: =IF($AO$143<>"",C16,"") | AP149: =IF($AP$143<>"",C16,"") | AQ149: =IF($AQ$143<>"",C16,"") | AR149: =IF($AR$143<>"",C16,"") | AS149: =IF($AS$143<>"",C16,"") | AT149: =IF($AT$143<>"",C16,"") | AU149: =IF($AU$143<>"",C16,"") | AV149: =IF($AV$143<>"",C16,"") | AW149: =IF($AW$143<>"",C16,"") | AX149: =IF($AX$143<>"",C16,"") | AY149: =IF($AY$143<>"",C16,"") | AZ149: =IF($AZ$143<>"",C16,"") | BA149: =IF(BA148<>"",$C$11,"") | BB149: =IF($BB$143<>"",C16,"") | BC149: =IF($BC$143<>"",C16,"") | BD149: =IF($BD$143<>"",C16,"") | BE149: =IF($BE$143<>"",C16,"") | BF149: =IF($BF$143<>"",C16,"") | BG149: =IF($BG$143<>"",C16,"") | BH149: =IF($BH$143<>"",C16,"") | BI149: =IF($BI$143<>"",C16,"") | BJ149: =IF($BJ$143<>"",C16,"") | BK149: =IF($BK$143<>"",C16,"") | BL149: =IF($BL$143<>"",C16,"") | BM149: =IF($BM$143<>"",C16,"") | BN149: =IF($BN$143<>"",C16,"") | BO149: =IF($BO$143<>"",C16,"") | BP149: =IF($BP$143<>"",C16,"") | BQ149: =IF($BQ$143<>"",C16,"") | BR149: =IF($BR$143<>"",C16,"") | BS149: =IF($BS$143<>"",C16,"") | BT149: =IF($BT$143<>"",C16,"") | BU149: =IF($BU$143<>"",C16,"") | BV149: =IF($BV$143<>"",C16,"") | BW149: =IF($BW$143<>"",C16,"") | BX149: =IF($BX$143<>"",C16,"") | BY149: =IF($BY$143<>"",C16,"") | BZ149: =IF($BZ$143<>"",C16,"") | CA149: =IF($CA$143<>"",C16,"") | CB149: =IF($CB$143<>"",C16,"") | CC149: =IF($CC$143<>"",C16,"") | CD149: =IF($CD$143<>"",C16,"") | CE149: =IF($CE$143<>"",C16,"") | CF149: =IF($CF$143<>"",C16,"") | CG149: =IF($CG$143<>"",C16,"") | CH149: =IF($CH$143<>"",C16,"") | CI149: =IF($CI$143<>"",C16,"") | CJ149: =IF($CJ$143<>"",C16,"") | CK149: =IF($CK$143<>"",C16,"") | CL149: =IF($CL$143<>"",C16,"") | CM149: =IF($CM$143<>"",C16,"") | CN149: =IF($CN$143<>"",C16,"") | CO149: =IF($CO$143<>"",C16,"") | CP149: =IF($CP$143<>"",C16,"") | CQ149: =IF($CQ$143<>"",C16,"") | CR149: =IF($CR$143<>"",C16,"") | CS149: =IF(CS148<>"",B$16,"") | CT149: =IF($CT$143<>"",C16,"") | CU149: =IF($CU$143<>"",C16,"") | CV149: =IF($CV$143<>"",C16,"") | CW149: =IF($CW$143<>"",C16,"") | CX149: =IF(CX143<>"",$C$16,"") | CY149: =IF($CY$143<>"",C16,"") | CZ149: =IF($CZ$143<>"",C16,"") | DA149: =IF($DA$143<>"",C16,"") | DB149: =IF($DB$143<>"",C16,"") | DC149: =IF($DC$143<>"",C16,"") | DD149: =IF($DD$143<>"",C16,"") | DE149: =IF($DE$143<>"",C16,"") | DF149: =IF($DF$143<>"",C16,"") | DG149: =IF($DG$143<>"",C16,"") | DH149: =IF($DH$143<>"",C16,"") | DI149: =IF($DI$143<>"",C16,"") | DJ149: =IF($DJ$143<>"",C16,"") | DK149: =IF($DK$143<>"",$C16,"") | DL149: =IF($DL$143<>"",$C16,"") | DM149: =IF($DM$143<>"",$C16,"") | DN149: =IF($DN$143<>"",$C16,"") | DO149: =IF($DO$143<>"",$C16,"") | DP149: =IF($DP$143<>"",$C16,"") | DQ149: =IF($DQ$143<>"",$C16,"") | DR149: =IF($DR$143<>"",$C16,"") | DS149: =IF($DS$143<>"",$C16,"") | DT149: =IF($DT$143<>"",$C16,"") | DU149: =IF($DU$143<>"",$C16,"") | DV149: =IF($DV$143<>"",$C16,"") | DY149: CAMISAO MASCULINO | DZ149: PREFEITURA | EA149: AMORARMA | EB149: AZURITE | EC149: BORDO TITANIUM
A150: =IF(PEDIDO!C411<>"",PEDIDO!B411,"") | B150: =IF(PEDIDO!X411<>"",PEDIDO!X411,"") | C150: =IF(PEDIDO!AA411<>"",PEDIDO!AA411,"") | D150: =IF(PEDIDO!AD411<>"",PEDIDO!AD411,"") | E150: =IF(PEDIDO!AG411<>"",PEDIDO!AG411,"") | F150: =IF(PEDIDO!AJ411<>"",PEDIDO!AJ411,"") | J150: =IF(PEDIDO!C42<>"",PEDIDO!B42,"") | K150: =IF($K$143<>"",C17,"") | L150: =IF($L$143<>"",C17,"") | M150: =IF($M$143<>"",C17,"") | N150: =IF($N$143<>"",C17,"") | O150: =IF($O$143<>"",C17,"") | P150: =IF($P$143<>"",C17,"") | Q150: =IF($Q$143<>"",C17,"") | R150: =IF($R$143<>"",C17,"") | S150: =IF($S$143<>"",C17,"") | T150: =IF($T$143<>"",C17,"") | U150: =IF($U$143<>"",C17,"") | V150: =IF($V$143<>"",C17,"") | W150: =IF($W$143<>"",C17,"") | X150: =IF($X$143<>"",C17,"") | Y150: =IF($Y$143<>"",C17,"") | Z150: =IF($Z$143<>"",C17,"") | AA150: =IF($AA$143<>"",C17,"") | AB150: =IF($AB$143<>"",C17,"") | AC150: =IF($AC$143<>"",C17,"") | AD150: =IF($AD$143<>"",C17,"") | AE150: =IF($AE$143<>"",C17,"") | AF150: =IF($AF$143<>"",C17,"") | AG150: =IF($AG$143<>"",C17,"") | AH150: =IF($AH$143<>"",C17,"") | AI150: =IF($AI$143<>"",C17,"") | AJ150: =IF($AJ$143<>"",C17,"") | AK150: =IF($AK$143<>"",C17,"") | AL150: =IF($AL$143<>"",C17,"") | AM150: =IF($AM$143<>"",C17,"") | AN150: =IF($AN$143<>"",C17,"") | AO150: =IF($AO$143<>"",C17,"") | AP150: =IF($AP$143<>"",C17,"") | AQ150: =IF($AQ$143<>"",C17,"") | AR150: =IF($AR$143<>"",C17,"") | AS150: =IF($AS$143<>"",C17,"") | AT150: =IF($AT$143<>"",C17,"") | AU150: =IF($AU$143<>"",C17,"") | AV150: =IF($AV$143<>"",C17,"") | AW150: =IF($AW$143<>"",C17,"") | AX150: =IF($AX$143<>"",C17,"") | AY150: =IF($AY$143<>"",C17,"") | AZ150: =IF($AZ$143<>"",C17,"") | BA150: =IF(BA149<>"",$C$11,"") | BB150: =IF($BB$143<>"",C17,"") | BC150: =IF($BC$143<>"",C17,"") | BD150: =IF($BD$143<>"",C17,"") | BE150: =IF($BE$143<>"",C17,"") | BF150: =IF($BF$143<>"",C17,"") | BG150: =IF($BG$143<>"",C17,"") | BH150: =IF($BH$143<>"",C17,"") | BI150: =IF($BI$143<>"",C17,"") | BJ150: =IF($BJ$143<>"",C17,"") | BK150: =IF($BK$143<>"",C17,"") | BL150: =IF($BL$143<>"",C17,"") | BM150: =IF($BM$143<>"",C17,"") | BN150: =IF($BN$143<>"",C17,"") | BO150: =IF($BO$143<>"",C17,"") | BP150: =IF($BP$143<>"",C17,"") | BQ150: =IF($BQ$143<>"",C17,"") | BR150: =IF($BR$143<>"",C17,"") | BS150: =IF($BS$143<>"",C17,"") | BT150: =IF($BT$143<>"",C17,"") | BU150: =IF($BU$143<>"",C17,"") | BV150: =IF($BV$143<>"",C17,"") | BW150: =IF($BW$143<>"",C17,"") | BX150: =IF($BX$143<>"",C17,"") | BY150: =IF($BY$143<>"",C17,"") | BZ150: =IF($BZ$143<>"",C17,"") | CA150: =IF($CA$143<>"",C17,"") | CB150: =IF($CB$143<>"",C17,"") | CC150: =IF($CC$143<>"",C17,"") | CD150: =IF($CD$143<>"",C17,"") | CE150: =IF($CE$143<>"",C17,"") | CF150: =IF($CF$143<>"",C17,"") | CG150: =IF($CG$143<>"",C17,"") | CH150: =IF($CH$143<>"",C17,"") | CI150: =IF($CI$143<>"",C17,"") | CJ150: =IF($CJ$143<>"",C17,"") | CK150: =IF($CK$143<>"",C17,"") | CL150: =IF($CL$143<>"",C17,"") | CM150: =IF($CM$143<>"",C17,"") | CN150: =IF($CN$143<>"",C17,"") | CO150: =IF($CO$143<>"",C17,"") | CP150: =IF($CP$143<>"",C17,"") | CQ150: =IF($CQ$143<>"",C17,"") | CR150: =IF($CR$143<>"",C17,"") | CS150: =IF(CS149<>"",B$16,"") | CT150: =IF($CT$143<>"",C17,"") | CU150: =IF($CU$143<>"",C17,"") | CV150: =IF($CV$143<>"",C17,"") | CW150: =IF($CW$143<>"",C17,"") | CX150: =IF($CX$11<>"",B149,"") | CY150: =IF($CY$143<>"",C17,"") | CZ150: =IF($CZ$143<>"",C17,"") | DA150: =IF($DA$143<>"",C17,"") | DB150: =IF($DB$143<>"",C17,"") | DC150: =IF($DC$143<>"",C17,"") | DD150: =IF($DD$143<>"",C17,"") | DE150: =IF($DE$143<>"",C17,"") | DF150: =IF($DF$143<>"",C17,"") | DG150: =IF($DG$143<>"",C17,"") | DH150: =IF($DH$143<>"",C17,"") | DI150: =IF($DI$143<>"",C17,"") | DJ150: =IF($DJ$143<>"",C17,"") | DK150: =IF($DK$143<>"",$C17,"") | DL150: =IF($DL$143<>"",$C17,"") | DM150: =IF($DM$143<>"",$C17,"") | DN150: =IF($DN$143<>"",$C17,"") | DO150: =IF($DO$143<>"",$C17,"") | DP150: =IF($DP$143<>"",$C17,"") | DQ150: =IF($DQ$143<>"",$C17,"") | DR150: =IF($DR$143<>"",$C17,"") | DS150: =IF($DS$143<>"",$C17,"") | DT150: =IF($DT$143<>"",$C17,"") | DU150: =IF($DU$143<>"",$C17,"") | DV150: =IF($DV$143<>"",$C17,"") | DY150: CAMISETA | DZ150: PAPELARIA IRMAOS RIBEIRO | EA150: AMORECA | EB150: BABALLO | EC150: BOREAL
A151: =IF(PEDIDO!C412<>"",PEDIDO!B412,"") | B151: =IF(PEDIDO!X412<>"",PEDIDO!X412,"") | C151: =IF(PEDIDO!AA412<>"",PEDIDO!AA412,"") | D151: =IF(PEDIDO!AD412<>"",PEDIDO!AD412,"") | E151: =IF(PEDIDO!AG412<>"",PEDIDO!AG412,"") | F151: =IF(PEDIDO!AJ412<>"",PEDIDO!AJ412,"") | J151: =IF(PEDIDO!C43<>"",PEDIDO!B43,"") | K151: =IF($K$143<>"",C18,"") | L151: =IF($L$143<>"",C18,"") | M151: =IF($M$143<>"",C18,"") | N151: =IF($N$143<>"",C18,"") | O151: =IF($O$143<>"",C18,"") | P151: =IF($P$143<>"",C18,"") | Q151: =IF($Q$143<>"",C18,"") | R151: =IF($R$143<>"",C18,"") | S151: =IF($S$143<>"",C18,"") | T151: =IF($T$143<>"",C18,"") | U151: =IF($U$143<>"",C18,"") | V151: =IF($V$143<>"",C18,"") | W151: =IF($W$143<>"",C18,"") | X151: =IF($X$143<>"",C18,"") | Y151: =IF($Y$143<>"",C18,"") | Z151: =IF($Z$143<>"",C18,"") | AA151: =IF($AA$143<>"",C18,"") | AB151: =IF($AB$143<>"",C18,"") | AC151: =IF($AC$143<>"",C18,"") | AD151: =IF($AD$143<>"",C18,"") | AE151: =IF($AE$143<>"",C18,"") | AF151: =IF($AF$143<>"",C18,"") | AG151: =IF($AG$143<>"",C18,"") | AH151: =IF($AH$143<>"",C18,"") | AI151: =IF($AI$143<>"",C18,"") | AJ151: =IF($AJ$143<>"",C18,"") | AK151: =IF($AK$143<>"",C18,"") | AL151: =IF($AL$143<>"",C18,"") | AM151: =IF($AM$143<>"",C18,"") | AN151: =IF($AN$143<>"",C18,"") | AO151: =IF($AO$143<>"",C18,"") | AP151: =IF($AP$143<>"",C18,"") | AQ151: =IF($AQ$143<>"",C18,"") | AR151: =IF($AR$143<>"",C18,"") | AS151: =IF($AS$143<>"",C18,"") | AT151: =IF($AT$143<>"",C18,"") | AU151: =IF($AU$143<>"",C18,"") | AV151: =IF($AV$143<>"",C18,"") | AW151: =IF($AW$143<>"",C18,"") | AX151: =IF($AX$143<>"",C18,"") | AY151: =IF($AY$143<>"",C18,"") | AZ151: =IF($AZ$143<>"",C18,"") | BA151: =IF(BA150<>"",$C$11,"") | BB151: =IF($BB$143<>"",C18,"") | BC151: =IF($BC$143<>"",C18,"") | BD151: =IF($BD$143<>"",C18,"") | BE151: =IF($BE$143<>"",C18,"") | BF151: =IF($BF$143<>"",C18,"") | BG151: =IF($BG$143<>"",C18,"") | BH151: =IF($BH$143<>"",C18,"") | BI151: =IF($BI$143<>"",C18,"") | BJ151: =IF($BJ$143<>"",C18,"") | BK151: =IF($BK$143<>"",C18,"") | BL151: =IF($BL$143<>"",C18,"") | BM151: =IF($BM$143<>"",C18,"") | BN151: =IF($BN$143<>"",C18,"") | BO151: =IF($BO$143<>"",C18,"") | BP151: =IF($BP$143<>"",C18,"") | BQ151: =IF($BQ$143<>"",C18,"") | BR151: =IF($BR$143<>"",C18,"") | BS151: =IF($BS$143<>"",C18,"") | BT151: =IF($BT$143<>"",C18,"") | BU151: =IF($BU$143<>"",C18,"") | BV151: =IF($BV$143<>"",C18,"") | BW151: =IF($BW$143<>"",C18,"") | BX151: =IF($BX$143<>"",C18,"") | BY151: =IF($BY$143<>"",C18,"") | BZ151: =IF($BZ$143<>"",C18,"") | CA151: =IF($CA$143<>"",C18,"") | CB151: =IF($CB$143<>"",C18,"") | CC151: =IF($CC$143<>"",C18,"") | CD151: =IF($CD$143<>"",C18,"") | CE151: =IF($CE$143<>"",C18,"") | CF151: =IF($CF$143<>"",C18,"") | CG151: =IF($CG$143<>"",C18,"") | CH151: =IF($CH$143<>"",C18,"") | CI151: =IF($CI$143<>"",C18,"") | CJ151: =IF($CJ$143<>"",C18,"") | CK151: =IF($CK$143<>"",C18,"") | CL151: =IF($CL$143<>"",C18,"") | CM151: =IF($CM$143<>"",C18,"") | CN151: =IF($CN$143<>"",C18,"") | CO151: =IF($CO$143<>"",C18,"") | CP151: =IF($CP$143<>"",C18,"") | CQ151: =IF($CQ$143<>"",C18,"") | CR151: =IF($CR$143<>"",C18,"") | CS151: =IF(CS150<>"",B$16,"") | CT151: =IF($CT$143<>"",C18,"") | CU151: =IF($CU$143<>"",C18,"") | CV151: =IF($CV$143<>"",C18,"") | CW151: =IF($CW$143<>"",C18,"") | CX151: =IF($CX$11<>"",B150,"") | CY151: =IF($CY$143<>"",C18,"") | CZ151: =IF($CZ$143<>"",C18,"") | DA151: =IF($DA$143<>"",C18,"") | DB151: =IF($DB$143<>"",C18,"") | DC151: =IF($DC$143<>"",C18,"") | DD151: =IF($DD$143<>"",C18,"") | DE151: =IF($DE$143<>"",C18,"") | DF151: =IF($DF$143<>"",C18,"") | DG151: =IF($DG$143<>"",C18,"") | DH151: =IF($DH$143<>"",C18,"") | DI151: =IF($DI$143<>"",C18,"") | DJ151: =IF($DJ$143<>"",C18,"") | DK151: =IF($DK$143<>"",$C18,"") | DL151: =IF($DL$143<>"",$C18,"") | DM151: =IF($DM$143<>"",$C18,"") | DN151: =IF($DN$143<>"",$C18,"") | DO151: =IF($DO$143<>"",$C18,"") | DP151: =IF($DP$143<>"",$C18,"") | DQ151: =IF($DQ$143<>"",$C18,"") | DR151: =IF($DR$143<>"",$C18,"") | DS151: =IF($DS$143<>"",$C18,"") | DT151: =IF($DT$143<>"",$C18,"") | DU151: =IF($DU$143<>"",$C18,"") | DV151: =IF($DV$143<>"",$C18,"") | DY151: CAMISETA FEMININO | DZ151: BLACKBULL | EA151: AMORIM EXTINTORES | EB151: BABALOO | EC151: BOROGODO
A152: =IF(PEDIDO!C413<>"",PEDIDO!B413,"") | B152: =IF(PEDIDO!X413<>"",PEDIDO!X413,"") | C152: =IF(PEDIDO!AA413<>"",PEDIDO!AA413,"") | D152: =IF(PEDIDO!AD413<>"",PEDIDO!AD413,"") | E152: =IF(PEDIDO!AG413<>"",PEDIDO!AG413,"") | F152: =IF(PEDIDO!AJ413<>"",PEDIDO!AJ413,"") | J152: =IF(PEDIDO!C44<>"",PEDIDO!B44,"") | K152: =IF($K$143<>"",C19,"") | L152: =IF($L$143<>"",C19,"") | M152: =IF($M$143<>"",C19,"") | N152: =IF($N$143<>"",C19,"") | O152: =IF($O$143<>"",C19,"") | P152: =IF($P$143<>"",C19,"") | Q152: =IF($Q$143<>"",C19,"") | R152: =IF($R$143<>"",C19,"") | S152: =IF($S$143<>"",C19,"") | T152: =IF($T$143<>"",C19,"") | U152: =IF($U$143<>"",C19,"") | V152: =IF($V$143<>"",C19,"") | W152: =IF($W$143<>"",C19,"") | X152: =IF($X$143<>"",C19,"") | Y152: =IF($Y$143<>"",C19,"") | Z152: =IF($Z$143<>"",C19,"") | AA152: =IF($AA$143<>"",C19,"") | AB152: =IF($AB$143<>"",C19,"") | AC152: =IF($AC$143<>"",C19,"") | AD152: =IF($AD$143<>"",C19,"") | AE152: =IF($AE$143<>"",C19,"") | AF152: =IF($AF$143<>"",C19,"") | AG152: =IF($AG$143<>"",C19,"") | AH152: =IF($AH$143<>"",C19,"") | AI152: =IF($AI$143<>"",C19,"") | AJ152: =IF($AJ$143<>"",C19,"") | AK152: =IF($AK$143<>"",C19,"") | AL152: =IF($AL$143<>"",C19,"") | AM152: =IF($AM$143<>"",C19,"") | AN152: =IF($AN$143<>"",C19,"") | AO152: =IF($AO$143<>"",C19,"") | AP152: =IF($AP$143<>"",C19,"") | AQ152: =IF($AQ$143<>"",C19,"") | AR152: =IF($AR$143<>"",C19,"") | AS152: =IF($AS$143<>"",C19,"") | AT152: =IF($AT$143<>"",C19,"") | AU152: =IF($AU$143<>"",C19,"") | AV152: =IF($AV$143<>"",C19,"") | AW152: =IF($AW$143<>"",C19,"") | AX152: =IF($AX$143<>"",C19,"") | AY152: =IF($AY$143<>"",C19,"") | AZ152: =IF($AZ$143<>"",C19,"") | BA152: =IF(BA151<>"",$C$11,"") | BB152: =IF($BB$143<>"",C19,"") | BC152: =IF($BC$143<>"",C19,"") | BD152: =IF($BD$143<>"",C19,"") | BE152: =IF($BE$143<>"",C19,"") | BF152: =IF($BF$143<>"",C19,"") | BG152: =IF($BG$143<>"",C19,"") | BH152: =IF($BH$143<>"",C19,"") | BI152: =IF($BI$143<>"",C19,"") | BJ152: =IF($BJ$143<>"",C19,"") | BK152: =IF($BK$143<>"",C19,"") | BL152: =IF($BL$143<>"",C19,"") | BM152: =IF($BM$143<>"",C19,"") | BN152: =IF($BN$143<>"",C19,"") | BO152: =IF($BO$143<>"",C19,"") | BP152: =IF($BP$143<>"",C19,"") | BQ152: =IF($BQ$143<>"",C19,"") | BR152: =IF($BR$143<>"",C19,"") | BS152: =IF($BS$143<>"",C19,"") | BT152: =IF($BT$143<>"",C19,"") | BU152: =IF($BU$143<>"",C19,"") | BV152: =IF($BV$143<>"",C19,"") | BW152: =IF($BW$143<>"",C19,"") | BX152: =IF($BX$143<>"",C19,"") | BY152: =IF($BY$143<>"",C19,"") | BZ152: =IF($BZ$143<>"",C19,"") | CA152: =IF($CA$143<>"",C19,"") | CB152: =IF($CB$143<>"",C19,"") | CC152: =IF($CC$143<>"",C19,"") | CD152: =IF($CD$143<>"",C19,"") | CE152: =IF($CE$143<>"",C19,"") | CF152: =IF($CF$143<>"",C19,"") | CG152: =IF($CG$143<>"",C19,"") | CH152: =IF($CH$143<>"",C19,"") | CI152: =IF($CI$143<>"",C19,"") | CJ152: =IF($CJ$143<>"",C19,"") | CK152: =IF($CK$143<>"",C19,"") | CL152: =IF($CL$143<>"",C19,"") | CM152: =IF($CM$143<>"",C19,"") | CN152: =IF($CN$143<>"",C19,"") | CO152: =IF($CO$143<>"",C19,"") | CP152: =IF($CP$143<>"",C19,"") | CQ152: =IF($CQ$143<>"",C19,"") | CR152: =IF($CR$143<>"",C19,"") | CS152: =IF(CS151<>"",B$16,"") | CT152: =IF($CT$143<>"",C19,"") | CU152: =IF($CU$143<>"",C19,"") | CV152: =IF($CV$143<>"",C19,"") | CW152: =IF($CW$143<>"",C19,"") | CX152: =IF($CX$11<>"",B151,"") | CY152: =IF($CY$143<>"",C19,"") | CZ152: =IF($CZ$143<>"",C19,"") | DA152: =IF($DA$143<>"",C19,"") | DB152: =IF($DB$143<>"",C19,"") | DC152: =IF($DC$143<>"",C19,"") | DD152: =IF($DD$143<>"",C19,"") | DE152: =IF($DE$143<>"",C19,"") | DF152: =IF($DF$143<>"",C19,"") | DG152: =IF($DG$143<>"",C19,"") | DH152: =IF($DH$143<>"",C19,"") | DI152: =IF($DI$143<>"",C19,"") | DJ152: =IF($DJ$143<>"",C19,"") | DK152: =IF($DK$143<>"",$C19,"") | DL152: =IF($DL$143<>"",$C19,"") | DM152: =IF($DM$143<>"",$C19,"") | DN152: =IF($DN$143<>"",$C19,"") | DO152: =IF($DO$143<>"",$C19,"") | DP152: =IF($DP$143<>"",$C19,"") | DQ152: =IF($DQ$143<>"",$C19,"") | DR152: =IF($DR$143<>"",$C19,"") | DS152: =IF($DS$143<>"",$C19,"") | DT152: =IF($DT$143<>"",$C19,"") | DU152: =IF($DU$143<>"",$C19,"") | DV152: =IF($DV$143<>"",$C19,"") | DY152: CAMISETA INFANTIL | DZ152: G7 NET | EA152: AMOSTRAS | EB152: BAILEYS | EC152: BOTE
A153: =IF(PEDIDO!C414<>"",PEDIDO!B414,"") | B153: =IF(PEDIDO!X414<>"",PEDIDO!X414,"") | C153: =IF(PEDIDO!AA414<>"",PEDIDO!AA414,"") | D153: =IF(PEDIDO!AD414<>"",PEDIDO!AD414,"") | E153: =IF(PEDIDO!AG414<>"",PEDIDO!AG414,"") | F153: =IF(PEDIDO!AJ414<>"",PEDIDO!AJ414,"") | J153: =IF(PEDIDO!C45<>"",PEDIDO!B45,"") | K153: =IF($K$143<>"",C20,"") | L153: =IF($L$143<>"",C20,"") | M153: =IF($M$143<>"",C20,"") | N153: =IF($N$143<>"",C20,"") | O153: =IF($O$143<>"",C20,"") | P153: =IF($P$143<>"",C20,"") | Q153: =IF($Q$143<>"",C20,"") | R153: =IF($R$143<>"",C20,"") | S153: =IF($S$143<>"",C20,"") | T153: =IF($T$143<>"",C20,"") | U153: =IF($U$143<>"",C20,"") | V153: =IF($V$143<>"",C20,"") | W153: =IF($W$143<>"",C20,"") | X153: =IF($X$143<>"",C20,"") | Y153: =IF($Y$143<>"",C20,"") | Z153: =IF($Z$143<>"",C20,"") | AA153: =IF($AA$143<>"",C20,"") | AB153: =IF($AB$143<>"",C20,"") | AC153: =IF($AC$143<>"",C20,"") | AD153: =IF($AD$143<>"",C20,"") | AE153: =IF($AE$143<>"",C20,"") | AF153: =IF($AF$143<>"",C20,"") | AG153: =IF($AG$143<>"",C20,"") | AH153: =IF($AH$143<>"",C20,"") | AI153: =IF($AI$143<>"",C20,"") | AJ153: =IF($AJ$143<>"",C20,"") | AK153: =IF($AK$143<>"",C20,"") | AL153: =IF($AL$143<>"",C20,"") | AM153: =IF($AM$143<>"",C20,"") | AN153: =IF($AN$143<>"",C20,"") | AO153: =IF($AO$143<>"",C20,"") | AP153: =IF($AP$143<>"",C20,"") | AQ153: =IF($AQ$143<>"",C20,"") | AR153: =IF($AR$143<>"",C20,"") | AS153: =IF($AS$143<>"",C20,"") | AT153: =IF($AT$143<>"",C20,"") | AU153: =IF($AU$143<>"",C20,"") | AV153: =IF($AV$143<>"",C20,"") | AW153: =IF($AW$143<>"",C20,"") | AX153: =IF($AX$143<>"",C20,"") | AY153: =IF($AY$143<>"",C20,"") | AZ153: =IF($AZ$143<>"",C20,"") | BA153: =IF(BA152<>"",$C$11,"") | BB153: =IF($BB$143<>"",C20,"") | BC153: =IF($BC$143<>"",C20,"") | BD153: =IF($BD$143<>"",C20,"") | BE153: =IF($BE$143<>"",C20,"") | BF153: =IF($BF$143<>"",C20,"") | BG153: =IF($BG$143<>"",C20,"") | BH153: =IF($BH$143<>"",C20,"") | BI153: =IF($BI$143<>"",C20,"") | BJ153: =IF($BJ$143<>"",C20,"") | BK153: =IF($BK$143<>"",C20,"") | BL153: =IF($BL$143<>"",C20,"") | BM153: =IF($BM$143<>"",C20,"") | BN153: =IF($BN$143<>"",C20,"") | BO153: =IF($BO$143<>"",C20,"") | BP153: =IF($BP$143<>"",C20,"") | BQ153: =IF($BQ$143<>"",C20,"") | BR153: =IF($BR$143<>"",C20,"") | BS153: =IF($BS$143<>"",C20,"") | BT153: =IF($BT$143<>"",C20,"") | BU153: =IF($BU$143<>"",C20,"") | BV153: =IF($BV$143<>"",C20,"") | BW153: =IF($BW$143<>"",C20,"") | BX153: =IF($BX$143<>"",C20,"") | BY153: =IF($BY$143<>"",C20,"") | BZ153: =IF($BZ$143<>"",C20,"") | CA153: =IF($CA$143<>"",C20,"") | CB153: =IF($CB$143<>"",C20,"") | CC153: =IF($CC$143<>"",C20,"") | CD153: =IF($CD$143<>"",C20,"") | CE153: =IF($CE$143<>"",C20,"") | CF153: =IF($CF$143<>"",C20,"") | CG153: =IF($CG$143<>"",C20,"") | CH153: =IF($CH$143<>"",C20,"") | CI153: =IF($CI$143<>"",C20,"") | CJ153: =IF($CJ$143<>"",C20,"") | CK153: =IF($CK$143<>"",C20,"") | CL153: =IF($CL$143<>"",C20,"") | CM153: =IF($CM$143<>"",C20,"") | CN153: =IF($CN$143<>"",C20,"") | CO153: =IF($CO$143<>"",C20,"") | CP153: =IF($CP$143<>"",C20,"") | CQ153: =IF($CQ$143<>"",C20,"") | CR153: =IF($CR$143<>"",C20,"") | CS153: =IF(CS152<>"",B$16,"") | CT153: =IF($CT$143<>"",C20,"") | CU153: =IF($CU$143<>"",C20,"") | CV153: =IF($CV$143<>"",C20,"") | CW153: =IF($CW$143<>"",C20,"") | CX153: =IF($CX$11<>"",B152,"") | CY153: =IF($CY$143<>"",C20,"") | CZ153: =IF($CZ$143<>"",C20,"") | DA153: =IF($DA$143<>"",C20,"") | DB153: =IF($DB$143<>"",C20,"") | DC153: =IF($DC$143<>"",C20,"") | DD153: =IF($DD$143<>"",C20,"") | DE153: =IF($DE$143<>"",C20,"") | DF153: =IF($DF$143<>"",C20,"") | DG153: =IF($DG$143<>"",C20,"") | DH153: =IF($DH$143<>"",C20,"") | DI153: =IF($DI$143<>"",C20,"") | DJ153: =IF($DJ$143<>"",C20,"") | DK153: =IF($DK$143<>"",$C20,"") | DL153: =IF($DL$143<>"",$C20,"") | DM153: =IF($DM$143<>"",$C20,"") | DN153: =IF($DN$143<>"",$C20,"") | DO153: =IF($DO$143<>"",$C20,"") | DP153: =IF($DP$143<>"",$C20,"") | DQ153: =IF($DQ$143<>"",$C20,"") | DR153: =IF($DR$143<>"",$C20,"") | DS153: =IF($DS$143<>"",$C20,"") | DT153: =IF($DT$143<>"",$C20,"") | DU153: =IF($DU$143<>"",$C20,"") | DV153: =IF($DV$143<>"",$C20,"") | DY153: CAMISETA INFANTIL FEMININO | DZ153: GROMANN MATERIAL ELETRICO LTDA | EA153: AMUAGE | EB153: BALE | EC153: BOTTLE
A154: =IF(PEDIDO!C415<>"",PEDIDO!B415,"") | B154: =IF(PEDIDO!X415<>"",PEDIDO!X415,"") | C154: =IF(PEDIDO!AA415<>"",PEDIDO!AA415,"") | D154: =IF(PEDIDO!AD415<>"",PEDIDO!AD415,"") | E154: =IF(PEDIDO!AG415<>"",PEDIDO!AG415,"") | F154: =IF(PEDIDO!AJ415<>"",PEDIDO!AJ415,"") | J154: =IF(PEDIDO!C46<>"",PEDIDO!B46,"") | K154: =IF($K$143<>"",C21,"") | L154: =IF($L$143<>"",C21,"") | M154: =IF($M$143<>"",C21,"") | N154: =IF($N$143<>"",C21,"") | O154: =IF($O$143<>"",C21,"") | P154: =IF($P$143<>"",C21,"") | Q154: =IF($Q$143<>"",C21,"") | R154: =IF($R$143<>"",C21,"") | S154: =IF($S$143<>"",C21,"") | T154: =IF($T$143<>"",C21,"") | U154: =IF($U$143<>"",C21,"") | V154: =IF($V$143<>"",C21,"") | W154: =IF($W$143<>"",C21,"") | X154: =IF($X$143<>"",C21,"") | Y154: =IF($Y$143<>"",C21,"") | Z154: =IF($Z$143<>"",C21,"") | AA154: =IF($AA$143<>"",C21,"") | AB154: =IF($AB$143<>"",C21,"") | AC154: =IF($AC$143<>"",C21,"") | AD154: =IF($AD$143<>"",C21,"") | AE154: =IF($AE$143<>"",C21,"") | AF154: =IF($AF$143<>"",C21,"") | AG154: =IF($AG$143<>"",C21,"") | AH154: =IF($AH$143<>"",C21,"") | AI154: =IF($AI$143<>"",C21,"") | AJ154: =IF($AJ$143<>"",C21,"") | AK154: =IF($AK$143<>"",C21,"") | AL154: =IF($AL$143<>"",C21,"") | AM154: =IF($AM$143<>"",C21,"") | AN154: =IF($AN$143<>"",C21,"") | AO154: =IF($AO$143<>"",C21,"") | AP154: =IF($AP$143<>"",C21,"") | AQ154: =IF($AQ$143<>"",C21,"") | AR154: =IF($AR$143<>"",C21,"") | AS154: =IF($AS$143<>"",C21,"") | AT154: =IF($AT$143<>"",C21,"") | AU154: =IF($AU$143<>"",C21,"") | AV154: =IF($AV$143<>"",C21,"") | AW154: =IF($AW$143<>"",C21,"") | AX154: =IF($AX$143<>"",C21,"") | AY154: =IF($AY$143<>"",C21,"") | AZ154: =IF($AZ$143<>"",C21,"") | BA154: =IF(BA153<>"",$C$11,"") | BB154: =IF($BB$143<>"",C21,"") | BC154: =IF($BC$143<>"",C21,"") | BD154: =IF($BD$143<>"",C21,"") | BE154: =IF($BE$143<>"",C21,"") | BF154: =IF($BF$143<>"",C21,"") | BG154: =IF($BG$143<>"",C21,"") | BH154: =IF($BH$143<>"",C21,"") | BI154: =IF($BI$143<>"",C21,"") | BJ154: =IF($BJ$143<>"",C21,"") | BK154: =IF($BK$143<>"",C21,"") | BL154: =IF($BL$143<>"",C21,"") | BM154: =IF($BM$143<>"",C21,"") | BN154: =IF($BN$143<>"",C21,"") | BO154: =IF($BO$143<>"",C21,"") | BP154: =IF($BP$143<>"",C21,"") | BQ154: =IF($BQ$143<>"",C21,"") | BR154: =IF($BR$143<>"",C21,"") | BS154: =IF($BS$143<>"",C21,"") | BT154: =IF($BT$143<>"",C21,"") | BU154: =IF($BU$143<>"",C21,"") | BV154: =IF($BV$143<>"",C21,"") | BW154: =IF($BW$143<>"",C21,"") | BX154: =IF($BX$143<>"",C21,"") | BY154: =IF($BY$143<>"",C21,"") | BZ154: =IF($BZ$143<>"",C21,"") | CA154: =IF($CA$143<>"",C21,"") | CB154: =IF($CB$143<>"",C21,"") | CC154: =IF($CC$143<>"",C21,"") | CD154: =IF($CD$143<>"",C21,"") | CE154: =IF($CE$143<>"",C21,"") | CF154: =IF($CF$143<>"",C21,"") | CG154: =IF($CG$143<>"",C21,"") | CH154: =IF($CH$143<>"",C21,"") | CI154: =IF($CI$143<>"",C21,"") | CJ154: =IF($CJ$143<>"",C21,"") | CK154: =IF($CK$143<>"",C21,"") | CL154: =IF($CL$143<>"",C21,"") | CM154: =IF($CM$143<>"",C21,"") | CN154: =IF($CN$143<>"",C21,"") | CO154: =IF($CO$143<>"",C21,"") | CP154: =IF($CP$143<>"",C21,"") | CQ154: =IF($CQ$143<>"",C21,"") | CR154: =IF($CR$143<>"",C21,"") | CS154: =IF(CS153<>"",B$16,"") | CT154: =IF($CT$143<>"",C21,"") | CU154: =IF($CU$143<>"",C21,"") | CV154: =IF($CV$143<>"",C21,"") | CW154: =IF($CW$143<>"",C21,"") | CX154: =IF($CX$11<>"",B153,"") | CY154: =IF($CY$143<>"",C21,"") | CZ154: =IF($CZ$143<>"",C21,"") | DA154: =IF($DA$143<>"",C21,"") | DB154: =IF($DB$143<>"",C21,"") | DC154: =IF($DC$143<>"",C21,"") | DD154: =IF($DD$143<>"",C21,"") | DE154: =IF($DE$143<>"",C21,"") | DF154: =IF($DF$143<>"",C21,"") | DG154: =IF($DG$143<>"",C21,"") | DH154: =IF($DH$143<>"",C21,"") | DI154: =IF($DI$143<>"",C21,"") | DJ154: =IF($DJ$143<>"",C21,"") | DK154: =IF($DK$143<>"",$C21,"") | DL154: =IF($DL$143<>"",$C21,"") | DM154: =IF($DM$143<>"",$C21,"") | DN154: =IF($DN$143<>"",$C21,"") | DO154: =IF($DO$143<>"",$C21,"") | DP154: =IF($DP$143<>"",$C21,"") | DQ154: =IF($DQ$143<>"",$C21,"") | DR154: =IF($DR$143<>"",$C21,"") | DS154: =IF($DS$143<>"",$C21,"") | DT154: =IF($DT$143<>"",$C21,"") | DU154: =IF($DU$143<>"",$C21,"") | DV154: =IF($DV$143<>"",$C21,"") | DY154: CAMISETA INFANTIL MASCULINO | DZ154: OESTE MED | EA154: AN | EB154: BALI | EC154: BOX LULUCA
A155: =IF(PEDIDO!C416<>"",PEDIDO!B416,"") | B155: =IF(PEDIDO!X416<>"",PEDIDO!X416,"") | C155: =IF(PEDIDO!AA416<>"",PEDIDO!AA416,"") | D155: =IF(PEDIDO!AD416<>"",PEDIDO!AD416,"") | E155: =IF(PEDIDO!AG416<>"",PEDIDO!AG416,"") | F155: =IF(PEDIDO!AJ416<>"",PEDIDO!AJ416,"") | J155: =IF(PEDIDO!C47<>"",PEDIDO!B47,"") | K155: =IF($K$143<>"",C22,"") | L155: =IF($L$143<>"",C22,"") | M155: =IF($M$143<>"",C22,"") | N155: =IF($N$143<>"",C22,"") | O155: =IF($O$143<>"",C22,"") | P155: =IF($P$143<>"",C22,"") | Q155: =IF($Q$143<>"",C22,"") | R155: =IF($R$143<>"",C22,"") | S155: =IF($S$143<>"",C22,"") | T155: =IF($T$143<>"",C22,"") | U155: =IF($U$143<>"",C22,"") | V155: =IF($V$143<>"",C22,"") | W155: =IF($W$143<>"",C22,"") | X155: =IF($X$143<>"",C22,"") | Y155: =IF($Y$143<>"",C22,"") | Z155: =IF($Z$143<>"",C22,"") | AA155: =IF($AA$143<>"",C22,"") | AB155: =IF($AB$143<>"",C22,"") | AC155: =IF($AC$143<>"",C22,"") | AD155: =IF($AD$143<>"",C22,"") | AE155: =IF($AE$143<>"",C22,"") | AF155: =IF($AF$143<>"",C22,"") | AG155: =IF($AG$143<>"",C22,"") | AH155: =IF($AH$143<>"",C22,"") | AI155: =IF($AI$143<>"",C22,"") | AJ155: =IF($AJ$143<>"",C22,"") | AK155: =IF($AK$143<>"",C22,"") | AL155: =IF($AL$143<>"",C22,"") | AM155: =IF($AM$143<>"",C22,"") | AN155: =IF($AN$143<>"",C22,"") | AO155: =IF($AO$143<>"",C22,"") | AP155: =IF($AP$143<>"",C22,"") | AQ155: =IF($AQ$143<>"",C22,"") | AR155: =IF($AR$143<>"",C22,"") | AS155: =IF($AS$143<>"",C22,"") | AT155: =IF($AT$143<>"",C22,"") | AU155: =IF($AU$143<>"",C22,"") | AV155: =IF($AV$143<>"",C22,"") | AW155: =IF($AW$143<>"",C22,"") | AX155: =IF($AX$143<>"",C22,"") | AY155: =IF($AY$143<>"",C22,"") | AZ155: =IF($AZ$143<>"",C22,"") | BA155: =IF(BA154<>"",$C$11,"") | BB155: =IF($BB$143<>"",C22,"") | BC155: =IF($BC$143<>"",C22,"") | BD155: =IF($BD$143<>"",C22,"") | BE155: =IF($BE$143<>"",C22,"") | BF155: =IF($BF$143<>"",C22,"") | BG155: =IF($BG$143<>"",C22,"") | BH155: =IF($BH$143<>"",C22,"") | BI155: =IF($BI$143<>"",C22,"") | BJ155: =IF($BJ$143<>"",C22,"") | BK155: =IF($BK$143<>"",C22,"") | BL155: =IF($BL$143<>"",C22,"") | BM155: =IF($BM$143<>"",C22,"") | BN155: =IF($BN$143<>"",C22,"") | BO155: =IF($BO$143<>"",C22,"") | BP155: =IF($BP$143<>"",C22,"") | BQ155: =IF($BQ$143<>"",C22,"") | BR155: =IF($BR$143<>"",C22,"") | BS155: =IF($BS$143<>"",C22,"") | BT155: =IF($BT$143<>"",C22,"") | BU155: =IF($BU$143<>"",C22,"") | BV155: =IF($BV$143<>"",C22,"") | BW155: =IF($BW$143<>"",C22,"") | BX155: =IF($BX$143<>"",C22,"") | BY155: =IF($BY$143<>"",C22,"") | BZ155: =IF($BZ$143<>"",C22,"") | CA155: =IF($CA$143<>"",C22,"") | CB155: =IF($CB$143<>"",C22,"") | CC155: =IF($CC$143<>"",C22,"") | CD155: =IF($CD$143<>"",C22,"") | CE155: =IF($CE$143<>"",C22,"") | CF155: =IF($CF$143<>"",C22,"") | CG155: =IF($CG$143<>"",C22,"") | CH155: =IF($CH$143<>"",C22,"") | CI155: =IF($CI$143<>"",C22,"") | CJ155: =IF($CJ$143<>"",C22,"") | CK155: =IF($CK$143<>"",C22,"") | CL155: =IF($CL$143<>"",C22,"") | CM155: =IF($CM$143<>"",C22,"") | CN155: =IF($CN$143<>"",C22,"") | CO155: =IF($CO$143<>"",C22,"") | CP155: =IF($CP$143<>"",C22,"") | CQ155: =IF($CQ$143<>"",C22,"") | CR155: =IF($CR$143<>"",C22,"") | CS155: =IF(CS154<>"",B$16,"") | CT155: =IF($CT$143<>"",C22,"") | CU155: =IF($CU$143<>"",C22,"") | CV155: =IF($CV$143<>"",C22,"") | CW155: =IF($CW$143<>"",C22,"") | CX155: =IF($CX$11<>"",B154,"") | CY155: =IF($CY$143<>"",C22,"") | CZ155: =IF($CZ$143<>"",C22,"") | DA155: =IF($DA$143<>"",C22,"") | DB155: =IF($DB$143<>"",C22,"") | DC155: =IF($DC$143<>"",C22,"") | DD155: =IF($DD$143<>"",C22,"") | DE155: =IF($DE$143<>"",C22,"") | DF155: =IF($DF$143<>"",C22,"") | DG155: =IF($DG$143<>"",C22,"") | DH155: =IF($DH$143<>"",C22,"") | DI155: =IF($DI$143<>"",C22,"") | DJ155: =IF($DJ$143<>"",C22,"") | DK155: =IF($DK$143<>"",$C22,"") | DL155: =IF($DL$143<>"",$C22,"") | DM155: =IF($DM$143<>"",$C22,"") | DN155: =IF($DN$143<>"",$C22,"") | DO155: =IF($DO$143<>"",$C22,"") | DP155: =IF($DP$143<>"",$C22,"") | DQ155: =IF($DQ$143<>"",$C22,"") | DR155: =IF($DR$143<>"",$C22,"") | DS155: =IF($DS$143<>"",$C22,"") | DT155: =IF($DT$143<>"",$C22,"") | DU155: =IF($DU$143<>"",$C22,"") | DV155: =IF($DV$143<>"",$C22,"") | DY155: CAMISETA MASCULINO | DZ155: JUSSAMA MOTORES E FERRAMENTAS | EA155: ANA AMARAL | EB155: BALI SORBET | EC155: BOX REBECCA BONBON
A156: =IF(PEDIDO!C417<>"",PEDIDO!B417,"") | B156: =IF(PEDIDO!X417<>"",PEDIDO!X417,"") | C156: =IF(PEDIDO!AA417<>"",PEDIDO!AA417,"") | D156: =IF(PEDIDO!AD417<>"",PEDIDO!AD417,"") | E156: =IF(PEDIDO!AG417<>"",PEDIDO!AG417,"") | F156: =IF(PEDIDO!AJ417<>"",PEDIDO!AJ417,"") | J156: =IF(PEDIDO!C48<>"",PEDIDO!B48,"") | K156: =IF($K$143<>"",C23,"") | L156: =IF($L$143<>"",C23,"") | M156: =IF($M$143<>"",C23,"") | N156: =IF($N$143<>"",C23,"") | O156: =IF($O$143<>"",C23,"") | P156: =IF($P$143<>"",C23,"") | Q156: =IF($Q$143<>"",C23,"") | R156: =IF($R$143<>"",C23,"") | S156: =IF($S$143<>"",C23,"") | T156: =IF($T$143<>"",C23,"") | U156: =IF($U$143<>"",C23,"") | V156: =IF($V$143<>"",C23,"") | W156: =IF($W$143<>"",C23,"") | X156: =IF($X$143<>"",C23,"") | Y156: =IF($Y$143<>"",C23,"") | Z156: =IF($Z$143<>"",C23,"") | AA156: =IF($AA$143<>"",C23,"") | AB156: =IF($AB$143<>"",C23,"") | AC156: =IF($AC$143<>"",C23,"") | AD156: =IF($AD$143<>"",C23,"") | AE156: =IF($AE$143<>"",C23,"") | AF156: =IF($AF$143<>"",C23,"") | AG156: =IF($AG$143<>"",C23,"") | AH156: =IF($AH$143<>"",C23,"") | AI156: =IF($AI$143<>"",C23,"") | AJ156: =IF($AJ$143<>"",C23,"") | AK156: =IF($AK$143<>"",C23,"") | AL156: =IF($AL$143<>"",C23,"") | AM156: =IF($AM$143<>"",C23,"") | AN156: =IF($AN$143<>"",C23,"") | AO156: =IF($AO$143<>"",C23,"") | AP156: =IF($AP$143<>"",C23,"") | AQ156: =IF($AQ$143<>"",C23,"") | AR156: =IF($AR$143<>"",C23,"") | AS156: =IF($AS$143<>"",C23,"") | AT156: =IF($AT$143<>"",C23,"") | AU156: =IF($AU$143<>"",C23,"") | AV156: =IF($AV$143<>"",C23,"") | AW156: =IF($AW$143<>"",C23,"") | AX156: =IF($AX$143<>"",C23,"") | AY156: =IF($AY$143<>"",C23,"") | AZ156: =IF($AZ$143<>"",C23,"") | BA156: =IF(BA155<>"",$C$11,"") | BB156: =IF($BB$143<>"",C23,"") | BC156: =IF($BC$143<>"",C23,"") | BD156: =IF($BD$143<>"",C23,"") | BE156: =IF($BE$143<>"",C23,"") | BF156: =IF($BF$143<>"",C23,"") | BG156: =IF($BG$143<>"",C23,"") | BH156: =IF($BH$143<>"",C23,"") | BI156: =IF($BI$143<>"",C23,"") | BJ156: =IF($BJ$143<>"",C23,"") | BK156: =IF($BK$143<>"",C23,"") | BL156: =IF($BL$143<>"",C23,"") | BM156: =IF($BM$143<>"",C23,"") | BN156: =IF($BN$143<>"",C23,"") | BO156: =IF($BO$143<>"",C23,"") | BP156: =IF($BP$143<>"",C23,"") | BQ156: =IF($BQ$143<>"",C23,"") | BR156: =IF($BR$143<>"",C23,"") | BS156: =IF($BS$143<>"",C23,"") | BT156: =IF($BT$143<>"",C23,"") | BU156: =IF($BU$143<>"",C23,"") | BV156: =IF($BV$143<>"",C23,"") | BW156: =IF($BW$143<>"",C23,"") | BX156: =IF($BX$143<>"",C23,"") | BY156: =IF($BY$143<>"",C23,"") | BZ156: =IF($BZ$143<>"",C23,"") | CA156: =IF($CA$143<>"",C23,"") | CB156: =IF($CB$143<>"",C23,"") | CC156: =IF($CC$143<>"",C23,"") | CD156: =IF($CD$143<>"",C23,"") | CE156: =IF($CE$143<>"",C23,"") | CF156: =IF($CF$143<>"",C23,"") | CG156: =IF($CG$143<>"",C23,"") | CH156: =IF($CH$143<>"",C23,"") | CI156: =IF($CI$143<>"",C23,"") | CJ156: =IF($CJ$143<>"",C23,"") | CK156: =IF($CK$143<>"",C23,"") | CL156: =IF($CL$143<>"",C23,"") | CM156: =IF($CM$143<>"",C23,"") | CN156: =IF($CN$143<>"",C23,"") | CO156: =IF($CO$143<>"",C23,"") | CP156: =IF($CP$143<>"",C23,"") | CQ156: =IF($CQ$143<>"",C23,"") | CR156: =IF($CR$143<>"",C23,"") | CS156: =IF(CS155<>"",B$16,"") | CT156: =IF($CT$143<>"",C23,"") | CU156: =IF($CU$143<>"",C23,"") | CV156: =IF($CV$143<>"",C23,"") | CW156: =IF($CW$143<>"",C23,"") | CX156: =IF($CX$11<>"",B155,"") | CY156: =IF($CY$143<>"",C23,"") | CZ156: =IF($CZ$143<>"",C23,"") | DA156: =IF($DA$143<>"",C23,"") | DB156: =IF($DB$143<>"",C23,"") | DC156: =IF($DC$143<>"",C23,"") | DD156: =IF($DD$143<>"",C23,"") | DE156: =IF($DE$143<>"",C23,"") | DF156: =IF($DF$143<>"",C23,"") | DG156: =IF($DG$143<>"",C23,"") | DH156: =IF($DH$143<>"",C23,"") | DI156: =IF($DI$143<>"",C23,"") | DJ156: =IF($DJ$143<>"",C23,"") | DK156: =IF($DK$143<>"",$C23,"") | DL156: =IF($DL$143<>"",$C23,"") | DM156: =IF($DM$143<>"",$C23,"") | DN156: =IF($DN$143<>"",$C23,"") | DO156: =IF($DO$143<>"",$C23,"") | DP156: =IF($DP$143<>"",$C23,"") | DQ156: =IF($DQ$143<>"",$C23,"") | DR156: =IF($DR$143<>"",$C23,"") | DS156: =IF($DS$143<>"",$C23,"") | DT156: =IF($DT$143<>"",$C23,"") | DU156: =IF($DU$143<>"",$C23,"") | DV156: =IF($DV$143<>"",$C23,"") | DY156: CAMISETA MASCULINO JUVENIL | DZ156: JF PAPELARIA | EA156: ANA BELLA | EB156: BALI VEGAS | EC156: BOXER
